Workbook
Name _GoBack: '4.1 Design & Construction'!$A$10

Sheet 2030
C2: Global | D2: LAyC | E2: Argentina
B4: 1990 | C4: 756 | D4: 709 | E4: 612
B6: 2000 | C6: 711 | D6: 652 | E6: 601
B8: 2010 | C8: 634 | D8: 603 | E8: 570
B10: 2020 | C10: 624 | D10: 589 | E10: 507
C11: Meta No Condicionada | D11: Meta Condicionada
B12: 2030 | D12: 500

Sheet LB
B2: ESCENARIO EMISIONES 2020 - 2050
B4: Las emisiones proyectadas al año 2050 se calculan a partir de la línea base de emisiones al año 2020(*), y el incremento de producción de cemento al 2050 sin eficiencias (58%), según escenario BAU (Business as Usual), que significa producir y utilizar el cemento bajo las mismas condiciones actuales en el 2050.
B8: Las emisiones LB2020 fueron 6,9 MtCO2e, considerando emisiones directas (6,5 MtCO2e) e indirectas del uso de energía eléctrica (0,4 MtCO2e). Al año 2050, se consideró un aumento del 58% del consumo de cemento, que implica llegar a 19,5 Mt, lo que significaría 10,7 MtCO2e de emisiones totales BAU.
B12: AUMENTO DEMANDA | L12: PROYECCION EMISIONES TOTALES BAU
B48: Aumento Demanda | C48: 2020 | D48: 2030 | E48: 2040 | F48: 2050 | L48: Emisiones Totales | M48: 2020 | N48: 2030 | O48: 2040 | P48: 2050
B49: FICEM | C49: 0 | D49: 20 | E49: =AVERAGE(D49,F49) -> 45 | F49: 70 | L49: FICEM | M49: 126 | N49: 151 | O49: =AVERAGE(N49,P49) -> 182.5 | P49: 214
B50: Perú | C50: 0 | D50: 20 | E50: =AVERAGE(D50,F50) -> 50 | F50: 80 | L50: Perú | M50: 6.7 | N50: 8.1 | O50: =AVERAGE(N50,P50) -> 10.15 | P50: 12.2
B51: Colombia | C51: 0 | D51: 20 | E51: =AVERAGE(D51,F51) -> 35 | F51: 50 | L51: Colombia | M51: 8.4 | N51: 9.5 | O51: =AVERAGE(N51,P51) -> 11.1 | P51: 12.7 | S51: SE DEJA COMPARACION CON PAISES
B52: Chile | C52: 0 | D52: 10 | E52: =AVERAGE(D52,F52) -> 25 | F52: 40 | L52: Chile | M52: 3.8 | N52: 4 | O52: =AVERAGE(N52,P52) -> 4.35 | P52: 4.7 | S52: FICEM SE CAMBIA POR COMPAÑÍA
B53: ARGENTINA | C53: =+M60 -> 0 | D53: =+N60 -> 18 | E53: =+AVERAGE(D53,F53) -> 36.5 | F53: =+P60 -> 55 | L53: Argentina | M53: =+M63 -> 6.8665 | N53: =+N63 -> 8.10247 | O53: =+O63 -> 9.3130537 | P53: =+P63 -> 10.643075 | S53: ARGENTINA SE SUMA INDEPENDIENTE
B54: GCCA Roadmap | C54: 0 | D54: 14.545455 | E54: =AVERAGE(D54,F54) -> 33.272727 | F54: 52
L56: EMISIONES ESCENARIO BAU | M56: 2020 | N56: 2030 | O56: 2040 | P56: 2050
L57: Clínker BAU [Mt] | M57: 8.5 | N57: =+M57*(1+N60/100) -> 10.03 | O57: =+AVERAGE(N57,P57) -> 11.6025 | P57: =+M57*(1+P60/100) -> 13.175
L58: Cemento BAU [Mt] | M58: 12.5 | N58: =+M58*(1+N60/100) -> 14.75 | O58: =+AVERAGE(N58,P58) -> 17.0625 | P58: =+M58*(1+P60/100) -> 19.375
L59: FE Clinker BAU [kgCO2/tck] | M59: 749 | N59: 749 | O59: =+AVERAGE(N59,P59) -> 749 | P59: 749
L60: Aumento Demanda Escenario BAU [%] | M60: 0 | N60: 18 | O60: =+AVERAGE(N60,P60) -> 36.5 | P60: 55
L61: Emisiones Directas Clinker BAU [MtCO2] | M61: =+M59*M57/1000 -> 6.3665 | N61: =+N59*N57/1000 -> 7.51247 | O61: =+O59*O57/1000 -> 8.6902725 | P61: =+P59*P57/1000 -> 9.868075
L62: Emisiones Alcance 2 BAU [MTCO2] | M62: 0.5 | N62: 0.3 | O62: =+O60*O58/1000 -> 0.62278125 | P62: 0.6
L63: Emisiones Totales BAU [MTCO2] | M63: =+M62+M61 -> 6.8665 | N63: =+M63*(1+N60/100) -> 8.10247 | O63: =+O62+O61 -> 9.3130537 | P63: =+M63*(1+P60/100) -> 10.643075

Sheet Eje 1-1
C2: DISEÑO Y CONSTRUCCION
C4: Aumentar la eficiencia en el uso de concreto en la construcción, a través de la inclusión de etapas y actividades aguas arriba y aguas abajo de la industria del cemento y concreto – como diseño, planificación, especificación y construcción – significa, entre otros, no sobre utilizar concreto, si no el volumen más bajo posible que cumpla con los requisitos de aplicación sin comprometer durabilidad y seguridad.
C9: Algunas aplicaciones son: elementos de fachada tipo sándwich; diseño con AI y optimización elementos estructurales; cálculos de diseño lineal/elásticos hasta cálculos basados en plasticidad, reutilización residuos de concreto, entre otros. Proyectistas, diseñadores, especificadores, inspectores y directores de obra, contratistas y el Poder Público tienen un rol central para su despliegue.

Sheet Eje 1-2
B2: EFICIENCIA PRODUCCION CONCRETO
B4: La optimización en la producción de concreto, implica hacer más eficiente el uso del cemento en el concreto, para una prestación de referencia, reduciendo, además, la huella de carbono del concreto. Esta mejora se debe lograr sin comprometer la calidad del producto.
B7: Actualmente, la composición de la fabricación del concreto en LAC, se distribuye de la siguiente manera: 28% de premezclado, 64% de cemento en sacos; 5% de mezcla en silos de obra; 3% de prefabricados. Se proyecta, que para el año 2050, la distribución sea de la siguiente forma: 45% de premezclado, 40% de cemento en sacos; 5% de mezcla en silos de obra; 10% de prefabricados; aumentando así la industrialización en este proceso.
B11: % CEMENTO EN SACOS | K11: % READYMIX | U11: % CEMENTO EN SILOS OBRA | AF11: % PREFABRICADOS
B47: % Cemento Sacos | C47: 2020 | D47: 2030 | E47: 2040 | F47: 2050 | L47: % Readymix | M47: 2020 | N47: 2030 | O47: 2040 | P47: 2050 | U47: % Silos | V47: 2020 | W47: 2030 | X47: 2040 | Y47: 2050 | AF47: % Prefabricados | AG47: 2020 | AH47: 2030 | AI47: 2040 | AJ47: 2050
B48: FICEM | C48: 64 | D48: 59 | E48: =AVERAGE(D48,F48) -> 49.5 | F48: 40 | L48: FICEM | M48: 28 | N48: 33 | O48: =AVERAGE(N48,P48) -> 39 | P48: 45 | U48: FICEM | V48: 5 | W48: 5 | X48: =AVERAGE(W48,Y48) -> 5 | Y48: 5 | AF48: FICEM | AG48: 3 | AH48: 3 | AI48: =AVERAGE(AH48,AJ48) -> 6.5 | AJ48: 10
B49: Perú | C49: 78.1 | D49: 75 | E49: =+AVERAGE(D49,F49) -> 72.5 | F49: 70 | L49: Perú | M49: 17 | N49: 24 | O49: =+AVERAGE(N49,P49) -> 29 | P49: 34 | U49: Perú | V49: 3 | W49: 6 | X49: =+AVERAGE(W49,Y49) -> 6.5 | Y49: 7 | AF49: Perú | AG49: 1 | AH49: 2 | AI49: =+AVERAGE(AH49,AJ49) -> 3 | AJ49: 4
B50: Colombia | C50: 69 | D50: 64 | E50: =AVERAGE(D50,F50) -> 57 | F50: 50 | L50: Colombia | M50: 23 | N50: 26 | O50: =AVERAGE(N50,P50) -> 30.5 | P50: 35 | U50: Colombia | V50: 6 | W50: 5 | X50: =AVERAGE(W50,Y50) -> 7.5 | Y50: 10 | AF50: Colombia | AG50: 3 | AH50: 5 | AI50: =AVERAGE(AH50,AJ50) -> 5 | AJ50: 5
B51: Chile | C51: 30 | D51: 25 | E51: =AVERAGE(D51,F51) -> 17.5 | F51: 10 | L51: Chile | M51: 55 | N51: 60 | O51: =AVERAGE(N51,P51) -> 65 | P51: 70 | U51: Chile | V51: 10 | W51: 5 | X51: =AVERAGE(W51,Y51) -> 7.5 | Y51: 10 | AF51: Chile | AG51: 5 | AH51: 10 | AI51: =AVERAGE(AH51,AJ51) -> 12.5 | AJ51: 15
B52: ARGENTINA | C52: 53 | D52: 47 | E52: =AVERAGE(D52,F52) -> 45 | F52: 43 | L52: ARGENTINA | M52: 35 | N52: 39 | O52: =AVERAGE(N52,P52) -> 40.5 | P52: 42 | U52: ARGENTINA | V52: 7 | W52: 7 | X52: =AVERAGE(W52,Y52) -> 7 | Y52: 7 | AF52: ARGENTINA | AG52: 5 | AH52: 7 | AI52: =AVERAGE(AH52,AJ52) -> 7 | AJ52: 7
C54: 2020 | D54: 2030 | E54: 2040 | F54: 2050
B55: Sacos | C55: 53.3 | D55: 47 | E55: 45 | F55: 43
B56: Factor Clínker | C56: 58 | D56: 55 | E56: =+AVERAGE(D56,F56) -> 53.5 | F56: 52 | L56: COMPOSICION CONCRETO | M56: 2020 | N56: 2030 | O56: 2040 | P56: 2050 | U56: % y FCk por Canal | V56: 2020 | W56: 2030 | X56: 2040 | Y56: 2050
B57: Readymix | C57: 35 | D57: 39 | E57: 41 | F57: 42 | L57: Volumen Total Concreto [Mm3] | M57: 48.4 | N57: 57.1 | O57: =+AVERAGE(N57,P57) -> 66.05 | P57: 75 | U57: % Readymix | V57: 35 | W57: 39 | X57: 41 | Y57: 42
B58: Factor Clínker | C58: 78 | D58: 75 | E58: =+AVERAGE(D58,F58) -> 72 | F58: 69 | L58: Participacion Premezclado [%] | M58: 0.35 | N58: 0.39 | O58: =+AVERAGE(N58,P58) -> 0.445 | P58: 0.5 | U58: FCk
B59: Silos Obra | C59: 7 | D59: 7 | E59: 7 | F59: 7 | L59: Participacion Sacos [%] | M59: 0.48 | N59: 0.47 | O59: =AVERAGE(N59,P59) -> 0.385 | P59: 0.3 | U59: Sacos
B60: Factor Clínker | C60: 77 | D60: 72 | E60: =+AVERAGE(D60,F60) -> 69.5 | F60: 67 | L60: Participacion Silos [%] | M60: 0.06 | N60: 0.07 | O60: =+AVERAGE(N60,P60) -> 0.085 | P60: 0.1 | U60: FCk
B61: Precast | C61: 5 | D61: 7 | E61: 7 | F61: 7 | L61: Participacion Prefabricados [%] | M61: 0.08 | N61: 0.07 | O61: =+AVERAGE(N61,P61) -> 0.085 | P61: 0.1 | U61: Silos
B62: Factor Clínker | C62: 80 | D62: 75 | E62: =+AVERAGE(D62,F62) -> 71 | F62: 67 | L62: CEMENTO EN CONCRETO [kgCem/m3) | M62: 380 | N62: 375 | O62: =+AVERAGE(N62,P62) -> 360.5 | P62: 346 | U62: FCk
U63: Precast
C64: =+(C55*C56+C57*C58+C59*C60+C61*C62)/100 -> 67.604 | D64: =+(D55*D56+D57*D58+D59*D60+D61*D62)/100 -> 65.39 | E64: =+(E55*E56+E57*E58+E59*E60+E61*E62)/100 -> 63.43 | F64: =+(F55*F56+F57*F58+F59*F60+F61*F62)/100 -> 60.72 | U64: FCk

Sheet Eje 2
B5: CEMENTO EN CONCRETO
O38: CEMENTO [Mt] | P38: 2020 | Q38: 2030 | R38: 2040 | S38: 2050
C39: CEMENTO EN CONCRETO | D39: 2020 | E39: 2030 | F39: 2040 | G39: 2050 | O39: CEMENTO BAU | P39: 12.5 | Q39: 14.8 | R39: =+AVERAGE(Q39,S39) -> 17.1 | S39: 19.4
C40: FICEM | D40: 451 | E40: 447 | F40: =+AVERAGE(E40,G40) -> 401.5 | G40: 356 | O40: CEMENTO NZA | P40: 12.5 | Q40: 14.1 | R40: =+AVERAGE(Q40,S40) -> 15.7 | S40: 17.3
C41: Perú | D41: 366 | E41: 322 | F41: =+AVERAGE(E41,G41) -> 316 | G41: 310
C42: Colombia | D42: 366 | E42: 333 | F42: =+AVERAGE(E42,G42) -> 316.5 | G42: 300 | O42: CONCRETO
C43: Chile | D43: 354 | E43: 347 | F43: =+AVERAGE(E43,G43) -> 336.5 | G43: 326 | O43: Mm3 | P43: 34 | Q43: 46 | R43: =+AVERAGE(Q43,S43) -> 51.5 | S43: 57
C44: ARGENTINA | D44: 381.5 | E44: 377.1 | F44: =+AVERAGE(E44,G44) -> 356.05 | G44: 335
O45: CEMENTO/CONCRETO
O46: kgCem/m3 | P46: =+P40/P43*1000 -> 367.64706 | Q46: =+Q40/Q43*1000 -> 306.52174 | R46: =+R40/R43*1000 -> 304.85437 | S46: =+S40/S43*1000 -> 303.50877

Sheet Eje 3
C3: CEMENTO Y ADICIONES
B5: El parámetro más importante para determinar las emisiones de CO2e del cemento es su contenido o porcentaje de clínker, que se conoce como factor clínker. A nivel global, según datos reportados en GNR al año 2022, el factor clínker fue de 77%, el cual junto al yeso (5%), caliza (9%), puzolana (2%), escoria (3%); cenizas (3%) y otras adiciones (1%), forman el cemento.
B9: En LAC, el porcentaje de clínker es de 67%, 10 puntos porcentuales bajo el valor global, debido a la mayor disponibilidad de adiciones como las puzolanas, escoria y cenizas en nuestra región lo que resulta en un producto con menores emisiones de CO2e. Los porcentajes de composición del cemento en LAC son los siguientes: yeso (6%), caliza (11%), puzolana (11%), escoria (2%); cenizas (2%) y otras adiciones (1%) y clínker (67%).
B13: FACTOR CLINKER | M13: FACTOR CLINKER POR CANAL ARGENTINA | W13: PARTICIPACION POR CANAL
M46: FACTOR CLINKER CANAL | N46: 2020 | O46: 2030 | P46: 2040 | Q46: 2050 | X46: CANAL | Y46: 2020 | Z46: 2030 | AA46: 2040 | AB46: 2050
C47: Factor Clinker | D47: 2020 | E47: 2030 | F47: 2040 | G47: 2050 | M47: FCk Readymix | N47: 0.78 | O47: 0.75 | P47: =+AVERAGE(O47,Q47) -> 0.72 | Q47: 0.69 | X47: Concreto Mm3 | Y47: 33 | Z47: 38 | AA47: =+AVERAGE(Z47,AB47) -> 44 | AB47: 50
C48: FICEM | D48: 67 | E48: 66 | F48: =AVERAGE(E48,G48) -> 63 | G48: 60 | M48: FCk Sacos | N48: 0.58 | O48: 0.55 | P48: =+AVERAGE(O48,Q48) -> 0.535 | Q48: 0.52 | X48: Premezclado [%] | Y48: 0.35 | Z48: 0.39 | AA48: =+AVERAGE(Z48,AB48) -> 0.405 | AB48: 0.42
C49: Perú | D49: 75 | E49: 70 | F49: =AVERAGE(E49,G49) -> 68.5 | G49: 67 | M49: FCk Silos | N49: 0.77 | O49: 0.72 | P49: =AVERAGE(O49,Q49) -> 0.695 | Q49: 0.67 | X49: Sacos [%] | Y49: 0.53 | Z49: 0.47 | AA49: =+AVERAGE(Z49,AB49) -> 0.45 | AB49: 0.43
C50: Colombia | D50: 69 | E50: 64 | F50: =AVERAGE(E50,G50) -> 59.5 | G50: 55 | M50: FCk Precast | N50: 0.8 | O50: 0.75 | P50: =AVERAGE(O50,Q50) -> 0.71 | Q50: 0.67 | X50: Silos [%] | Y50: 0.07 | Z50: 0.07 | AA50: =AVERAGE(Z50,AB50) -> 0.07 | AB50: 0.07
C51: Chile | D51: 71 | E51: 68 | F51: =AVERAGE(E51,G51) -> 65.5 | G51: 63 | X51: Prefabricados [%] | Y51: 0.05 | Z51: 0.07 | AA51: =AVERAGE(Z51,AB51) -> 0.07 | AB51: 0.07
C52: ARGENTINA | D52: 68 | E52: 65 | F52: =AVERAGE(E52,G52) -> 63 | G52: 61 | M52: MATERIAS PRIMAS CEMENTO | N52: 2020 | O52: 2030 | P52: 2040 | Q52: 2050
C53: GCCA Roadmap | D53: 63 | E53: 58 | F53: =AVERAGE(E53,G53) -> 56 | G53: 54 | M53: Clínker [%] | N53: 0.67 | O53: 0.65 | P53: =+AVERAGE(O53,Q53) -> 0.63 | Q53: 0.61
M54: Yeso [%] | N54: 0.05 | O54: 0.05 | P54: =+AVERAGE(O54,Q54) -> 0.05 | Q54: 0.05
M55: Caliza [%] | N55: 0.17 | O55: 0.15 | P55: =+AVERAGE(O55,Q55) -> 0.175 | Q55: 0.2
M56: Escoria Alto Horno [%] | N56: 0.05 | O56: 0.04 | P56: =+AVERAGE(O56,Q56) -> 0.045 | Q56: 0.05
C57: Pertic | M57: Cenizas Volantes [%] | N57: 0 | O57: 0.02 | P57: =+AVERAGE(O57,Q57) -> 0.01 | Q57: 0
M58: Puzolana Natural [%] | N58: 0.05 | O58: 0.05 | P58: =+AVERAGE(O58,Q58) -> 0.04 | Q58: 0.03
M59: Arcillas Calcinadas [%] | N59: 0.01 | O59: 0.04 | P59: =+AVERAGE(O59,Q59) -> 0.045 | Q59: 0.05
M60: Otras Adiciones [%] | N60: 0 | O60: 0.01 | P60: =+AVERAGE(O60,Q60) -> 0.01 | Q60: 0.01
N63: =+SUM(N53:N60) -> 1 | O63: =+SUM(O53:O60) -> 1.01 | P63: =+SUM(P53:P60) -> 1.005 | Q63: =+SUM(Q53:Q60) -> 1

Sheet Eje 4
B2: EFICIENCIA TERMICA
B4: Este eje depende de varios factores, entre los que se destacan la preparación de materias pimas y combustibles, el aumento en la capacidad de los hornos, el cambio de hornos largos a hornos con 6 etapas y precalcinador y uso de enfriadores de clínker con tecnología eficiente. El promedio global reportado en GNR año 2022 es de 3501 MJ/tclínker.
B7: Actualmente, en LAC, según datos de GNR del año 2022, el 55% de los hornos son de tipo proceso seco, con precalentador y precalcinador, mientras que un 24% de hornos operan con proceso seco, con precalentador y sin precalcinador, un 1% de hornos largos sin precalcinador, 18% de hornos mixtos; y el 2% restante corresponde a hornos verticales con proceso húmedo. Los valores de energía específica se encuentran entre los 3465 MJ/tclínker y los 6405 MJ/tclínker. El promedio en LAC es de 3576 MJ/tclínker.
D44: Eficiencia Térmica | E44: 2020 | F44: 2030 | G44: 2040 | H44: 2050
D45: FICEM | E45: 3.6 | F45: 3.5 | G45: =AVERAGE(F45,H45) -> 3.45 | H45: 3.4
D46: Perú | E46: 3.4 | F46: 3.2 | G46: =AVERAGE(F46,H46) -> 3.15 | H46: 3.1
D47: Colombia | E47: 4.1 | F47: 3.8 | G47: =AVERAGE(F47,H47) -> 3.65 | H47: 3.5
D48: Chile | E48: 3.9 | F48: 3.5 | G48: =AVERAGE(F48,H48) -> 3.4 | H48: 3.3
D49: ARGENTINA | E49: 3.425 | F49: 3.4 | G49: =AVERAGE(F49,H49) -> 3.35 | H49: 3.3

Sheet Eje 5
B2: COMBUSTIBLES FOSILES CONVENCIONALES
B3: Los combustibles fósiles tradicionales utilizados en hornos de cemento son, principalmente, el carbón y los derivados del petróleo. La energía aportada por este tipo de combustibles, corresponde a la suma de la participación de cada uno de ellos. A nivel global, según GNR 2022, los combustibles fósiles tradicionales correspondieron al 77% de la matriz de combustibles, distribuidos de la siguiente manera: carbón, 38%, petcoke 25%, gas natural 10% y el 4% restante, otros combustibles.
B5: Actualmente, el uso de combustibles fósiles es predominante en la industria del cemento, debido a su alta disponibilidad y bajo costo. En la región, el 81% de la matriz de combustibles de la industria cementera corresponde a fósiles tradicionales, distribuidos de la siguiente manera: 49% petcoke, 16% carbón, 14% gas natural y el 2% restante a otros combustibles.
K42: Combustible | L42: 2020 | M42: 2030 | N42: 2040 | O42: 2050
C43: Fosiles Tradicionales | D43: 2020 | E43: 2030 | F43: 2040 | G43: 2050 | K43: Total Fosiles Tradicionales | L43: =+L44+L45 -> 0.93 | M43: =+M44+M45 -> 0.9 | N43: =+N44+N45 -> 0.835 | O43: =+O44+O45 -> 0.77
C44: FICEM | D44: 89 | E44: 75 | F44: =AVERAGE(E44,G44) -> 57.5 | G44: 40 | K44: Gas Natural | L44: 0.82 | M44: 0.82 | N44: =+AVERAGE(M44,O44) -> 0.785 | O44: 0.75
C45: Perú | D45: 100 | E45: 81 | F45: =+AVERAGE(E45,G45) -> 67.5 | G45: 54 | K45: Petcoke | L45: 0.11 | M45: 0.08 | N45: =AVERAGE(M45,O45) -> 0.05 | O45: 0.02
C46: Colombia | D46: 92 | E46: 85 | F46: =AVERAGE(E46,G46) -> 65 | G46: 45 | K46: Carbón
C47: Chile | D47: 85 | E47: 65 | F47: =AVERAGE(E47,G47) -> 43.5 | G47: 22 | K47: Heavy Fuel
C48: ARGENTINA | D48: 93 | E48: 90 | F48: =AVERAGE(E48,G48) -> 83.5 | G48: 77 | K48: Diesel Oil
C49: GCCA Roadmap | D49: 94 | E49: 78 | F49: =AVERAGE(E49,G49) -> 67.5 | G49: 57 | K49: Otros
C51: Carbon
C52: Petcoke
C53: Gas Natural

Sheet Eje Coproc
B2: COPROCESAMIENTO
B3: Corresponden a combustibles cuya energía proviene de la fracción fósil de los residuos. Entre ellos se puede destacar los derivados de residuos urbanos o industriales, neumáticos fuera de uso, plásticos, solventes, aceites usados, entre otros, lo que permite el desplazamiento del uso de combustibles fósiles tradicionales.
B6: El bajo despliegue de este eje, se debe, entre otros factores, a la inadecuada gestión de los residuos en la Región.
B8: Actualmente, la participación de este tipo de combustibles, a nivel regional es de 8%, distribuidos de la siguiente manera: 4% corresponde a residuos industriales y urbanos, 2% a neumáticos fuera de uso, y el 2% restante, a otros combustibles derivados de residuos.
D45: Coprocesamiento | E45: 2020 | F45: 2030 | G45: 2040 | H45: 2050 | J45: Biomasa | K45: 2020 | L45: 2030 | M45: 2040 | N45: 2050 | Q45: Combustible | R45: 2020 | S45: 2030 | T45: 2040 | U45: 2050
D46: FICEM | E46: 11 | F46: 24 | G46: 42.5 | H46: 50 | J46: FICEM | K46: 3 | L46: 4 | M46: =AVERAGE(L46,N46) -> 7 | N46: 10 | Q46: Derivados de Residuos | R46: 0.03 | S46: 0.05 | T46: =+AVERAGE(S46,U46) -> 0.065 | U46: 0.08
D47: Perú | E47: 0 | F47: 19 | G47: 32.5 | H47: 46 | J47: Perú | K47: 0 | L47: 8 | M47: =+AVERAGE(L47,N47) -> 15.5 | N47: 23 | Q47: Residuos Sólidos (RSU/RIS) | R47: 0.01 | S47: 0.02 | T47: =+AVERAGE(S47,U47) -> 0.03 | U47: 0.04
D48: Colombia | E48: 8 | F48: 15 | G48: 35 | H48: 55 | J48: Colombia | K48: 1 | L48: 3 | M48: =AVERAGE(L48,N48) -> 6.5 | N48: 10 | Q48: Neumáticos Fuera de Uso | R48: 0.01 | S48: 0.02 | T48: =AVERAGE(S48,U48) -> 0.025 | U48: 0.03
D49: Chile | E49: 15 | F49: 35 | G49: 56.5 | H49: 78 | J49: Chile | K49: 1 | L49: 7 | M49: =AVERAGE(L49,N49) -> 14.5 | N49: 22 | Q49: Otros Residuos | R49: 0.01 | S49: 0.01 | T49: =+AVERAGE(S49,U49) -> 0.02 | U49: 0.03
D50: ARGENTINA | E50: 5 | F50: 10 | G50: =AVERAGE(F50,H50) -> 14 | H50: 18 | J50: Argentina | K50: 3 | L50: 5 | M50: =AVERAGE(L50,N50) -> 7.5 | N50: 10
D51: GCCA Roadmap | E51: 6 | F51: 22 | G51: =+AVERAGE(F51,H51) -> 32.5 | H51: 43 | K51: =+K50+E50 -> 8 | L51: =+L50+F50 -> 15 | M51: =+M50+G50 -> 21.5 | N51: =+N50+H50 -> 28 | Q51: grafico 2 local biomasa + cdr y coproc

Sheet Eje 6
B2: COMBUSTIBLES FOSILES ALTERNATIVOS
B3: Corresponden a combustibles cuya energía proviene de la fracción fósil de los residuos. Entre ellos se puede destacar los derivados de residuos urbanos o industriales, neumáticos fuera de uso, plásticos, solventes, aceites usados, entre otros, lo que permite el desplazamiento del uso de combustibles fósiles tradicionales.
B6: El bajo despliegue de este eje, se debe, entre otros factores, a la inadecuada gestión de los residuos en la Región.
B8: Actualmente, la participación de este tipo de combustibles, a nivel regional es de 8%, distribuidos de la siguiente manera: 4% corresponde a residuos industriales y urbanos, 2% a neumáticos fuera de uso, y el 2% restante, a otros combustibles derivados de residuos.
D45: CDR Fosiles | E45: 2020 | F45: 2030 | G45: 2040 | H45: 2050 | J45: Biomasa | K45: 2020 | L45: 2030 | M45: 2040 | N45: 2050 | Q45: Combustible | R45: 2020 | S45: 2030 | T45: 2040 | U45: 2050
D46: FICEM | E46: 8 | F46: 20 | G46: =+AVERAGE(F46,H46) -> 30 | H46: 40 | J46: FICEM | K46: 3 | L46: 4 | M46: =AVERAGE(L46,N46) -> 7 | N46: 10 | Q46: Derivados de Residuos | R46: 0.03 | S46: 0.05 | T46: =+AVERAGE(S46,U46) -> 0.065 | U46: 0.08
D47: Perú | E47: 0 | F47: 4 | G47: =+AVERAGE(F47,H47) -> 11 | H47: 18 | J47: Perú | K47: 0 | L47: 8 | M47: =+AVERAGE(L47,N47) -> 15.5 | N47: 23 | Q47: Residuos Sólidos (RSU/RIS) | R47: 0.01 | S47: 0.02 | T47: =+AVERAGE(S47,U47) -> 0.03 | U47: 0.04
D48: Colombia | E48: 7 | F48: 12 | G48: =+AVERAGE(F48,H48) -> 26 | H48: 40 | J48: Colombia | K48: 1 | L48: 3 | M48: =AVERAGE(L48,N48) -> 6.5 | N48: 10 | Q48: Neumáticos Fuera de Uso | R48: 0.01 | S48: 0.02 | T48: 0.02 | U48: 0.02
D49: Chile | E49: 14 | F49: 23 | G49: =+AVERAGE(F49,H49) -> 33 | H49: 43 | J49: Chile | K49: 1 | L49: 7 | M49: =AVERAGE(L49,N49) -> 14.5 | N49: 22 | Q49: Otros Residuos | R49: 0.01 | S49: 0.01 | T49: =+AVERAGE(S49,U49) -> 0.015 | U49: 0.02
D50: ARGENTINA | E50: 3 | F50: 5 | G50: 7 | H50: 8 | J50: Argentina | K50: 3 | L50: 5 | M50: =AVERAGE(L50,N50) -> 7.5 | N50: 10 | Q50: Waste oil
K51: =+K50+E50 -> 6 | L51: =+L50+F50 -> 10 | M51: =+M50+G50 -> 14.5 | N51: =+N50+H50 -> 18 | Q51: RDF (incl. Plasticos)
Q52: Solventes

Sheet Eje 7
C2: COMBUSTIBLES DERIVADOS DE BIOMASA
C38: Biomasa | D38: 2020 | E38: 2030 | F38: 2040 | G38: 2050 | N38: Combustible | O38: 2020 | P38: 2030 | Q38: 2040 | R38: 2050
C39: FICEM | D39: 3 | E39: 4 | F39: =AVERAGE(E39,G39) -> 7 | G39: 10 | N39: Derivados de Biomasa | O39: 0.04 | P39: 0.05 | Q39: =+AVERAGE(P39,R39) -> 0.075 | R39: 0.1
C40: Perú | D40: 0 | E40: 8 | F40: =+AVERAGE(E40,G40) -> 15.5 | G40: 23 | N40: Residuos Agrícolas | O40: 0.03 | P40: 0.04 | Q40: 0.05 | R40: 0.07
C41: Colombia | D41: 1 | E41: 3 | F41: =AVERAGE(E41,G41) -> 6.5 | G41: 10 | N41: Maderas | O41: 0 | P41: 0 | Q41: 0.01 | R41: 0.01
C42: Chile | D42: 1 | E42: 7 | F42: =AVERAGE(E42,G42) -> 14.5 | G42: 22 | N42: Otros Residuos Biomasa | O42: 0.01 | P42: 0.01 | Q42: 0.02 | R42: 0.02
C43: ARGENTINA | D43: 4 | E43: 5 | F43: =AVERAGE(E43,G43) -> 7.5 | G43: 10 | N43: Lodos
N44: Papeles, cartones

Sheet Eje 8
C2: COMBUSTIBLES DE HIDROGENO BAJO EN CARBONO
P17: MATRIZ COMBUSTIBLES | Q17: 2020 | R17: 2030 | S17: 2040 | T17: 2050
P18: Fósiles Tradicionales | Q18: 0.93 | R18: 0.9 | S18: =+AVERAGE(R18,T18) -> 0.835 | T18: 0.77
P19: Derivados Residuos Fósiles | Q19: 0.03 | R19: 0.05 | S19: =+AVERAGE(R19,T19) -> 0.065 | T19: 0.08
P20: Biomasa | Q20: 0.04 | R20: 0.05 | S20: =+AVERAGE(R20,T20) -> 0.075 | T20: 0.1
P21: Hidrógeno | Q21: 0 | R21: 0 | S21: 0.01 | T21: 0.05
P22: Energia Producción H2 (MWh/tH2) | Q22: 44 | R22: 44 | S22: 44 | T22: 44
P23: Poder Calorífico (MJ/kgH2) | Q23: 120 | R23: 120 | S23: 120 | T23: 120
C38: Coprocesamiento | D38: 2020 | E38: 2030 | F38: 2040 | G38: 2050
C39: FICEM | D39: 0 | E39: 1 | F39: =AVERAGE(E39,G39) -> 5.5 | G39: 10
C40: Perú | D40: 0 | E40: 0 | F40: =+AVERAGE(E40,G40) -> 0.5 | G40: 1
C41: Colombia | D41: 1 | E41: 3 | F41: =AVERAGE(E41,G41) -> 6.5 | G41: 10
C42: Chile | D42: 0 | E42: 2 | F42: =AVERAGE(E42,G42) -> 6 | G42: 10
C43: Argentina | D43: 0 | E43: 0 | F43: =AVERAGE(E43,G43) -> 2.5 | G43: 5
C44: Global GNR

Sheet Eje 9-10-11
C2: COMBUSTIBLES DE HIDROGENO BAJO EN CARBONO
C38: 2050 | D38: CCUS | E38: Metano | F38: SbN | G38: total
C39: FICEM | D39: 30 | E39: 3 | F39: 9 | G39: =+SUM(D39:F39) -> 42
C40: Argentina | D40: 19 | E40: 10 | F40: 13 | G40: =+SUM(D40:F40) -> 42
C41: Perú | D41: 20 | E41: 9 | F41: 11 | G41: =+SUM(D41:F41) -> 40 | L41: =2.5*0.33 -> 0.825 | N41: =8.3*0.33 -> 2.739
C42: GCCA | D42: 36 | E42: 0 | F42: 0 | G42: =+SUM(D42:F42) -> 36 | L42: =+L41/3.8 -> 0.21710526 | N42: =+N41/16.9 -> 0.16207101
C43: Colombia | D43: 16 | E43: 4 | F43: 13 | G43: =+SUM(D43:F43) -> 33
C44: Chile | D44: 22 | E44: 2 | F44: 9 | G44: =+SUM(D44:F44) -> 33
C45: Cembureau | D45: 42
C46: India
C47: China | D47: 30
C48: Canada | D48: 57
D49: Ejes 12-13 | E49: CCUS
S53: RECARBONATACION | U53: 2020 | V53: 2030 | W53: 2040 | X53: 2050
S54: Factor Recarbonatación | T54: % | U54: 0.2 | V54: 0.2 | W54: 0.2 | X54: 0.2
S55: Factor Emisión Calcinación | T55: kgCO2/kgCk | U55: 0.525 | V55: 0.525 | W55: 0.525 | X55: 0.525
S56: Volumen Producción Clínker | T56: MtCk | U56: 8.5 | V56: 9.2 | W56: =+AVERAGE(V56,X56) -> 9.85 | X56: 10.5
S57: Sumidero de Emsiones | T57: MtCO2 | U57: =+U54*U55*U56 -> 0.8925 | V57: =+V54*V55*V56 -> 0.966 | W57: =+W54*W55*W56 -> 1.03425 | X57: =+X54*X55*X56 -> 1.1025

Sheet CCUS
B38: 2050 | D38: CCUS | E38: SbN | F38: Metano | G38: Total | H38: FCk | I38: Coproces
B39: India* | D39: 0.25 | G39: =SUM(D39:F39) -> 0.25 | H39: 0.56 | I39: 0.5
B40: China | D40: 0.3 | G40: =SUM(D40:F40) -> 0.3 | H40: 0.65 | I40: 0.53
B41: Chile | D41: 0.22 | E41: 0.02 | F41: 0.09 | G41: =SUM(D41:F41) -> 0.33 | H41: 0.63 | I41: 0.66
B42: Colombia | D42: 0.16 | E42: 0.04 | F42: 0.13 | G42: =SUM(D42:F42) -> 0.33 | H42: 0.55 | I42: 0.5
B43: GCCA | D43: 0.36 | G43: =SUM(D43:F43) -> 0.36 | H43: 0.54 | I43: 0.43
B44: Perú | D44: 0.2 | E44: 0.09 | F44: 0.11 | G44: =SUM(D44:F44) -> 0.4 | H44: 0.63 | I44: 0.45
B45: FICEM | D45: 0.3 | E45: 0.03 | F45: 0.09 | G45: =SUM(D45:F45) -> 0.42 | H45: 0.6 | I45: 0.5
B46: Cembureau | D46: 0.42 | G46: =SUM(D46:F46) -> 0.42 | H46: 0.65 | I46: 0.9
B47: Argentina | D47: 0.19 | E47: 0.1 | F47: 0.13 | G47: =SUM(D47:F47) -> 0.42 | H47: 0.61 | I47: 0.18
D49: Ejes 12-13 | E49: CCUS
S53: RECARBONATACION | U53: 2020 | V53: 2030 | W53: 2040 | X53: 2050
S54: Factor Recarbonatación | T54: % | U54: 0.2 | V54: 0.2 | W54: 0.2 | X54: 0.2
S55: Factor Emisión Calcinación | T55: kgCO2/kgCk | U55: 0.525 | V55: 0.525 | W55: 0.525 | X55: 0.525
S56: Volumen Producción Clínker | T56: MtCk | U56: 8.5 | V56: 9.2 | W56: =+AVERAGE(V56,X56) -> 9.85 | X56: 10.5
S57: Sumidero de Emsiones | T57: MtCO2 | U57: =+U54*U55*U56 -> 0.8925 | V57: =+V54*V55*V56 -> 0.966 | W57: =+W54*W55*W56 -> 1.03425 | X57: =+X54*X55*X56 -> 1.1025

Sheet Resumen Ejes de Reduccion
B2: ROADMAP NZA GCCA-FICEM ARGENTINA 2050
E3: 2023 | F3: 0.18 | G3: 0.55
E4: 2020 | F4: 2030 | G4: 2050 | H4: baja demanda | I4: alta demanda
B5: PRINCIPALES INDICADORES | C5: Cemento BAU | D5: Mt | E5: =+'Whole life model'!F17 -> 12.55 | F5: =+E5*(1+F3) -> 14.809 | G5: =+E5*(1+G3) -> 19.4525 | H5: 2030: 10% a 20% 2050: 25% a 40% | I5: 2030: 25% a 40% 2050: 50% a 80%
C6: Cemento NZA | D6: Mt | E6: =+'Whole life model'!F21 -> 12.55 | F6: =+'Whole life model'!G21 -> 14.141428 | G6: =+'Whole life model'!H21 -> 16.913329 | I6: 1 | J6: LB 2020 Ck | K6: =+E25 -> 6.3131988
C7: Emisiones Brutas Cemento | D7: kg CO2/t cement | E7: =+E17/E6*1000 -> 503.04373 | F7: =+F17/F5*1000 -> 490.8808 | G7: =+G17/G5*1000 -> 485.50488 | J7: Alc2 | K7: =+E28 -> 0.42105302
C8: Emisiones Netas Cemento | D8: kg CO2/t cement | E8: =+E7-1000*(E112*E113*E119)/1000000 -> 494.82373 | F8: =+F7-1000*(F112*F113*F119)/1000000 -> 476.8808 | G8: =+G7-1000*(G112*G113*G119)/1000000 -> 464.38488 | J8: Total 2020 | K8: =+K6+K7 -> 6.7342518
C9: Clinker BAU | D9: Mt | E9: =+E11*E5 -> 8.47125 | F9: =+F11*F5 -> 9.6836051 | G9: =+E9*(1+G3) -> 13.130438 | J9: Aumento 2050 | K9: =+G19 -> 1.55
C10: Clinker NZA | D10: Mt | E10: =+E6*E11 -> 8.47125 | F10: =+F6*F11 -> 9.24708 | G10: =+G6*G11 -> 10.358906 | H10: 0.2 | J10: BAU 2050 | K10: =+K8*K9 -> 10.43809
C11: Factor Clinker NZA | D11: % | E11: 0.675 | F11: =+F32*F33+F37*F38+F42*F43+F47*F48 -> 0.6539 | G11: =+G32*G33+G37*G38+G42*G43+G47*G48 -> 0.61247 | H11: =+H10/H12 -> 0.01980198
C12: Coprocesamiento NZA | D12: % | E12: =+E111 -> 0.07 | F12: =+F111 -> 0.1 | G12: =+G111 -> 0.18 | H12: =6.1+0.4+3.6 -> 10.1 | I12: 2 | J12: D&C (13%) | K12: =-G54 -> -1.0078503 | L12: =K10+K10*M12 -> 9.43024 | M12: =-H54 -> -0.09655505 | N12: =+K10+K12 -> 9.43024
C13: Biomasa | D13: % | E13: =+E114 -> 0.04 | F13: =+F114 -> 0.05 | G13: =+G114 -> 0.1 | I13: =+I12+1 -> 3 | J13: Concreto (7%) | K13: =+L12-L13 -> -0.63594932 | L13: =+L12-K10*M13 -> 10.066189 | M13: =-H55 -> -0.06092583 | N13: =+N12+K13 -> 8.7942907
C14: Consumo Térmico | D14: MJ/t clinker | E14: 3425 | F14: 3400 | G14: 3300 | I14: =+I13+1 -> 4 | J14: Cem&Adic (7%) | K14: =+L13-L14 -> -0.85273514 | L14: =+L13-K$10*M14 -> 10.918924 | M14: =-H68-H74 -> -0.081694555 | N14: =+N13+K14 -> 7.9415555
C15: Consumo de Concreto | D15: Mm3 | E15: =+'Whole life model'!N49*1000 -> 32.9 | F15: =+'Whole life model'!O49*1000 -> 37.5 | G15: =+'Whole life model'!P49*1000 -> 50.5 | H15: Clinker (15,5%) | I15: =+I14+1 -> 5 | J15: Efic. Term (2%) | K15: =+L14-L15 -> -0.053832098 | L15: =+L14-K$10*M15 -> 10.972757 | M15: =-L28 -> -0.0051572746
C16: Cemento en el Concreto | D16: kgcem/m3 | E16: =+E6/E15*1000 -> 381.45897 | F16: =+F6/F15*1000 -> 377.10476 | G16: =+G6/G15*1000 -> 334.9174 | I16: =+I15+1 -> 6 | J16: Fosil Conv (3%) | K16: =+L15-L16 -> -0.083439752 | L16: =+L15-K$10*M16 -> 11.056196 | M16: =-L29 -> -0.0079937757
C17: Emisiones Directas (Calcinación + Comb. Fósiles) | D17: Mt | E17: =+E9*E21/1000 -> 6.3131988 | F17: =+F9*F21/1000 -> 7.2694537 | G17: =+G9*G21/1000 -> 9.4442836 | H17: =+G10*G21/1000 -> 7.4508141 | I17: =+I16+1 -> 7 | J17: Fosil Alt (2%) | K17: =+L16-L17 -> -0.2187801 | L17: =+L16-K$10*M17 -> 11.274976 | M17: =-H120 -> -0.020959782
C18: Emisiones Residuales (sin CCUS) | D18: Mt | E18: =+E131 -> 5.3540839 | F18: =+F131 -> 6.1690512 | G18: =+G131 -> 5.5301906 | I18: =+I17+1 -> 8 | J18: Biom (5%) | K18: =+L17-L18 -> -0.12112222 | L18: =+L17-K$10*M18 -> 11.396099 | M18: =-L30 -> -0.011603868
C19: Aumento Demanda | D19: % | E19: 0 | F19: =1+F3 -> 1.18 | G19: =1+G3 -> 1.55 | I19: =+I21+1 -> 11 | J19: Metano (5%) | K19: =+L21-L19 -> -0.5174967 | L19: =+L21-K$10*M19 -> 14.194362 | M19: =-H133 -> -0.049577718
C20: Indicador | D20: Unidad | E20: 2020 | F20: 2030 | G20: 2050 | I20: =+I18+1 -> 9 | J20: H2V (0,5%) | K20: =+L18-L20 -> -0.01076642 | L20: =+L18-K$10*M20 -> 11.406865 | M20: =-L31 -> -0.0010314549
C21: Factor de Emisión Clínker Ponderado | D21: kg CO2/t clinker | E21: =+(E22*(1-E24)+E24*E23) -> 745.24997 | F21: =+(F22*(1-F24)+F24*F23) -> 750.69705 | G21: =+(G22*(1-G24)+G24*G23) -> 719.26648 | I21: =+I20+1 -> 10 | J21: CCUS (21%) | K21: =+L20-L21 -> -2.27 | L21: =+L20-K$10*M21 -> 13.676865 | M21: =-H132 -> -0.21747273 | O21: a | P21: 19
C22: FE Clínker Local Bruta | D22: kg CO2/t clinker | E22: =+E95 -> 745.24997 | F22: =+F95 -> 750.69705 | G22: =+G95 -> 719.26648 | I22: =+I24+1 -> 14 | J22: SbN (21%) | K22: =+L24-L22 -> -2.27 | L22: =+L24-K$10*M22 -> 18.157456 | M22: =-H134 -> -0.21747273 | O22: b | P22: 23
C23: FE Clínker Importado Bruta | D23: kg CO2/t clinker | E23: =+E99 -> 865 | F23: =+F99 -> 865 | G23: =+G99 -> 865 | I23: =+I19+1 -> 12 | J23: Electr (7%) | K23: =+L19-L23 -> -0.60540924 | L23: =+L19-K$10*M23 -> 14.799771 | M23: -0.058 | O23: c | P23: 41
C24: Participación Clínker Importado | D24: % | E24: =+E96 -> 0 | F24: 0 | G24: 0 | I24: =+I23+1 -> 13 | J24: Recarb (12%) | K24: =+L23-L24 -> -1.0876852 | L24: =+L23-K$10*M24 -> 15.887456 | M24: =-H125 -> -0.10420346 | O24: d | P24: 7
C25: Emisiones Clínker 2020 | D25: Mt CO2 | E25: =+E21*E9/1000 -> 6.3131988 | F25: =+F21*F9/1000 -> 7.2694537 | G25: =+G21*G9/1000 -> 9.4442836 | J25: =13+7+7+15.5+7+12 -> 61.5 | M25: =+SUM(M12:M24) -> -0.93264823 | O25: e | P25: 10
C26: Factor Eléctrico | D26: [g CO2/kWh] | E26: =+E76 -> 272.4 | F26: =+F76 -> 200 | G26: =+G76 -> 14.1 | J26: =100-J25 -> 38.5
C27: Consumo eléctrico Total | D27: TWh | E27: =+E78+E80+E82 -> 1.5457159 | F27: =+F78+F80+F82 -> 1.6773572 | G27: =+G78+G80+G82 -> 3.712892 | K27: =+K15+K16+K18+K20 -> -0.26916049 | M27: =+M16+M18+M15+M20 -> -0.025786373
C28: Emisiones Eléctricas | D28: Mt CO2 | E28: =+E26*E27/1000 -> 0.42105302 | F28: =+F26*F27/1000 -> 0.33547143 | G28: =+G26*G27/1000 -> 0.052351777 | J28: 20 | K28: E. Termica | L28: =+J28*H$102/100 -> 0.0051572746
B29: EMISIONES TOTALES DE CO2 LINEA BASE 2020 (LINEA BASE) | D29: Mt CO2 | E29: =+E25+E28 -> 6.7342518 | F29: =+F25+F28 -> 7.6049252 | G29: =+G25+G28 -> 9.4966354 | J29: 31 | K29: Fosil Conv | L29: =+J29*H$102/100 -> 0.0079937757
B30: AUMENTO EMISIONES POR DEMANDA SOCIAL 2050 (EJE 1) | D30: Mt CO2 | E30: N/A | F30: =+F17 -> 7.2694537 | G30: =+E29*(G19-1) -> 3.7038385 | H30: =+E29*(1+G3) -> 10.43809 | J30: 45 | K30: Biomasa | L30: =+J30*H$102/100 -> 0.011603868
E31: 2022 | F31: 2030 | G31: 2050 | I31: =+(G32-E32)/E32 -> 0.21813031 | J31: 4 | K31: H2V | L31: =+J31*H$102/100 -> 0.0010314549
B32: CANALES | C32: Concreto Premezclado | D32: % | E32: 0.353 | F32: 0.39 | G32: 0.43 | H32: =+E32*E33+E37*E38+E42*E43+E47*E48 -> 0.678048 | I32: =+(G33-E33)/E33 -> -0.11025641 | J32: =+SUM(J28:J31) -> 100 | L32: =+SUM(L28:L31) -> 0.025786373
C33: Factor clínker | D33: % | E33: 0.78 | F33: 0.75 | G33: 0.694 | H33: =+F32*F33+F37*F38+F42*F43+F47*F48 -> 0.6539 | J33: =+E32+E37+E42+E47 -> 1.01
C34: Infraestructura | D34: % | E34: 0.5 | F34: 0.5 | G34: 0.5 | H34: =+G32*G33+G37*G38+G42*G43+G47*G48 -> 0.61247 | J34: =+F32+F37+F42+F47 -> 1
C35: Construcción Estructural | D35: % | E35: 0.5 | F35: 0.5 | G35: 0.5 | J35: =+G32+G37+G42+G47 -> 0.995
C36: Construcción No Estructural | D36: % | E36: 0 | F36: =100%-F34-F35 -> 0 | G36: =100%-G34-G35 -> 0 | I36: =+(G37-E37)/E37 -> -0.19172932
C37: Sacos | D37: % | E37: 0.532 | F37: 0.47 | G37: 0.43 | I37: =+(G38-E38)/E38 -> -0.094076655 | AD37: =5.5/(6.3+0.3+3.36) -> 0.55220884
C38: Factor clínker | D38: % | E38: 0.574 | F38: 0.55 | G38: 0.52
C39: Infraestructura | D39: % | E39: 0.2 | F39: 0.2 | G39: 0.2
C40: Estructural | D40: % | E40: 0.4 | F40: 0.4 | G40: 0.4
C41: No Estructural | D41: % | E41: =100%-E39-E40 -> 0.4 | F41: =100%-F39-F40 -> 0.4 | G41: =100%-G39-G40 -> 0.4
C42: Silo en Obra | D42: % | E42: 0.072 | F42: 0.07 | G42: 0.065
C43: Factor clínker | D43: % | E43: 0.766 | F43: 0.72 | G43: 0.67
C44: Infraestructura | D44: % | E44: 1 | F44: 1 | G44: 1
C45: Estructural | D45: % | E45: 0 | F45: 0 | G45: 0 | K45: =41+44+7+7 -> 99
C46: No Estructural | D46: % | E46: =100%-E44-E45 -> 0 | F46: =100%-F44-F45 -> 0 | G46: =100%-G44-G45 -> 0
C47: Prefabricados | D47: % | E47: 0.053 | F47: 0.07 | G47: 0.07
C48: Factor clínker | D48: % | E48: 0.796 | F48: 0.75 | G48: 0.67
C49: Infraestructura | D49: % | E49: 0.8 | F49: 0.8 | G49: 0.7
C50: Estructural | D50: % | E50: 0.2 | F50: 0.2 | G50: 0.3
C51: No Estructural | D51: % | E51: =100%-E49-E50 -> 0 | F51: =100%-F49-F50 -> 0 | G51: =100%-G49-G50 -> 0
C52: Adiciones (DS, Ef. D&C) | D52: Mt | E52: =+'Whole life model'!J17*'Whole life model'!J11*'Whole life model'!J13*'Whole life model'!J15+'Whole life model'!M17*'Whole life model'!M11*'Whole life model'!M13*'Whole life model'!M15+'Whole life model'!P17*'Whole life model'!P11*'Whole life model'!P13*'Whole life model'!P15+'Whole life model'!S17*'Whole life model'!S11*'Whole life model'!S13*'Whole life model'!S15 -> 5.1496016 | F52: =+'Whole life model'!J17*'Whole life model'!K11/'Whole life model'!J11*'Whole life model'!K13/'Whole life model'!J13*'Whole life model'!K15/'Whole life model'!J15+'Whole life model'!M17*'Whole life model'!N11/'Whole life model'!M11*'Whole life model'!N13/'Whole life model'!M13*'Whole life model'!N15/'Whole life model'!M15+'Whole life model'!P17*'Whole life model'!Q11/'Whole life model'!P11*'Whole life model'!Q13/'Whole life model'!P13*'Whole life model'!Q15/'Whole life model'!P15+'Whole life model'!S17*'Whole life model'!T11/'Whole life model'!S11*'Whole life model'!T13/'Whole life model'!S13*'Whole life model'!T15/'Whole life model'!S15 -> 11.984261 | G52: =+('Whole life model'!J17*G32/E32*'Whole life model'!L13/'Whole life model'!J13*'Whole life model'!L15/'Whole life model'!J15)+('Whole life model'!M17*G37/E37*'Whole life model'!O13/'Whole life model'!M13*'Whole life model'!O15/'Whole life model'!M15)+('Whole life model'!P17*G42/E42*'Whole life model'!R13/'Whole life model'!P13*'Whole life model'!R15/'Whole life model'!P15)+('Whole life model'!S17*G47/E47*'Whole life model'!U13/'Whole life model'!S13*'Whole life model'!U15/'Whole life model'!S15) -> 10.740993
C53: Adiciones (DS, Ef. Concreto) | D53: Mt | E53: =+'Whole life model'!J17*'Whole life model'!J11*'Whole life model'!J15+'Whole life model'!M17*'Whole life model'!M11*'Whole life model'!M15+'Whole life model'!P17*'Whole life model'!P11*'Whole life model'!P15+'Whole life model'!S17*'Whole life model'!S11*'Whole life model'!S15 -> 5.1496016 | F53: =+'Whole life model'!J17*'Whole life model'!K11/'Whole life model'!J11*'Whole life model'!K15/'Whole life model'!J15+'Whole life model'!M17*'Whole life model'!N11/'Whole life model'!M11*'Whole life model'!N15/'Whole life model'!M15+'Whole life model'!P17*'Whole life model'!Q11/'Whole life model'!P11*'Whole life model'!Q15/'Whole life model'!P15+'Whole life model'!S17*'Whole life model'!T11/'Whole life model'!S11*'Whole life model'!T15/'Whole life model'!S15 -> 12.537764 | G53: =('Whole life model'!J17*G32/E32*'Whole life model'!L15/'Whole life model'!J15)+('Whole life model'!M17*G37/E37*'Whole life model'!O15/'Whole life model'!M15)+('Whole life model'!P17*G42/E42*'Whole life model'!R15/'Whole life model'!P15)+('Whole life model'!S17*G47/E47*'Whole life model'!U15/'Whole life model'!S15) -> 11.703663 | I53: =+H54+H55+H68+H74+H86+H102+H120+H125+H132+H133+H134 -> 0.92225174
B54: EMISIONES EVITADAS DISEÑO & CONSTRUCCION (EJE 2) | D54: Mt CO2 | E54: N/A | F54: =(E29+F30)-(E29+F30)*F52/(E70*'Whole life model'!G15) -> 0.61821909 | G54: =+(E29+G30)-(E29+G30)*G52/(E70*'Whole life model'!H15) -> 1.0078503 | H54: =+G54/H30 -> 0.09655505 | P54: =0.059*0.35+0.035*0.53+0.035*0.07+0.035*0.05 -> 0.0434
B55: EMISIONES EVITADAS CONCRETO (EJE 3) | D55: Mt CO2 | E55: N/A | F55: =(E29+F30-F54)-((E29+F30-F54)*F53/E69) -> 13.302487 | G55: =+(E29+G30-G54)-((E29+G30-G54)*G53/E70) -> 0.63594932 | H55: =+G55/H30 -> 0.06092583
B56: CEMENTO EN EL CONCRETO | D56: kg cemento / m3 | E56: =+'Whole life model'!N46 -> 381.45897 | F56: =+'Whole life model'!O46 -> 377.10476 | G56: =+'Whole life model'!P46 -> 334.9174 | H56: =+G53/E70 -> 0.93256276 | L56: 65
E57: 2022 | F57: 2030 | G57: 2050 | L57: 5
B58: CEMENTO & ADICIONES | C58: Factor Clínker Consolidado | D58: % | E58: =E32*E33+E37*E38+E42*E43+E47*E48 -> 0.678048 | F58: =F32*F33+F37*F38+F42*F43+F47*F48 -> 0.6539 | G58: =G32*G33+G37*G38+G42*G43+G47*G48 -> 0.61247 | H58: =+SUM(E58:E65) -> 1.010048 | I58: =+SUM(F58:F65) -> 1.0039 | J58: =+SUM(G58:G65) -> 1.00247 | L58: 15
C59: Yeso | D59: % | E59: 0.05 | F59: 0.05 | G59: 0.05 | L59: 4
C60: Caliza | D60: % | E60: 0.17 | F60: 0.15 | G60: 0.2 | L60: 2
C61: Escoria | D61: % | E61: 0.05 | F61: 0.04 | G61: 0.05 | L61: 5
C62: Cenizas | D62: % | E62: 0 | F62: 0.02 | G62: 0 | L62: 4
C63: Puzolana | D63: % | E63: 0.05 | F63: 0.05 | G63: 0.03
C64: Arcilla Calcinada | D64: % | E64: 0.01 | F64: 0.03 | G64: 0.05
C65: Otras Adiciones | D65: % | E65: 0.002 | F65: 0.01 | G65: 0.01
C66: Diferencia Factor Clínker vs. 2022 | E66: 0 | F66: =+E58-F58 -> 0.024148 | G66: =+E58-G58 -> 0.065578
C67: Factor Emisión Clínker 2020 | E67: =+E88*E95+E96*E99 -> 745.24997 | F67: =+E67 -> 745.24997 | G67: =+F67 -> 745.24997
B68: EMISIONES EVITADAS CEMENTO & ADICIONES (EJE 4) | D68: Mt CO2 | F68: =+'Resumen Ejes de Reduccion'!F6*'Resumen Ejes de Reduccion'!F66*'Resumen Ejes de Reduccion'!F67/1000 -> 0.25449333 | G68: =+'Resumen Ejes de Reduccion'!G6*'Resumen Ejes de Reduccion'!G66*'Resumen Ejes de Reduccion'!G67/1000 -> 0.82658823 | H68: =+G68/H30 -> 0.079189603 | I68: =+(E67*E58+G67*G58)/1000 -> 0.9617585 | J68: =+I68/H30 -> 0.092139316
E69: 2022 | F69: 2030 | G69: 2050
B70: NUEVOS CEMENTOS | C70: Cementicio en el Concreto | D70: Mt Cementicio | E70: =+'Whole life model'!F17 -> 12.55 | F70: =+'Whole life model'!G17 -> 14.141428 | G70: =+'Whole life model'!H17 -> 16.913329
C71: Nuevos cementicios en producción de concreto | D71: kg CO2/kg new binder | E71: =+'Whole life model'!G30 -> 0.01150919 | F71: =+'Whole life model'!H28 -> 0.01 | G71: =+'Whole life model'!H28 -> 0.01
C72: Factor medio emisión CO2 nuevos cementicios | D72: kg CO2/kg new binder | E72: =+'Whole life model'!G31 -> 6.7959812 | F72: =+'Whole life model'!G29 -> 0.4 | G72: =+'Whole life model'!H29 -> 0.29
C73: Factor Aglomerante Clínker en Concreto | D73: kg Ck/kg cementitious | E73: =+'Whole life model'!G21 -> 14.141428 | F73: =+'Whole life model'!H23 -> 13.022325 | G73: =+'Whole life model'!H19 -> 0.61812072
B74: EMISIONES EVITADAS NUEVOS CEMENTOS (EJE 6) | E74: =+E70*E71*(E22/1000*E73-E72) -> 0.54062831 | F74: =+F70*F71*(F22/1000*F73-F72) -> 1.325875 | G74: =+G70*G71*(G22/1000*G73-G72) -> 0.026146909 | H74: =+G74/H30 -> 0.0025049514
E75: 2022 | F75: 2030 | G75: 2050
B76: EMISIONES ELECTRICAS | C76: Factor emisión red eléctrica | D76: [g CO2/kWh] | E76: 272.4 | F76: 200 | G76: 14.1
C77: Consumo eléctrico específico | D77: [kWh/t cement] | E77: =+'1.2 Clinker EF'!F46 -> 120 | F77: =+'1.2 Clinker EF'!G46 -> 115 | G77: =+'1.2 Clinker EF'!H46 -> 87
C78: Consumo eléctrico producción cemento | D78: [TWh] | E78: =+E77*E6/1000 -> 1.506 | F78: =+F77*F6/1000 -> 1.6262643 | G78: =+G77*G6/1000 -> 1.4714596
C79: Consumo eléctrico adicional de CCUS | D79: [kWh/t clinker] | E79: 0 | F79: 0 | G79: 200
C80: Consumo eléctrico de CCUS | D80: [TWh] | E80: 0 | F80: 0 | G80: 2.11
C81: Consumo eléctrico adicional en concreto | D81: [kWh/m3] | E81: =+'Whole life model'!N39 -> 3 | F81: =+'Whole life model'!O39 -> 3 | G81: =+'Whole life model'!P39 -> 5
C82: Consumo eléctrico de mezcla concreto | D82: [TWh] | E82: =+'Whole life model'!N40 -> 0.039715936 | F82: =+'Whole life model'!O40 -> 0.051092906 | G82: =+'Whole life model'!P40 -> 0.13143241
C83: Consumo eléctrico Total | D83: [TWh] | E83: =+E82+E80+E78 -> 1.5457159 | F83: =+F82+F80+F78 -> 1.6773572 | G83: =+G82+G80+G78 -> 3.712892
B84: EMISIONES INDIRECTAS ELECTRICIDAD (EJE 1) | D84: (Mt CO2) | E84: =+E76*E83/1000 -> 0.42105302 | F84: =+F76*F83/1000 -> 0.33547143 | G84: =+G76*G83/1000 -> 0.052351777
B86: EMISIONES UPTAKE (EJE 6) | D86: (Mt CO2) | G86: =+(E84-G84)*G6/E6 -> 0.49688966 | H86: =+G86/H30 -> 0.047603503 | I86: =+H86+0.5% -> 0.052603503
E87: 2022 | F87: 2030 | G87: 2050 | I87: 99,5% lo abate directamente y queda u 0,5%
B88: FACTOR EMISIONES CLINKER | C88: Clínker Propio | D88: % | E88: 1 | F88: 1 | G88: 1
C89: Emisiones Calcinación | D89: kg CO2/kg clinker | E89: 0.525 | F89: 0.525 | G89: 0.525
C90: Emisiones carbono organico piedra caliza | D90: kg CO2/kg clinker | E90: 0.0113584 | F90: 0.0113584 | G90: 0.0113584
C91: Emisiones Combustibles Fósiles | D91: kg CO2/kg clinker | E91: =+'1.2 Clinker EF'!F38 -> 0.20073925 | F91: =+'1.2 Clinker EF'!G38 -> 0.200991 | G91: =+'1.2 Clinker EF'!H38 -> 0.1660923 | H91: =+(G91-E91)/G91 -> -0.20860058
C92: Emisiones Combustibles Derivados Residuos fósiles | D92: kg CO2/kg clinker | E92: =+'Whole life model'!F48/'Resumen Ejes de Reduccion'!E9 -> 0.0081523187 | F92: =+'Whole life model'!G48/'Resumen Ejes de Reduccion'!F9 -> 0.013347646 | G92: =+'Whole life model'!H48/'Resumen Ejes de Reduccion'!G9 -> 0.016815783 | H92: =+(G92-E92)/G92 -> 0.51519839
C93: Emisiones de Biomasa | D93: kg CO2/GJ fuel mix | E93: =+'1.2 Clinker EF'!F39 -> 0.0137 | F93: =+'1.2 Clinker EF'!G39 -> 0.0175 | G93: =+'1.2 Clinker EF'!H39 -> 0.033 | H93: =+(G93-E93)/G93 -> 0.58484848
C94: Factor Emisión Clínker Local Neta | D94: kg CO2/t clinker | E94: =+(E89+E90+E91)*1000 -> 737.09765 | F94: =+(F89+F90+F91)*1000 -> 737.3494 | G94: =+(G89+G90+G91)*1000 -> 702.4507
C95: Factor Emisión Clínker Local Bruta | D95: kg CO2/t clinker | E95: =+(E89+E90+E91+E92)*1000 -> 745.24997 | F95: =+(F89+F90+F91+F92)*1000 -> 750.69705 | G95: =+(G89+G90+G91+G92)*1000 -> 719.26648
C96: Clínker Importado | D96: % | E96: 0 | F96: 0 | G96: 0
C97: Factor Emisión | D97: kg CO2/t clinker | E97: 865 | F97: 865 | G97: 865
C98: Transporte Naviero (20,000 kms) | E98: 0 | F98: 0 | G98: 0
C99: Factor Emision Clínker Importado | E99: =+E97+E98 -> 865 | F99: =+F97+F98 -> 865 | G99: =+G97+G98 -> 865
B100: EMISIONES DE CO2 CLINKER BAU | D100: Mt CO2 | E100: =+E9*(E88*E95+E96*E99)/1000 -> 6.3131988 | F100: =+F9*(F88*F95+F96*F99)/1000 -> 7.2694537 | G100: =+G10*(E88*E95+E96*E99)/1000 -> 7.7199746
B101: EMISIONES DE CO2 CLINKER NZA | D101: Mt CO2 | E101: =+E10*(E88*E95+E96*E99)/1000 -> 6.3131988 | F101: =+F10*(F88*F95+F96*F99)/1000 -> 6.9417556 | G101: =+G10*(G88*G95+G96*G99)/1000 -> 7.4508141
B102: EMISIONES EVITADAS (EJE 7) | D102: Mt CO2 | G102: =+G100-G101 -> 0.26916049 | H102: =+G102/H30 -> 0.025786373
...

Sheet Whole life model
E1: Reference | F1: CEMENT FOR DOMESTIC USE | J1: Select world region for GCCA Roadmap: | P1: Colour index: | V1: Market segments | W1: README information
E2: Region | F2: ARGENTINA | J2: North America (Canada/USA) PCA/CAC | M2: Europe (Cembureau, ERMCO, BIBM) | P2: text information and descriptions | R2: default starting values, do not change
E3: Organisation | F3: AFCP | J3: Central + South America (Ficem) | M3: CIS Countries | P3: start with cement volumes | R3: Value from other worksheet
E4: corresponding author | F4: FICEM and AFCP | J4: China (CNBM) | M4: Africa (Dangote) | P4: then fill in all parts in green | R4: Calculated automatically | W4: Numbers to be filled in have been pre-set, for sake of easy reading. Please change!
E5: E-mail contact | F5: maria.lefevre@afcp.org.ar | J5: India (GCCA India) | M5: Middle East | P5: instruction text in italics, further README information at the right side | W5: Numbers only filled in for example of RMX
E6: Phone contact | F6: Phone | J6: Asia (incl. Japan, S.Korea, SE Asia, Oceania, excl. China and India)
B7: GCCA Roadmap Template | D7: Version 202, 19.07.2022, ECRA | E7: Reference year | F7: 2020 | G7: 2030 | H7: 2050 | J7: =F7 -> 2020 | K7: =G7 -> 2030 | L7: =H7 -> 2050 | M7: =F7 -> 2020 | N7: =G7 -> 2030 | O7: =H7 -> 2050 | P7: =F7 -> 2020 | Q7: =G7 -> 2030 | R7: =H7 -> 2050 | S7: =F7 -> 2020 | T7: =G7 -> 2030 | U7: =H7 -> 2050 | W7: Enter absolute values in volumes per one year, 2020 reference is assessed based on 2018 data
B8: Index | C8: Section | D8: Description | E8: Unit | G8: Summary | K8: Readymix | N8: (Concrete, mortar, screed from ) Bagged Cement | Q8: (Mortar, screed, others) Project Site Silos | T8: Precast (all factory produced product) | W8: Cement end use segment
B9: 0 | C9: Society demand
B10: 0.1 | D10: Crecimiento/disminución del mercado de la construcción* (desarrollo de la demanda social externa) | E10: % vs. status quo | F10: 1 | G10: =+'Resumen Ejes de Reduccion'!F3+1 -> 1.18 | H10: =+'Resumen Ejes de Reduccion'!G3+1 -> 1.55 | W10: The relative numbers of society demand shall allow for growth and efficiency effects, i.e. effects of rising population, urbanisation, development etc. AND decline due to re-use of buildings, higher utilisation, etc. For your estimate you can also use additional information from sources suggested on the sheet 'Info Society demand'
B11: 0.2 | D11: Cuota de segmentos de mercado de la producción de hormigón | E11: % | F11: =IF((J11+M11+S11+P11)=1,(J11+M11+S11+P11), "different from 100%, please correct line 0.2.5") -> 1 | G11: =IF((K11+N11+T11+Q11)=1,(K11+N11+T11+Q11), "different from 100%, please correct line 0.2.5") -> 1 | H11: =IF((L11+O11+U11+R11)=1,(L11+O11+U11+R11), "different from 100%, please correct line 0.2.5") -> 1 | J11: =J17/$F$17 -> 0.35258964 | K11: =+'0.2 Share of concrete'!G16 -> 0.39 | L11: =+'0.2 Share of concrete'!H16 -> 0.43 | M11: =M17/$F$17 -> 0.52788845 | N11: =+'0.2 Share of concrete'!J16 -> 0.47 | O11: =+'0.2 Share of concrete'!K16 -> 0.43 | P11: =P17/$F$17 -> 0.069721116 | Q11: =+'0.2 Share of concrete'!M16 -> 0.07 | R11: =+'0.2 Share of concrete'!N16 -> 0.07 | S11: =S17/$F$17 -> 0.049800797 | T11: =+'0.2 Share of concrete'!P16 -> 0.07 | U11: =+'0.2 Share of concrete'!Q16 -> 0.07 | W11: Value taken from sheet "0.2 Share of concrete".
B12: 4 | C12: Design & Construction
B13: 4.1 | D13: Ganancia de eficiencia (intensidad de material) por diseño y construcción | E13: % vs. status quo | F13: =(J17*F10/F10*J11/J11*J15/J15*J13/J13+M17*F10/F10*M11/M11*M15/M15*M13/M13+P17*F10/F10*P11/P11*P15/P15*P13/P13+S17*F10/F10*S11/S11*S15/S15*S13/S13)/(F17*F10/F10*F15/F15) -> 1 | G13: =(J17*G10/F10*K11/J11*K15/J15*K13/J13+M17*G10/F10*N11/M11*N15/M15*N13/M13+P17*G10/F10*Q11/P11*Q15/P15*Q13/P13+S17*G10/F10*T11/S11*T15/S15*T13/S13)/(F17*G10/F10*G15/F15) -> 0.95585318 | H13: =(J17*H10/F10*L11/J11*L15/J15*L13/J13+M17*H10/F10*O11/M11*O15/M15*O13/M13+P17*H10/F10*R11/P11*R15/P15*R13/P13+S17*H10/F10*U11/S11*U15/S15*U13/S13)/(F17*H10/F10*H15/F15) -> 0.91781397 | I13: =+F13-H13 -> 0.082186034 | J13: 1 | K13: ='4.1 Design & Construction'!K44 -> 0.94111875 | L13: ='4.1 Design & Construction'!W44 -> 0.92169 | M13: 1 | N13: ='4.1 Design & Construction'!N44 -> 0.96525 | O13: ='4.1 Design & Construction'!Z44 -> 0.910518 | P13: 1 | Q13: ='4.1 Design & Construction'!Q44 -> 0.96525 | R13: ='4.1 Design & Construction'!AC44 -> 0.92169 | S13: 1 | T13: ='4.1 Design & Construction'!T44 -> 0.96525 | U13: ='4.1 Design & Construction'!AF44 -> 0.931 | W13: Value taken from sheet "4.1 Desing and construction". The unit for efficiency expressed as % cement saving, signficant design and construction efficiencies can be converted to a relative cement saving in %
B14: 3 | C14: Concrete
B15: 3.1 | D15: Ganancias de eficiencia (intensidad material) en la producción de concreto (excluyendo SCM) | E15: % vs. status quo | F15: =(J17*F10/F10*J11/J11*J15/J15+M17*F10/F10*M11/M11*M15/M15+P17*F10/F10*P11/P11*P15/P15+S17*F10/F10*S11/S11*S15/S15)/(F17*F10/F10) -> 1 | G15: =(J17*G10/F10*K11/J11*K15/J15+M17*G10/F10*N11/M11*N15/M15+P17*G10/F10*Q11/P11*Q15/P15+S17*G10/F10*T11/S11*T15/S15)/(F17*G10/F10) -> 0.999025 | H15: =(J17*H10/F10*L11/J11*L15/J15+M17*H10/F10*O11/M11*O15/M15+P17*H10/F10*R11/P11*R15/P15+S17*H10/F10*U11/S11*U15/S15)/(F17*H10/F10) -> 0.947325 | I15: =+F15-H15 -> 0.052675 | J15: 1 | K15: ='3.1 Concrete production'!G24 -> 0.9975 | L15: ='3.1 Concrete production'!H24 -> 0.9775 | M15: 1 | N15: ='3.1 Concrete production'!J24 -> 1 | O15: ='3.1 Concrete production'!K24 -> 0.9 | P15: 1 | Q15: ='3.1 Concrete production'!M24 -> 1 | R15: ='3.1 Concrete production'!N24 -> 1 | S15: 1 | T15: ='3.1 Concrete production'!P24 -> 1 | U15: ='3.1 Concrete production'!Q24 -> 1 | W15: Value taken from sheet "3.1 Concrete production". The unit for efficiency expressed as % cement saving, signficant efficiency gains in concrete production and shift between product categories can be converted to a relative cement saving in %
B16: 2 | C16: Cement & Binders | F16: BAU | G16: =+F17*G10 -> 14.809 | H16: =+F17*H10 -> 19.4525
B17: 2.1 | D17: Volumen de ligante en hormigón (material cementoso, cemento y SCM en planta de hormigón) | E17: Mt cementitious | F17: =J17+M17+P17++S17 -> 12.55 | G17: =K17+N17+Q17+T17 -> 14.141428 | H17: =L17+O17+R17++U17 -> 16.913329 | J17: =J21+J18 -> 4.425 | K17: =+J17*G10/$F$10*K13/$J$13*K15/$J$15*K11/$J$11 -> 5.4218521 | L17: =+J17*H10/$F$10*L13/$J$13*L15/$J$15*L11/$J$11 -> 7.5360804 | M17: =M21+M18 -> 6.625 | N17: =+M17*G10/$F$10*N13/$M$13*N15/$M$15*N11/$M$11 -> 6.718362 | O17: =+M17*H10/$F$10*O13/$M$13*O15/$M$15*O11/$M$11 -> 6.8544865 | P17: =P21+P18 -> 0.875 | Q17: =+P17*G10/$F$10*Q13/$P$13*Q15/$P$15*Q11/$P$11 -> 1.0006071 | R17: =+P17*H10/$F$10*R13/$P$13*R15/$P$15*R11/$P$11 -> 1.2550422 | S17: =S21+S18 -> 0.625 | T17: =+S17*G10/$F$10*T13/$S$13*T15/$S$15*T11/$S$11 -> 1.0006071 | U17: =+S17*H10/$F$10*U13/$S$13*U15/$S$15*U11/$S$11 -> 1.2677194 | W17: Value determined from cement volume (line 2.4.1) considering society demand changes and efficiency changes in design & construction and concrete production
B18: 2.2 | D18: Uso de materiales cementicios suplementarios (SCM) en la producción de hormigón | E18: Mt cementitious | F18: =J18+M18+P18++S18 -> 0 | G18: =K18+N18+Q18++T18 -> 0 | H18: =L18+O18+R18++U18 -> 0 | J18: 0 | K18: 0 | L18: 0 | M18: 0 | N18: 0 | O18: 0 | P18: 0 | Q18: 0 | R18: 0 | S18: 0 | T18: 0 | U18: 0 | W18: The use of supplementary cementitious materials (SCM) in concrete production is recorded in Mt of SCM. Note that the use of SCM in cement production is already reflected by changes in the clinker factor (line 2.4.2) and can be descirbed in the corresponding extra sheet.
B19: 2.3 | D19: "Factor aglomerante de clinker en el hormigón" que refleja el uso adicional de SCM en la producción de hormigón (comparable con IEA ETP, el enfoque de Cembureau) | E19: kg clinker/kg cementitious | F19: =F24/F17 -> 0.66944223 | G19: =G24/G17 -> 0.65286055 | H19: =H24/H17 -> 0.61812072 | J19: =IF(J17=0,"not available",J24/J17) -> 0.78 | K19: =IF(K17=0,"not available",K24/K17) -> 0.75 | L19: =IF(L17=0,"not available",L24/L17) -> 0.69 | M19: =IF(M17=0,"not available",M24/M17) -> 0.57 | N19: =IF(N17=0,"not available",N24/N17) -> 0.55 | O19: =IF(O17=0,"not available",O24/O17) -> 0.52 | P19: =IF(P17=0,"not available",P24/P17) -> 0.77 | Q19: =IF(Q17=0,"not available",Q24/Q17) -> 0.72 | ... U19: =IF(U17=0,"not available",U24/U17) -> 0.67 | W19: This clincker binder factor encompasses the change in SCM use in concrete in 2030 and 2050. It is used to jointly illustrate CO2 mitigation in cement & binders due to (i) changes in cement production (clinker factor) and (ii) changes in SCM use in concrete.
B20: 2.4 | C20: Cement | J20: =+J21+M21+P21+S21 -> 12.55
B21: 2.4.1 | D21: Volumen de producción de cemento (excl. SCM para uso en planta de concreto) | E21: Mt cement | F21: =J21+M21+P21+S21 -> 12.55 | G21: =K21+N21+Q21+T21 -> 14.141428 | H21: =L21+O21+R21+U21 -> 16.913329 | J21: =12.5*0.354 -> 4.425 | K21: =(+K17-K18) -> 5.4218521 | L21: =+L17-L18 -> 7.5360804 | M21: =12.5*0.53 -> 6.625 | N21: =(+N17-N18) -> 6.718362 | O21: =+O17-O18 -> 6.8544865 | P21: =12.5*0.07 -> 0.875 | Q21: =(+Q17-Q18) -> 1.0006071 | R21: =+R17-R18 -> 1.2550422 | S21: =12.5*0.05 -> 0.625 | T21: =(+T17-T18) -> 1.0006071 | U21: =+U17-U18 -> 1.2677194 | W21: Start the calculation with 2020 cement production volumes in four categories Readymix, Bagged Cement, Mortar and Precast. As 2020 statistics are not yet known, 2018 statistical data on cement production can be used as substitute and assuming similar production for 2020. Changes in SCM use in cement production shall be reflected in the production volume (line 2.4.1), the clinker factor (line 2.4.2) together with a brief description in the sheet "2.2 & 2.4.2 Cement & Binder". Future changes to SCM use in concrete production are recorded in line 2.2.
B22: 2.4.2 | D22: Clinker factor | E22: kg clinker/kg cement | F22: =F24/F21 -> 0.66944223 | G22: =G24/G21 -> 0.65286055 | H22: =H24/H21 -> 0.61812072 | J22: 0.78 | K22: 0.75 | L22: 0.69 | M22: 0.57 | N22: 0.55 | O22: 0.52 | P22: 0.77 | Q22: 0.72 | R22: 0.67 | S22: 0.8 | T22: 0.75 | U22: 0.67 | W22: Value reflecting the status quo 2020 (or 2018 statistics) and 2030 and 2050 development of the efficient use of clinker in cement production. Please record the description and relevance of related technologies in the sheet "2.2 & 2.4.2 Cement & Binder".
B23: 1 | C23: Clinker | F23: BAU | G23: =+F24*G10 -> 9.91377 | H23: =+F24*H10 -> 13.022325
B24: 1.1 | D24: Volumen producción de Clinker | E24: Mt clinker | F24: =J24+M24+P24+S24 -> 8.4015 | G24: =K24+N24+Q24++T24 -> 9.2323807 | H24: =L24+O24+R24++U24 -> 10.454479 | J24: =J21*J22 -> 3.4515 | K24: =K21*K22 -> 4.0663891 | L24: =L21*L22 -> 5.1998955 | M24: =M21*M22 -> 3.77625 | N24: =N21*N22 -> 3.6950991 | O24: =O21*O22 -> 3.564333 | P24: =P21*P22 -> 0.67375 | Q24: =Q21*Q22 -> 0.72043712 | ... U24: =U21*U22 -> 0.84937201
B25: 1.2 | D25: Factor emisión CO2 del Clinker (= linea 1.2.4) | E25: kg CO2/kg clinker | F25: ='1.2 Clinker EF'!F44 -> 0.73709765 | G25: ='1.2 Clinker EF'!G44 -> 0.7373494 | H25: ='1.2 Clinker EF'!H44 -> 0.7024507 | W25: Value taken from sheet "1.2 Clinker EF" reflecting the CO2 mitigation and improvement of thermal energy efficiency in the clinker production process (excl. new binders, recarbonation and CCUS).
B26: 1.3 | D26: Emisiones de CO2 (excluyendo efecto de nuevos ligantes, recarbonatación y CCUS) | E26: Mt CO2 > | F26: =F24*F25 -> 6.1927259 | G26: =G24*G25 -> 6.8074903 | H26: =H24*H25 -> 7.3437559 | J26: Emissions from clay calcination | N26: 2020 | O26: 2030 | P26: 2050
B27: 1.4 | C27: New binders | H27: =+F26-H26 -> -1.15103 | J27: Share of calcined clay in binder volume | N27: 0 | O27: 0 | P27: 0
B28: 1.4.1 | D28: Porcentaje de ligantes nuevos utilizados en la producción de hormigón, referencia al volumen de ligante, línea 2.1 | E28: % share of binder volume in concrete | F28: 0 | G28: 0.01 | H28: 0.01 | J28: Volume of calcined clay [Mt] | N28: =F17*N27 -> 0 | O28: =G17*O27 -> 0 | P28: =H17*P27 -> 0 | S28: 0.225 | W28: Share of use of new binders in relation to the Binder volume in concrete (line 2.1).
B29: 1.4.2 | D29: Factor medio de emisión de CO2 de los nuevos ligantes | E29: kg CO2/kg new binder | G29: 0.4 | H29: 0.29 | J29: Emission factor of calcined clay [kg CO2/kg calc. clay] | N29: 0 | O29: 0 | P29: 0 | W29: Specific average CO2 emission factor of new binders. If different technologies apply, determine the input from a weighted average from the application of these technologies.Note that the CO2 efficiency of cements and binders based on cement is evolving in parallel according to the assumptions made in section 1 and 2.
B30: 1.4.3 | D30: Ahorro de emisiones de CO2 por el uso de nuevos aglutinantes (número positivo = ahorro en comparación con los cementos y aglutinantes a base de clínker) | E30: Mt CO2 | G30: =G17*G28*(G25*G19-G29) -> 0.01150919 | H30: =H17*H28*(H25*H19-H29) -> 0.024388906 | J30: Emissions from clay calcination [Mt CO2] | N30: =N28*N29 -> 0 | O30: =O28*O29 -> 0 | P30: =P28*P29 -> 0 | W30: The CO2 emission saving is accounted as additional saving from the application of new binder technologies relative to the efficient production of cements and binders based on clinker (as specified in section 1 and 2).
B31: 1.4.4 | D31: CO2 emissions (excluding recarbonation and CCUS) | E31: Mt CO2 > | F31: =N31-F30 -> 6.1927259 | G31: =O31-G30 -> 6.7959812 | H31: =P31-H30 -> 7.319367 | J31: CO2 emissions (incl. clay calcination) [Mt CO2] | N31: =F26+N30 -> 6.1927259 | O31: =G26+O30 -> 6.8074903 | P31: =H26+P30 -> 7.3437559
B32: 5 | C32: Recarbonation
B33: 5.1 | D33: Product life cycle partial recarbonation according to IVL study (conservative estimate in relation to process emissions) | E33: kg CO2/kg calcination CO2 | F33: 0.29 | J33: Indirect emissions from electricity | N33: 2020 | O33: 2030 | P33: 2050 | W33: Refer to sheet 'Info Recarbonation estimate' for an easy and refined estimate according to IVL study
B34: 5.2 | D34: Amount of recarbonated CO2 during product life cycle | E34: Mt CO2 | F34: =F24*'1.2 Clinker EF'!F11*$F$33 -> 1.2791284 | G34: =G24*'1.2 Clinker EF'!G11*$F$33 -> 1.40563 | H34: =H24*'1.2 Clinker EF'!H11*$F$33 -> 1.5916944 | J34: Factor emisión red eléctrica [g CO2/kWh] | N34: 272 | O34: 200 | P34: 14.1 | Q34: =+N34*0.001 -> 0.272 | R34: =+Q34*1000 -> 272
B35: 5.3 | D35: CO2 emissions (excluding effect of CCUS) | E35: Mt CO2 > | F35: =F31-F34 -> 4.9135975 | G35: =G31-G34 -> 5.3903512 | H35: =H31-H34 -> 5.7276726 | J35: Consumo eléctrico específico [kWh/t cement] | N35: ='1.2 Clinker EF'!F46 -> 120 | O35: ='1.2 Clinker EF'!G46 -> 115 | P35: ='1.2 Clinker EF'!H46 -> 87
B36: 6 | C36: Carbon Capture | G36: =+F35*0.25 -> 1.2283994 | H36: =+F35-G36 -> 3.6851981 | J36: Consumo eléctrico producción cemento [TWh] | N36: =N35*F21/1000 -> 1.506 | O36: =O35*G21/1000 -> 1.6262643 | P36: =P35*H21/1000 -> 1.4714596
B37: 6.1 | D37: Cantidad de CO2 capturado para uso y/o almacenamiento (CCUS) | E37: Mt CO2 | F37: 0 | G37: 0 | H37: =+H35 -> 5.7276726 | J37: Consumo eléctrico adicional de CCUS [kWh/t clinker] | N37: 0 | O37: 0 | P37: 200 | Q37: Ocupando u tercio de la prod de ckmestara cubierta con CCUS. Paper 50, con eificiencia 80% | W37: Enter the absolute amount of CO2 captured and used or permanently stored in Mt CO2. E.g. if for 2050 the value for line 6.1 is equal to line 5.3, the calculation results in no residual CO2 emissions or carbon neutrality in line 6.3.
B38: 6.2 | D38: Cantidad equivalente producción clínker con captura de carbono al 90% eficiencia de captura CO2 de la cadena completa de CCUS | E38: Mt clinker produced with CCUS | F38: =F24*(F37/0.9)/F31 -> 0 | G38: =G24*(G37/0.9)/G31 -> 0 | H38: =H24*(H37/0.9)/H31 -> 9.0900137 | J38: Consumo eléctrico de CCUS [TWh] | N38: =N37*F24/1000 -> 0 | O38: =O37*G38/1000 -> 0 | P38: =P37*H24/1000 -> 2.0908957 | W38: This line is for information. It provieds a rough estimate of the clinker production volume that is assumed to be equipped with CCUS technology. The value should not exceed the value clinker productin volume determined in line 1.1. In this estimate a capture efficency of 90% is assumed, accounding for some efficiency losses in the capture process itself and in the CCUS chain, e.g. direct or indirect CO2 emissions during CO2 processing, transport and intermediate storage.
B39: 6.3 | D39: Emisiones de CO2 residuales (incluido el efecto de CCUS) | E39: Mt CO2 > | F39: =F35-F37 -> 4.9135975 | G39: =G35-G37 -> 5.3903512 | H39: =H35-H37 -> 0 | J39: Consumo eléctrico adicional en concreto [kWh/m3] | N39: 3 | O39: 3 | P39: 5
J40: Consumo eléctrico de mezcla concreto [TWh] | N40: =N54*N39 -> 0.039715936 | O40: =O54*O39 -> 0.051092906 | P40: =P54*P39 -> 0.13143241
B41: 7 | C41: Reporting | J41: Consumo eléctrico Total [TWh] | N41: =N38+N36+N40 -> 1.5457159 | O41: =O38+O36+O40 -> 1.6773572 | P41: =P38+P36+P40 -> 3.6937877
B42: 7.1 | C42: Absolute | D42: CO2 emissions | E42: Mt CO2 >> | F42: =F26+N30-F30-F34-F37 -> 4.9135975 | G42: =G26+O30-G30-G34-G37 -> 5.3903512 | H42: =H26+P30-H30-H34-H37 -> 0 | J42: Emisiones Indirectas Electricidad (Mt CO2) | N42: =N41*N34/1000 -> 0.42043473 | O42: =O41*O34/1000 -> 0.33547143 | P42: =P41*P34/1000 -> 0.052082407
B43: 7.2 | C43: Specific | D43: CO2 emissions
B44: 7.2.1 | D44: Clinker | E44: t CO2/t clinker | F44: =F42/F24 -> 0.58484765 | G44: =G42/G24 -> 0.58385279 | H44: =H42/H24 -> 0 | J44: Volúmenes de Concreto | N44: 2020 | O44: 2030 | P44: 2050
B45: 7.2.2 | D45: Cement | E45: t CO2/t cement | F45: =F42/F21 -> 0.39152172 | G45: =G42/G21 -> 0.38117445 | H45: =H42/H21 -> 0 | J45: Todos los segmentos de mercado
B46: 7.2.3 | D46: Cement & Binder, including change of SCMs in concrete | E46: t CO2/t cementitious | F46: =F42/F17 -> 0.39152172 | G46: =G42/G17 -> 0.38117445 | H46: =H42/H17 -> 0 | J46: Contenido de Cemento en el concret [kg cement / m3] | N46: =F21/N49 -> 381.45897 | O46: =G21/O49 -> 377.10476 | P46: =H21/P49 -> 334.9174
B47: 7.3 | C47: Additional information | J47: Contenido de SCM en el concreto [kg SCM / m3] | N47: =F18/N49 -> 0 | O47: =G18/O49 -> 0 | P47: =H18/P49 -> 0
B48: 7.3.1 | D48: Fossil CO2 from waste fuels | E48: Mt CO2 | F48: ='1.2 Clinker EF'!F21*'1.2 Clinker EF'!$J21*'1.2 Clinker EF'!F32/1000/1000*F24 -> 0.06906033 | G48: ='1.2 Clinker EF'!G21*'1.2 Clinker EF'!$J21*'1.2 Clinker EF'!G32/1000/1000*G24 -> 0.12925333 | H48: ='1.2 Clinker EF'!H21*'1.2 Clinker EF'!$J21*'1.2 Clinker EF'!H32/1000/1000*H24 -> 0.22079859 | J48: Contenido de Cementicio en concreto [kg binder / m3] | N48: =N46+N47 -> 381.45897 | O48: =O46+O47 -> 377.10476 | P48: =P46+P47 -> 334.9174
B49: 7.3.2 | D49: Capture of biogenic CO2 from waste fuels | E49: Mt CO2 | F49: =F37*('1.2 Clinker EF'!F39/'1.2 Clinker EF'!F44) -> 0 | G49: =G37*('1.2 Clinker EF'!G39/'1.2 Clinker EF'!G44) -> 0 | H49: =H37*('1.2 Clinker EF'!H39/'1.2 Clinker EF'!H44) -> 0.26907681 | J49: Volumen Total de concreto [Bn m3] | N49: 0.0329 | O49: 0.0375 | P49: 0.0505
B50: 7.3.3 | D50: CO2 uptake by enhanced carbonation (use of captured carbon in concrete and aggregate production) | E50: Mt CO2 | F50: 0 | G50: 0 | H50: 0 | J50: Volume of RMX concrete [M m3] | N50: =J17/N48 -> 0.011600199 | O50: =K17/O48 -> 0.014377576 | P50: =L17/P48 -> 0.022501311 | W50: Enter the estimated amount of CO2 uptake by enhanced carbonation during concrete and aggregate production as additional information for the GCCA roadmap.
D51: Note: Avoided emissions, offsets, natural based solutions will be regarded by GCCA in a separat process | J51: Volume of concrete made from bagged cement [M m3] | N51: =M17/N48 -> 0.01736753 | O51: =N17/O48 -> 0.017815638 | P51: =O17/P48 -> 0.0204662
J52: Volume of mortar, screed, others [Bn m3] | N52: =P17/N48 -> 0.0022938247 | O52: =Q17/O48 -> 0.002653393 | P52: =R17/P48 -> 0.0037473187
D53: Version 103, 17.12.2020, ECRA | J53: Volume of precast concrete [Bn m3] | N53: =S17/N48 -> 0.0016384462 | O53: =T17/O48 -> 0.002653393 | P53: =U17/P48 -> 0.0037851704
J54: Volume of RMX + precast concrete [Bn m3] | N54: =N50+N53 -> 0.013238645 | O54: =O50+O53 -> 0.017030969 | P54: =P50+P53 -> 0.026286481
G56: 11.5 | H56: Mm3 | J56: 0.6 | K56: =+K62*J56 -> 7.26 | L56: Premix
G57: =+G56/1000 -> 0.0115 | H57: Bnm3 | J57: 0.25 | K57: =+K62*J57 -> 3.025 | L57: Sacos
J58: 0.1 | K58: =+K62*J58 -> 1.21 | L58: Silos
J59: 0.05 | K59: =+K62*J59 -> 0.605 | L59: Precast
J60: =+SUM(J56:J59) -> 1 | K60: =+SUM(K56:K59) -> 12.1
J62: 0.25 | K62: 12.1 | L62: =+K62*4 -> 48.4
J63: 1 | K63: =+J63*K62/J62 -> 48.4

Sheet Waterfall data
E1: Reference | P1: Waterafall data for construction of diagrams
E2: Region | F2: ='Whole life model'!F2 -> ARGENTINA
E3: Organisation | F3: ='Whole life model'!F3 -> AFCP
E4: corresponding author | F4: ='Whole life model'!F4 -> FICEM and AFCP
E5: E-mail contact | F5: ='Whole life model'!F5 -> maria.lefevre@afcp.org.ar
E6: Phone contact | F6: ='Whole life model'!F6 -> Phone
E7: Reference year | F7: ='Whole life model'!F7 -> 2020 | G7: ='Whole life model'!G7 -> 2030 | H7: ='Whole life model'!H7 -> 2050 | I7: ='Whole life model'!F7 -> 2020 | J7: ='Whole life model'!G7 -> 2030 | K7: ='Whole life model'!H7 -> 2050 | L7: ='Whole life model'!F7 -> 2020 | M7: ='Whole life model'!G7 -> 2030 | N7: ='Whole life model'!H7 -> 2050
G8: Waterfall diagram data | J8: Direct emissions | M8: Indirect emissions | P8: Waterfall diagram data for GCCA CO2 roadmap status quo to 2030 | Y8: Waterfall diagram data for GCCA CO2 roadmap status quo to 2050
B9: 8 | C9: Absolute CO2 | D9: direct emissions from clinker production, calcination and fuel CO2, basis for waterfall diagram | Q9: Direct CO2 emissions (Mt CO2) | R9: Indirect CO2 emissions (Mt CO2) | S9: increase (blue) | T9: decrease (green) | U9: (white) | Z9: Direct CO2 emissions (Mt CO2) | AA9: Indirect CO2 emissions (Mt CO2) | AB9: increase (blue) | AC9: decrease (green) | AD9: (white)
B10: 8.00 | D10: CO2 reference (status quo) | E10: Mt CO2 | F10: =I10+L10 -> 6.6131606 | G10: =J10+M10 -> 6.6131606 | H10: =K10+N10 -> 6.6131606 | I10: ='Whole life model'!$F$26 -> 6.1927259 | J10: ='Whole life model'!$F$26 -> 6.1927259 | K10: ='Whole life model'!$F$26 -> 6.1927259 | L10: ='Whole life model'!$N$42 -> 0.42043473 | M10: ='Whole life model'!$N$42 -> 0.42043473 | N10: ='Whole life model'!$N$42 -> 0.42043473 | P10: ='Whole life model'!F7 -> 2020 | Q10: =J10 -> 6.1927259 | R10: =M10 -> 0.42043473 | V10: =G10 -> 6.6131606 | Y10: ='Whole life model'!F7 -> 2020 | Z10: =K10 -> 6.1927259 | AA10: =N10 -> 0.42043473 | AE10: =H10 -> 6.6131606
B11: 8.0 | D11: CO2 according to societal demand changes (status quo technology) | E11: Mt CO2 | F11: =I11+L11 -> 6.6131606 | G11: =J11+M11 -> 7.8035296 | H11: =K11+N11 -> 10.250399 | I11: =I$10*'Whole life model'!F10 -> 6.1927259 | J11: =J$10*'Whole life model'!G10 -> 7.3074166 | K11: =K$10*'Whole life model'!H10 -> 9.5987252 | L11: =L$10*'Whole life model'!F10 -> 0.42043473 | M11: =M$10*'Whole life model'!G10 -> 0.49611299 | N11: =N$10*'Whole life model'!H10 -> 0.65167384 | P11: Societal demand | S11: =IF(V11>W11,V11-U11,"") -> 1.1903689 | T11: =IF(V11<W11,W11-U11,"") | U11: =MIN(V11:W11) -> 6.6131606 | V11: =G11 -> 7.8035296 | W11: =V11-G23 -> 6.6131606 | Y11: Societal demand | AB11: =IF(AE11>AF11,AE11-AD11,"") -> 3.6372384 | AC11: =IF(AE11<AF11,AF11-AD11,"") | AD11: =MIN(AE11:AF11) -> 6.6131606 | AE11: =H11 -> 10.250399 | AF11: =AE11-H23 -> 6.6131606
B12: 8.4 | D12: CO2 emission with additional measures in section design & construction | E12: Mt CO2 | F12: =I12+L12 -> 6.6131606 | G12: =J12+M12 -> 7.4590285 | H12: =K12+N12 -> 9.4079594 | I12: =I11*('Whole life model'!F13/'Whole life model'!$F13) -> 6.1927259 | J12: =J11*('Whole life model'!G13/'Whole life model'!$F13) -> 6.9848174 | K12: =K11*('Whole life model'!H13/'Whole life model'!$F13) -> 8.809844 | L12: =L11*('Whole life model'!F13/'Whole life model'!$F13) -> 0.42043473 | M12: =M11*('Whole life model'!G13/'Whole life model'!$F13) -> 0.47421118 | N12: =N11*('Whole life model'!H13/'Whole life model'!$F13) -> 0.59811535 | P12: Design & Construction | S12: =IF(V12>W12,V12-U12,"") | T12: =IF(V12<W12,W12-U12,"") -> 0.34450103 | U12: =MIN(V12:W12) -> 7.4590285 | V12: =G12 -> 7.4590285 | W12: =V12-G24 -> 7.8035296 | Y12: Design&Construction | AB12: =IF(AE12>AF12,AE12-AD12,"") | AC12: =IF(AE12<AF12,AF12-AD12,"") -> 0.84243964 | AD12: =MIN(AE12:AF12) -> 9.4079594 | AE12: =H12 -> 9.4079594 | AF12: =AE12-H24 -> 10.250399 | AG12: =+AC12/AE$11 -> 0.082186034
B13: 8.3 | D13: CO2 emission with additional measures in section concrete | E13: Mt CO2 | F13: =I13+L13 -> 6.6131606 | G13: =J13+M13 -> 7.451756 | H13: =K13+N13 -> 8.9123951 | I13: =I12*('Whole life model'!F15/'Whole life model'!$F15) -> 6.1927259 | J13: =J12*('Whole life model'!G15/'Whole life model'!$F15) -> 6.9780072 | K13: =K12*('Whole life model'!H15/'Whole life model'!$F15) -> 8.3457855 | L13: =L12*('Whole life model'!F15/'Whole life model'!$F15) -> 0.42043473 | M13: =M12*('Whole life model'!G15/'Whole life model'!$F15) -> 0.47374882 | N13: =N12*('Whole life model'!H15/'Whole life model'!$F15) -> 0.56660962 | P13: Concrete | S13: =IF(V13>W13,V13-U13,"") | T13: =IF(V13<W13,W13-U13,"") -> 0.0072725528 | U13: =MIN(V13:W13) -> 7.451756 | V13: =G13 -> 7.451756 | W13: =V13-G25 -> 7.4590285 | Y13: Concrete | AB13: =IF(AE13>AF13,AE13-AD13,"") | AC13: =IF(AE13<AF13,AF13-AD13,"") -> 0.49556426 | AD13: =MIN(AE13:AF13) -> 8.9123951 | AE13: =H13 -> 8.9123951 | AF13: =AE13-H25 -> 9.4079594 | AG13: =+AC13/AE$11 -> 0.048345851
B14: 8.2 | D14: CO2 emission with additional measures in section cement & binders (incl. SCM) | E14: Mt CO2 | F14: =I14+L14 -> 6.6131606 | G14: =J14+M14 -> 7.2789149 | H14: =K14+N14 -> 8.2725813 | I14: =I13*('Whole life model'!F19/'Whole life model'!$F19)*('Whole life model'!N31/'Whole life model'!F26) -> 6.1927259 | J14: =J13*('Whole life model'!G19/'Whole life model'!$F19)*('Whole life model'!O31/'Whole life model'!G26) -> 6.8051661 | K14: =K13*('Whole life model'!H19/'Whole life model'!$F19)*('Whole life model'!P31/'Whole life model'!H26) -> 7.7059717 | L14: =L13 -> 0.42043473 | M14: =M13 -> 0.47374882 | N14: =N13 -> 0.56660962 | P14: Cement & binders | S14: =IF(V14>W14,V14-U14,"") | T14: =IF(V14<W14,W14-U14,"") -> 0.17284107 | U14: =MIN(V14:W14) -> 7.2789149 | V14: =G14 -> 7.2789149 | W14: =V14-G26 -> 7.451756 | Y14: Cement & binders | AB14: =IF(AE14>AF14,AE14-AD14,"") | AC14: =IF(AE14<AF14,AF14-AD14,"") -> 0.63981376 | AD14: =MIN(AE14:AF14) -> 8.2725813 | AE14: =H14 -> 8.2725813 | AF14: =AE14-H26 -> 8.9123951 | AG14: =+AC14/AE$11 -> 0.062418425
B15: 8.1.4 | D15: CO2 emission with additional measures in section new binders | E15: Mt CO3 | F15: =I15+L15 -> 6.6131606 | G15: =J15+M15 -> 7.2674097 | H15: =K15+N15 -> 8.2469895 | I15: =I14*('Whole life model'!F31/'Whole life model'!N31) -> 6.1927259 | J15: =J14*('Whole life model'!G31/'Whole life model'!O31) -> 6.7936608 | K15: =K14*('Whole life model'!H31/'Whole life model'!P31) -> 7.6803799 | L15: =L14 -> 0.42043473 | M15: =M14 -> 0.47374882 | N15: =N14 -> 0.56660962 | P15: New binders | S15: =IF(V15>W15,V15-U15,"") | T15: =IF(V15<W15,W15-U15,"") -> 0.01150526 | U15: =MIN(V15:W15) -> 7.2674097 | V15: =G15 -> 7.2674097 | W15: =V15-G27 -> 7.2789149 | Y15: New binders | AB15: =IF(AE15>AF15,AE15-AD15,"") | AC15: =IF(AE15<AF15,AF15-AD15,"") -> 0.02559184 | AD15: =MIN(AE15:AF15) -> 8.2469895 | AE15: =H15 -> 8.2469895 | AF15: =AE15-H27 -> 8.2725813 | AG15: =+AC15/AE$11 -> 0.0024966676
D16: CO2 emission with additional decarbonisation of electricity mix | E16: Mt CO2 | F16: =I16+L16 -> 6.6131606 | G16: =J16+M16 -> 7.1291323 | H16: =K16+N16 -> 7.7324623 | I16: =I15 -> 6.1927259 | J16: =J15 -> 6.7936608 | K16: =K15 -> 7.6803799 | L16: ='Whole life model'!N42 -> 0.42043473 | M16: ='Whole life model'!O42 -> 0.33547143 | N16: ='Whole life model'!P42 -> 0.052082407 | P16: Electricity | S16: =IF(V16>W16,V16-U16,"") | T16: =IF(V16<W16,W16-U16,"") -> 0.13827739 | U16: =MIN(V16:W16) -> 7.1291323 | V16: =G16 -> 7.1291323 | W16: =V16-G28 -> 7.2674097 | Y16: Electricity | AB16: =IF(AE16>AF16,AE16-AD16,"") | AC16: =IF(AE16<AF16,AF16-AD16,"") -> 0.51452722 | AD16: =MIN(AE16:AF16) -> 7.7324623 | AE16: =H16 -> 7.7324623 | AF16: =AE16-H28 -> 8.2469895 | AG16: =+AC16/AE$11 -> 0.050195823
B17: 8.1 | D17: CO2 emission with additional measures in section clinker | E17: Mt CO2 | F17: =I17+L17 -> 6.6131606 | G17: =J17+M17 -> 7.1314526 | H17: =K17+N17 -> 7.3714494 | I17: =I16*('Whole life model'!F25/'Whole life model'!$F25) -> 6.1927259 | J17: =J16*('Whole life model'!G25/'Whole life model'!$F25) -> 6.7959812 | K17: =K16*('Whole life model'!H25/'Whole life model'!$F25) -> 7.319367 | L17: =L16 -> 0.42043473 | M17: =M16 -> 0.33547143 | N17: =N16 -> 0.052082407 | P17: Clinker | S17: =IF(V17>W17,V17-U17,"") -> 0.0023203223 | T17: =IF(V17<W17,W17-U17,"") | U17: =MIN(V17:W17) -> 7.1291323 | V17: =G17 -> 7.1314526 | W17: =V17-G29 -> 7.1291323 | Y17: Clinker | AB17: =IF(AE17>AF17,AE17-AD17,"") | AC17: =IF(AE17<AF17,AF17-AD17,"") -> 0.36101287 | AD17: =MIN(AE17:AF17) -> 7.3714494 | AE17: =H17 -> 7.3714494 | AF17: =AE17-H29 -> 7.7324623 | AG17: =+AC17/AE$11 -> 0.035219397
B18: 8.5 | D18: CO2 emission with accounting of partial recarbonation (= line 5.3) | E18: Mt CO2 | F18: =I18+L18 -> 5.3340323 | G18: =J18+M18 -> 5.7258226 | H18: =K18+N18 -> 5.779755 | I18: =I17-'Whole life model'!F34 -> 4.9135975 | J18: =J17-'Whole life model'!G34 -> 5.3903512 | K18: =K17-'Whole life model'!H34 -> 5.7276726 | L18: =L17 -> 0.42043473 | M18: =M17 -> 0.33547143 | N18: =N17 -> 0.052082407 | P18: Recarbonation | S18: =IF(V18>W18,V18-U18,"") | T18: =IF(V18<W18,W18-U18,"") -> 1.40563 | U18: =MIN(V18:W18) -> 5.7258226 | V18: =G18 -> 5.7258226 | W18: =V18-G30 -> 7.1314526 | Y18: Recarbonation | AB18: =IF(AE18>AF18,AE18-AD18,"") | AC18: =IF(AE18<AF18,AF18-AD18,"") -> 1.5916944 | AD18: =MIN(AE18:AF18) -> 5.779755 | AE18: =H18 -> 5.779755 | AF18: =AE18-H30 -> 7.3714494 | AG18: =+AC18/AE$11 -> 0.15528121
D19: CO2 emission with additional deduction of emissions from fossil waste fuels | E19: Mt CO2 | F19: =I19+L19 -> 5.2649719 | G19: =J19+M19 -> 5.5965693 | H19: =K19+N19 -> 5.5589564 | I19: =I18-'Whole life model'!F48 -> 4.8445372 | J19: =J18-'Whole life model'!G48 -> 5.2610979 | K19: =K18-'Whole life model'!H48 -> 5.506874 | L19: =L18 -> 0.42043473 | M19: =M18 -> 0.33547143 | N19: =N18 -> 0.052082407 | P19: Fossil waste fuels | S19: =IF(V19>W19,V19-U19,"") | T19: =IF(V19<W19,W19-U19,"") -> 0.12925333 | U19: =MIN(V19:W19) -> 5.5965693 | V19: =G19 -> 5.5965693 | W19: =V19-G31 -> 5.7258226 | Y19: Fossil waste fuels | AB19: =IF(AE19>AF19,AE19-AD19,"") | AC19: =IF(AE19<AF19,AF19-AD19,"") -> 0.22079859 | AD19: =MIN(AE19:AF19) -> 5.5589564 | AE19: =H19 -> 5.5589564 | AF19: =AE19-H31 -> 5.779755 | AG19: =+AC19/AE$11 -> 0.021540487
B20: 8.6 | D20: CO2 emission with CO2 capture, CCUS (= line 6.3) | E20: Mt CO2 | F20: =I20+L20 -> 5.2649719 | G20: =J20+M20 -> 5.5965693 | H20: =K20+N20 -> 0.052082407 | I20: =I19-'Whole life model'!F37 -> 4.8445372 | J20: =J19-'Whole life model'!G37 -> 5.2610979 | K20: =K19-'Whole life model'!H37+'Whole life model'!H48 -> -2.9976022e-15 | L20: =L19 -> 0.42043473 | M20: =M19 -> 0.33547143 | N20: =N19 -> 0.052082407 | P20: CCUS | S20: =IF(V20>W20,V20-U20,"") | T20: =IF(V20<W20,W20-U20,"") | U20: =MIN(V20:W20) -> 5.5965693 | V20: =G20 -> 5.5965693 | W20: =V20-G32 -> 5.5965693 | Y20: CCUS/NbS/Metano | AB20: =IF(AE20>AF20,AE20-AD20,"") | AC20: =IF(AE20<AF20,AF20-AD20,"") -> 5.506874 | AD20: =MIN(AE20:AF20) -> 0.052082407 | AE20: =H20 -> 0.052082407 | AF20: =AE20-H32 -> 5.5589564 | AG20: =+AC20/AE$11 -> 0.53723509
P21: ='Whole life model'!G7 -> 2030 | Q21: =J20 -> 5.2610979 | R21: =M20 -> 0.33547143 | Y21: ='Whole life model'!H7 -> 2050 | Z21: =K20 -> -2.9976022e-15 | AA21: =N20 -> 0.052082407
B22: 9 | C22: Absolute CO2 emission changes, cummulative
B23: 9.0 | D23: CO2 change according to societal demand changes (status quo technology) | E23: Mt CO2 | F23: =F11-F10 -> 0 | G23: =G11-G10 -> 1.1903689 | H23: =H11-H10 -> 3.6372384
B24: 9.4 | D24: CO2 emission change by additional measures in section design & construction | E24: Mt CO2 | F24: =F12-F11 -> 0 | G24: =G12-G11 -> -0.34450103 | H24: =H12-H11 -> -0.84243964
B25: 9.3 | D25: CO2 emission change by additional measures in section concrete | E25: Mt CO2 | F25: =F13-F12 -> 0 | G25: =G13-G12 -> -0.0072725528 | H25: =H13-H12 -> -0.49556426
B26: 9.2 | D26: CO2 emission change by additional measures in section cement & binders (incl. SCM) | E26: Mt CO2 | F26: =F14-F13 -> 0 | G26: =G14-G13 -> -0.17284107 | H26: =H14-H13 -> -0.63981376
B27: 9.1.4 | D27: CO2 emission change by additional measures in section new binders (based on line 1.4.3) | E27: Mt CO3 | F27: =F15-F14 -> 0 | G27: =G15-G14 -> -0.01150526 | H27: =H15-H14 -> -0.02559184
D28: CO2 emission change by decarbonisation electricity | E28: Mt CO2 | F28: =F16-F15 -> 0 | G28: =G16-G15 -> -0.13827739 | H28: =H16-H15 -> -0.51452722
B29: 9.1 | D29: CO2 emission change by additional measures in section clinker | E29: Mt CO2 | F29: =F17-F16 -> 0 | G29: =G17-G16 -> 0.0023203223 | H29: =H17-H16 -> -0.36101287
B30: 9.5 | D30: CO2 emission change by accounting of partial recarbonation (based on line 5.2) | E30: Mt CO2 | F30: =F18-F17 -> -1.2791284 | G30: =G18-G17 -> -1.40563 | H30: =H18-H17 -> -1.5916944
D31: CO2 emission change by deduction of emissions from fossil waste fuels | E31: Mt CO2 | F31: =F19-F18 -> -0.06906033 | G31: =G19-G18 -> -0.12925333 | H31: =H19-H18 -> -0.22079859
B32: 9.6 | D32: CO2 emission change by CO2 capture, CCUS (based on line 6.1) | E32: Mt CO2 | F32: =F20-F19 -> 0 | G32: =G20-G19 -> 0 | H32: =H20-H19 -> -5.506874
B34: 10 | C34: Relative improvement factors
B35: 10.0 | D35: Society demand improvement factors (Society demand) | E35: Factor | F35: =F11/F10 -> 1 | G35: =G11/G10 -> 1.18 | H35: =H11/H10 -> 1.55
B36: 10.1 | D36: Clinker improvement factors | E36: Factor | F36: =F17/F11 -> 1 | G36: =G17/G11 -> 0.91387526 | H36: =H17/H11 -> 0.7191378
B37: 10.1.4 | D37: New binders improvement factors | E37: Factor | F37: =F15/F17 -> 1 | G37: =G15/G17 -> 1.0190644 | H37: =H15/H17 -> 1.1187745
B38: 10.2 | D38: Cement & binders improvement factors (incl. SCM) | E38: Factor | F38: =F14/F15 -> 1 | G38: =G14/G15 -> 1.0015831 | H38: =H14/H15 -> 1.0031032
B39: 10.3 | D39: Concrete improvement factors | E39: Factor | F39: =F13/F14 -> 1 | G39: =G13/G14 -> 1.0237454 | H39: =H13/H14 -> 1.0773415
B40: 10.4 | D40: Design & Construction improvement factors | E40: Factor | F40: =F12/F13 -> 1 | G40: =G12/G13 -> 1.000976 | H40: =H12/H13 -> 1.0556039
B41: 10.5 | D41: Recarbonation improvement factors | E41: Factor | F41: =F18/F12 -> 0.80657836 | G41: =G18/G12 -> 0.76763651 | H41: =H18/H12 -> 0.61434736
B42: 10.6 | D42: Carbon Capture improvement factors (CCUS) | E42: Factor | F42: =F20/F18 -> 0.98705288 | G42: =G20/G18 -> 0.97742624 | H42: =H20/H18 -> 0.009011179
D44: Version 103, 17.12.2020, ECRA

Sheet 0.2 Share of concrete
E1: Reference | L1: Colour index: | R1: End use segments | T1: README information | U1: GCCA Example | AE1: high
E2: Region | F2: ='Whole life model'!F2 -> ARGENTINA | L2: text information and descriptions | N2: default starting values, do not change | AE2: medium
E3: Organisation | F3: ='Whole life model'!F3 -> AFCP | L3: start with cement volumes | N3: Value from / to other worksheet | AE3: low
E4: corresponding author | F4: ='Whole life model'!F4 -> FICEM and AFCP | L4: then fill in all parts in green | N4: Calculated automatically | AE4: no
E5: E-mail contact | F5: ='Whole life model'!F5 -> maria.lefevre@afcp.org.ar | L5: instruction text in italics, further README information at the right side | AE5: <blank>
E6: Phone contact | F6: ='Whole life model'!F6 -> Phone
B7: ='Whole life model'!B7 -> GCCA Roadmap Template | D7: ='Whole life model'!D7 -> Version 202, 19.07.2022, ECRA | E7: Reference year | F7: ='Whole life model'!F7 -> 2020 | G7: ='Whole life model'!G7 -> 2030 | H7: ='Whole life model'!H7 -> 2050 | I7: ='Whole life model'!F7 -> 2020 | J7: ='Whole life model'!G7 -> 2030 | K7: ='Whole life model'!H7 -> 2050 | L7: ='Whole life model'!F7 -> 2020 | M7: ='Whole life model'!G7 -> 2030 | N7: ='Whole life model'!H7 -> 2050 | O7: ='Whole life model'!F7 -> 2020 | P7: ='Whole life model'!G7 -> 2030 | Q7: ='Whole life model'!H7 -> 2050
B8: Index | C8: Section / Lever | D8: Description | E8: Relevance rating or unit | G8: Readymix | J8: (Concrete, mortar, screed from ) Bagged Cement | M8: (Mortar, screed, others) Project Site Silos | P8: Precast (all factory produced product)
B9: 0.2 | C9: Cuota de segmentos de mercado de la producción de hormigón | F9: =IF(($F$16+$I$16+$L$16+$O$16)=1,"", "difference from 100% for total concrete production today") | G9: =IF(($G$16+$J$16+$M$16+$P$16)=1,"", "difference from 100% for total concrete production 2030") | H9: =IF(($H$16+$K$16+$N$16+$Q$16)=1,"", "difference from 100% for total concrete production 2050") | I9: =IF(($F$16+$I$16+$L$16+$O$16)=1,"", "difference from 100% for total concrete production today") | J9: =IF(($G$16+$J$16+$M$16+$P$16)=1,"", "difference from 100% for total concrete production 2030") | K9: =IF(($H$16+$K$16+$N$16+$Q$16)=1,"", "difference from 100% for total concrete production 2050") | L9: =IF(($F$16+$I$16+$L$16+$O$16)=1,"", "difference from 100% for total concrete production today") | M9: =IF(($G$16+$J$16+$M$16+$P$16)=1,"", "difference from 100% for total concrete production 2030") | N9: =IF(($H$16+$K$16+$N$16+$Q$16)=1,"", "difference from 100% for total concrete production 2050") | O9: =IF(($F$16+$I$16+$L$16+$O$16)=1,"", "difference from 100% for total concrete production today") | P9: =IF(($G$16+$J$16+$M$16+$P$16)=1,"", "difference from 100% for total concrete production 2030") | Q9: =IF(($H$16+$K$16+$N$16+$Q$16)=1,"", "difference from 100% for total concrete production 2050")
C10: Specify your levers with a name and short description, use given examples or define own | E10: Rate high, medium, low or no
B11: 0.2.1 | C11: Cambio embolsado a premezclado | D11: Mayor participación de RMX, menor participación de cemento embolsado | E11: high | T11: Rate relevance of "Shift bagged to Ready mix"
B12: 0.2.2 | C12: others | D12: please specifiy | E12: <blank> | K12: Summarize the integrated effect in line 0.2.5 | T12: Define own lever and rate relevance
B13: 0.2.3 | C13: others | D13: please specifiy | E13: <blank> | T13: Define own lever and rate relevance
B14: 0.2.4 | C14: others | D14: please specifiy | E14: <blank> | T14: Define own lever and rate relevance
C15: Use sheet 'User_notes' for further description and additional information
B16: 0.2.5 | C16: Participación en la producción total de concreto, información para "Modelo de vida entera", línea 0.2 | E16: % | F16: ='Whole life model'!J11 -> 0.35258964 | G16: 0.39 | H16: 0.43 | I16: ='Whole life model'!M11 -> 0.52788845 | J16: 0.47 | K16: 0.43 | L16: ='Whole life model'!P11 -> 0.069721116 | M16: 0.07 | N16: 0.07 | O16: ='Whole life model'!S11 -> 0.049800797 | P16: 0.07 | Q16: 0.07 | T16: Estimate share of total concrete production of the 4 categories (sum = 100% per year) in 2030 and 2050, information is used in "Whole life model", line 0.2
B17: 0.2.6 | C17: Cambio de cuota de mercado en comparación con el statu quo | E17: % | G17: =G16-F16 -> 0.037410359 | H17: =H16-F16 -> 0.077410359 | J17: =J16-I16 -> -0.057888446 | K17: =K16-I16 -> -0.097888446 | M17: =M16-L16 -> 0.00027888446 | N17: =N16-L16 -> 0.00027888446 | P17: =P16-O16 -> 0.020199203 | Q17: =Q16-O16 -> 0.020199203
B18: 0.2.7 | C18: Aumento de la participación del cemento en sacos (en comparación con el statu quo) | E18: % | G18: 0.05 | H18: 0.15 | J18: =J16-I16 -> -0.057888446 | K18: =K16-I16 -> -0.097888446 | M18: 0 | N18: 0 | P18: 0 | Q18: 0 | R18: =P18+M18+G18 -> 0.05 | S18: =Q18+N18+H18 -> 0.15

Sheet 4.1 Design & Construction
E1: Reference | AB1: Colour index: | AI1: README information | AJ1: GCCA Example | AT1: high
E2: Region | F2: ='Whole life model'!F2 -> ARGENTINA | AB2: text information and descriptions | AD2: default starting values, do not change | AT2: medium
E3: Organisation | F3: ='Whole life model'!F3 -> AFCP | AB3: start with cement volumes | AD3: Value from other worksheet | AT3: low
E4: corresponding author | F4: ='Whole life model'!F4 -> FICEM and AFCP | AB4: then fill in all parts in green | AD4: Calculated automatically | AT4: no
E5: E-mail contact | F5: ='Whole life model'!F5 -> maria.lefevre@afcp.org.ar | AB5: instruction text in italics, further README information at the right side | AT5: <blank>
E6: Phone contact | F6: ='Whole life model'!F6 -> Phone
B7: ='Whole life model'!B7 -> GCCA Roadmap Template | D7: ='Whole life model'!D7 -> Version 202, 19.07.2022, ECRA | E7: Reference year | I7: Concrete type | K7: Readymix | N7: (Concrete, mortar, screed from ) Bagged Cement | Q7: (Mortar, screed, others) Project Site Silos | T7: Precast (all factory produced product) | W7: Readymix | Z7: (Concrete or mortar from) Bagged Cement | AC7: Mortar, screed, others | AF7: Precast (all factory produced product)
I8: Use of concrete types | J8: Infrastructure | K8: Building - structural | L8: Building - non structural | M8: Infrastructure | N8: Building - structural | O8: Building - non structural | P8: Infrastructure | Q8: Building - structural | R8: Building - non structural | S8: Infrastructure | T8: Building - structural | U8: Building - non structural | V8: Infrastructure | W8: Building - structural | X8: Building - non structural | Y8: Infrastructure | Z8: Building - structural | AA8: Building - non structural | AB8: Infrastructure | AC8: Building - structural | AD8: Building - non structural | AE8: Infrastructure | AF8: Building - structural | AG8: Building - non structural
I9: Reference year | J9: ='Whole life model'!F7 -> 2020 | K9: ='Whole life model'!F7 -> 2020 | L9: ='Whole life model'!F7 -> 2020 | M9: ='Whole life model'!F7 -> 2020 | N9: ='Whole life model'!F7 -> 2020 | O9: ='Whole life model'!F7 -> 2020 | P9: ='Whole life model'!F7 -> 2020 | Q9: ='Whole life model'!F7 -> 2020 | R9: ='Whole life model'!F7 -> 2020 | S9: ='Whole life model'!F7 -> 2020 | T9: ='Whole life model'!F7 -> 2020 | U9: ='Whole life model'!F7 -> 2020
B10: 4.1.1 | C10: Estimated share of concrete used in different types of buildings today | J10: 0.5 | K10: 0.5 | L10: =1-K10-J10 -> 0 | M10: 0.2 | N10: 0.4 | O10: =1-N10-M10 -> 0.4 | P10: 1 | Q10: 0 | R10: =1-Q10-P10 -> 0 | S10: 0.8 | T10: 0.2 | U10: =1-T10-S10 -> 0 | AI10: Estimated share of concrete used in different types of buildings today
B11: Index | C11: Section / Lever | D11: Description | E11: Relevance rating | F11: Unit | I11: Target year | J11: ='Whole life model'!G7 -> 2030 | K11: ='Whole life model'!G7 -> 2030 | L11: ='Whole life model'!G7 -> 2030 | M11: ='Whole life model'!G7 -> 2030 | N11: ='Whole life model'!G7 -> 2030 | O11: ='Whole life model'!G7 -> 2030 | P11: ='Whole life model'!G7 -> 2030 | Q11: ='Whole life model'!G7 -> 2030 | R11: ='Whole life model'!G7 -> 2030 | S11: ='Whole life model'!G7 -> 2030 | T11: ='Whole life model'!G7 -> 2030 | U11: ='Whole life model'!G7 -> 2030 | V11: ='Whole life model'!H7 -> 2050 | W11: ='Whole life model'!H7 -> 2050 | X11: ='Whole life model'!H7 -> 2050 | Y11: ='Whole life model'!H7 -> 2050 | Z11: ='Whole life model'!H7 -> 2050 | AA11: ='Whole life model'!H7 -> 2050 | AB11: ='Whole life model'!H7 -> 2050 | AC11: ='Whole life model'!H7 -> 2050 | AD11: ='Whole life model'!H7 -> 2050 | AE11: ='Whole life model'!H7 -> 2050 | AF11: ='Whole life model'!H7 -> 2050 | AG11: ='Whole life model'!H7 -> 2050 | AJ11: Example Lever Name | AK11: Example Description
B12: 4.1.2 | C12: Estimated share of concrete used in different types of buildings 2030 and 2050 | J12: 0.5 | K12: 0.5 | L12: =1-K12-J12 -> 0 | M12: 0.2 | N12: 0.4 | O12: =1-N12-M12 -> 0.4 | P12: 1 | Q12: 0 | R12: =1-Q12-P12 -> 0 | S12: 0.8 | T12: 0.2 | U12: =1-T12-S12 -> 0 | V12: 0.5 | W12: 0.5 | X12: =1-W12-V12 -> 0 | Y12: 0.2 | Z12: 0.4 | AA12: =1-Z12-Y12 -> 0.4 | AB12: 1 | AC12: 0 | AD12: =1-AC12-AB12 -> 0 | AE12: 0.7 | AF12: 0.3 | AG12: =1-AF12-AE12 -> 0 | AI12: Estimated share of concrete used in different types of buildings 2030 and 2050
C13: Specify your levers with a name and short description, see examples for inspiration | E13: Rate high, medium, low or no | J13: Estimate total savings of levers per category in 4.1.3.4, 4.1.7, 4.1.8.4, 4.1.9.4 , take account of fact that some levers cannot be applied simultaneously or do not add up | V13: Estimate total savings of levers per category in 4.1.3.4, 4.1.7, 4.1.8.4, 4.1.9.4 , take account of fact that some levers cannot be applied simultaneously or do not add up
B14: 4.1.3 | C14: Specifications / standards | AJ14: Specifications / standards
B15: 4.1.3.1 | C15: Cambiar las especificaciones para el rendimiento | D15: Elimina la necesidad de resistencia a la compresión por rendimiento mecánico en módulo elástico | E15: high | AI15: Specify your levers with a name and short description, see examples for inspiration | AJ15: Concrete strength at 28, 56 and 91 days | AK15: Many types of concrete see their strength increase after 28 days of maturity, and this can be utilised to reduce the CO2 footprint by specifying the compression strength at later intervals. Consequences along value chain have to be considered by designer, concrete producer and contractor (execution), Danish roadmap, intiative 2.2: 5-10% cement saving (for precast structural and RMX), implementation in 2021
B16: 4.1.3.2 | C16: Aplicación | D16: Mejora en la verificación de la calidad de los materiales de construcción | E16: high | O16: Summarize the integrated effect in line 4.1.3.4 | AA16: Summarize the integrated effect in line 4.1.3.4 | AI16: Specify your levers with a name and short description, see examples for inspiration
B17: 4.1.3.3 | C17: Name of lever | D17: Short description of lever [enter reference to comment sheet, if more description is appropriate] | E17: <blank> | AI17: Specify your levers with a name and short description, see examples for inspiration
B18: 4.1.3.4 | D18: Total saving estimation (concrete volume compared to today) | F18: % binder saving vs. status quo | J18: 0 | K18: 0 | L18: 0 | M18: 0 | N18: 0 | O18: 0 | P18: 0 | Q18: 0 | R18: 0 | S18: 0 | T18: 0 | U18: 0 | V18: 0 | W18: 0 | X18: 0 | Y18: 0 | Z18: 0 | AA18: 0 | AB18: 0 | AC18: 0 | AD18: 0 | AE18: 0 | AF18: 0 | AG18: 0 | AI18: Estimate total savings of levers of category "Specifications / standards", take account of fact that some levers cannot be applied simultaneously or do not add up
B19: 4.1.4 | C19: Structural system (choice of frame/solution/element type etc) | AJ19: Structural system (choice of frame/solution/element type etc)
B20: 4.1.4.1 | C20: Uso masivo de prefabricados | D20: Implementar en la normativa el uso de la prefabricación como sistema estructural de una forma más sencilla | E20: high | AI20: Specify your levers with a name and short description, see examples for inspiration | AJ20: Precasting/prefabrication | AK20: IEA: 36% cement suse (2060) for RCC frames (10%)
B21: 4.1.4.2 | C21: Hormigones de ultra altas prestaciones | D21: El uso de hormigones de mayor rendimiento reduce el consumo de material por metro cuadrado | E21: high | AI21: Specify your levers with a name and short description, see examples for inspiration | AJ21: Topology optimization | AK21: Topology optimisation tools are increasingly being used in the industry to design components that are optimised in relation to functional properties and material consumption. Creation of completely new architectonic expression and reduce material consumption. Danish roadmap, initiative 1.3: 3,33% CO2 saving per year (for precast), implementation in 2027
B22: 4.1.4.3 | C22: Name of lever | D22: Short description of lever [enter reference to comment sheet, if more description is appropriate] | E22: <blank> | AI22: Specify your levers with a name and short description, see examples for inspiration | AJ22: Increased post-tensioned structures (building) | AK22: Post-tensioning structures is viewed as a possibility for accommodating the need for more complex and flexible buildings. It reduces or minimises the need for stabilising walls, columns and beams. Danish roadmap, initiative 1.7: 3,33% CO2 saving per year (for precast), implementation in 2021
B23: 4.1.5 | C23: Structural design (lean design, CO2 as a main critieria for design etc: resulting in material savings) | AI23: Specify your levers with a name and short description, see examples for inspiration | AJ23: Structural design (lean design, CO2 as a main critieria for design etc: resulting in material savings)
B24: 4.1.5.1 | C24: Name of lever | D24: Short description of lever [enter reference to comment sheet, if more description is appropriate] | E24: <blank> | AI24: Specify your levers with a name and short description, see examples for inspiration | AJ24: Lean design | AK24: Automated design methods will boost opportunities to calculate and optimise the individual structural elements and connections, rather than continuing to allow the structural elements that carry the heaviest load to define the entire structure. Danish roadmap iniatives 1.2: 8,33% CO2 saving per year, implementation in 2026 for precast strutural element
B25: 4.1.5.2 | C25: Name of lever | D25: Short description of lever [enter reference to comment sheet, if more description is appropriate] | E25: <blank> | O25: Summarize the integrated effect in line 4.1.7 | AA25: Summarize the integrated effect in line 4.1.7 | AI25: Specify your levers with a name and short description, see examples for inspiration
B26: 4.1.5.3 | C26: Name of lever | D26: Short description of lever [enter reference to comment sheet, if more description is appropriate] | E26: <blank> | AI26: Specify your levers with a name and short description, see examples for inspiration
B27: 4.1.6 | C27: Both structural system and design COMBINED | AI27: Specify your levers with a name and short description, see examples for inspiration | AJ27: Both structural system and design COMBINED
B28: 4.1.6.1 | C28: Diseño estructural orgánico | D28: Métodos de diseño más adecuados en función de cada elemento, para elaborar elementos más esbeltos | E28: high | AI28: Specify your levers with a name and short description, see examples for inspiration | AJ28: Lean design and structural optimization | AK28: Some references published findings for both the system and the design. Referred to as STRUCTURAL OPTIMISATION : ETH Zurich: 10-20% CO2 reduction for 2030 and 20-40% for 2050 (for precast) and for IEA: 13% cement saving (for non-precast) by 2060
B29: 4.1.6.2 | C29: Name of lever | D29: Short description of lever [enter reference to comment sheet, if more description is appropriate] | E29: <blank> | AI29: Specify your levers with a name and short description, see examples for inspiration
B30: 4.1.6.3 | C30: Name of lever | D30: Short description of lever [enter reference to comment sheet, if more description is appropriate] | E30: <blank> | AI30: Specify your levers with a name and short description, see examples for inspiration
B31: 4.1.7 | C31: Structural design and systems | D31: Total saving estimation (concrete volume compared to today) | F31: % binder saving vs. status quo | J31: 0.025 | K31: 0.025 | L31: 0.025 | M31: 0.025 | N31: 0.025 | O31: 0.025 | P31: 0.025 | Q31: 0.025 | R31: 0.025 | S31: 0.025 | T31: 0.025 | U31: 0.025 | V31: 0.05 | W31: 0.05 | X31: 0.05 | Y31: 0.05 | Z31: 0.05 | AA31: 0.05 | AB31: 0.05 | AC31: 0.05 | AD31: 0.05 | AE31: 0.05 | AF31: 0.05 | AG31: 0.05 | AI31: Estimate total savings of levers of categories "Structural system and design", take account of fact that some levers cannot be applied simultaneously or do not add up
B32: 4.1.8 | C32: Construction processes | AJ32: Construction processes
B33: 4.1.8.1 | C33: Promover la prefabricación como proceso constructivo | D33: Optimice el prefabricado para evitar el desperdicio de hormigón | E33: high | AI33: Specify your levers with a name and short description, see examples for inspiration | AJ33: Waste reduction | AK33: includes avoid over ordering, Material economics: 4,1% cement saving from building use (2050)
B34: 4.1.8.2 | C34: Name of lever | D34: Short description of lever [enter reference to comment sheet, if more description is appropriate] | E34: <blank> | O34: Summarize the integrated effect in line 4.1.8.4 | AA34: Summarize the integrated effect in line 4.1.8.4 | AI34: Specify your levers with a name and short description, see examples for inspiration
B35: 4.1.8.3 | C35: Name of lever | D35: Short description of lever [enter reference to comment sheet, if more description is appropriate] | E35: <blank> | AI35: Specify your levers with a name and short description, see examples for inspiration
B36: 4.1.8.4 | D36: Total saving estimation (concrete volume compared to today) | F36: % binder saving vs. status quo | J36: 0.01 | K36: 0.01 | L36: 0.01 | M36: 0.01 | N36: 0.01 | O36: 0.01 | P36: 0.01 | Q36: 0.01 | R36: 0.01 | S36: 0.01 | T36: 0.01 | U36: 0.01 | V36: 0.02 | W36: 0.02 | X36: 0.02 | Y36: 0.02 | Z36: 0.02 | AA36: 0.02 | AB36: 0.02 | AC36: 0.02 | AD36: 0.02 | AE36: 0.02 | AF36: 0.02 | AG36: 0.02 | AI36: Estimate total savings of levers of category "Construction processes", take account of fact that some levers cannot be applied simultaneously or do not add up
B37: 4.1.9 | C37: Re-use of concrete elements | AJ37: Re-use of concrete
B38: 4.1.9.1 | C38: Impulsar el aprovechamiento de los residuos de la construcción | D38: Incrementar los procesos industriales para la reutilización de residuos de demolición de hormigón para su uso como árido | E38: high | AI38: Specify your levers with a name and short description, see examples for inspiration | AJ38: Reuse of concrete elements | AK38: IEA: 10% cement saving (2060) for precast building (10%) ; Danish roadmap, initiatives 4.3 & 4.4: 8,33% CO2 saving per year for precast, implementation in 2025 (elements of building) ; Material economics: 8,5% cement use building. Note: reuse of crushed concrete is accounted for elsewhere
B39: 4.1.9.2 | C39: Reducción de residuos | D39: Promover el aprovechamiento del concreto devuelto evitando su disposición final o pérdida del material, mediante su uso (ejemplo: en obra: pisos de baja especificación, prefabricados, etc.) | E39: high | O39: Summarize the integrated effect in line 4.1.9.4 | AA39: Summarize the integrated effect in line 4.1.9.4 | AI39: Specify your levers with a name and short description, see examples for inspiration
B40: 4.1.9.3 | C40: Name of lever | D40: Short description of lever [enter reference to comment sheet, if more description is appropriate] | E40: <blank> | AI40: Specify your levers with a name and short description, see examples for inspiration
B41: 4.1.9.4 | D41: Total saving estimation (concrete volume compared to today) | F41: % binder saving vs. status quo | J41: 0.025 | K41: 0.025 | L41: 0.025 | M41: 0 | N41: 0 | O41: 0 | P41: 0 | Q41: 0 | R41: 0 | S41: 0 | T41: 0 | U41: 0 | V41: 0.02 | W41: 0 | X41: 0 | Y41: 0.01 | Z41: 0.05 | AA41: 0 | AB41: 0.01 | AC41: 0 | AD41: 0.05 | AE41: 0 | AF41: 0 | AG41: 0 | AI41: Estimate total savings of levers of category "Re-use of concrete", take account of fact that some levers cannot be applied simultaneously or do not add up
B42: 4.1.10 | C42: Savings per use of concrete types in % | F42: % binder saving vs. status quo | J42: =(1-(1-J41)*(1-J31)*(1-J36)*(1-J18)) -> 0.05888125 | K42: =(1-(1-K41)*(1-K31)*(1-K36)*(1-K18)) -> 0.05888125 | L42: =(1-(1-L41)*(1-L31)*(1-L36)*(1-L18)) -> 0.05888125 | M42: =(1-(1-M41)*(1-M31)*(1-M36)*(1-M18)) -> 0.03475 | N42: =(1-(1-N41)*(1-N31)*(1-N36)*(1-N18)) -> 0.03475 | O42: =(1-(1-O41)*(1-O31)*(1-O36)*(1-O18)) -> 0.03475 | P42: =(1-(1-P41)*(1-P31)*(1-P36)*(1-P18)) -> 0.03475 | Q42: =(1-(1-Q41)*(1-Q31)*(1-Q36)*(1-Q18)) -> 0.03475 | ... AG42: =(1-(1-AG41)*(1-AG31)*(1-AG36)*(1-AG18)) -> 0.069
B43: 4.1.11 | C43: Cumulated savings in % | F43: % binder saving vs. status quo | K43: =J42*J12+K42*K12+L42*L12 -> 0.05888125 | N43: =M42*M12+N42*N12+O42*O12 -> 0.03475 | Q43: =P42*P12+Q42*Q12+R42*R12 -> 0.03475 | T43: =S42*S12+T42*T12+U42*U12 -> 0.03475 | W43: =V42*V12+W42*W12+X42*X12 -> 0.07831 | Z43: =Y42*Y12+Z42*Z12+AA42*AA12 -> 0.089482 | AC43: =AB42*AB12+AC42*AC12+AD42*AD12 -> 0.07831 | AF43: =AE42*AE12+AF42*AF12+AG42*AG12 -> 0.069
B44: 4.1.12 | C44: Cumulated demands in % | F44: % binder saving vs. status quo | K44: =1-K43 -> 0.94111875 | N44: =1-N43 -> 0.96525 | Q44: =1-Q43 -> 0.96525 | T44: =1-T43 -> 0.96525 | W44: =1-W43 -> 0.92169 | Z44: =1-Z43 -> 0.910518 | AC44: =1-AC43 -> 0.92169 | AF44: =1-AF43 -> 0.931
W46: =+W43*0.42+Z43*0.43+AC43*0.07+AF43*0.07 -> 0.08167916

Sheet 1.2 Clinker EF
E1: Reference | J1: Fuel CO2 emission factors | N1: README information | Q1: Colour index:
E2: Region | F2: ='Whole life model'!F2 -> ARGENTINA | J2: default values from GCCA/CSI cement CO2 and energy protocol V3.1 | Q2: text information and descriptions | S2: default starting values, do not change
E3: Organisation | F3: ='Whole life model'!F3 -> AFCP | Q3: start with cement volumes | S3: Value from other worksheet
E4: corresponding author | F4: ='Whole life model'!F4 -> FICEM and AFCP | Q4: then fill in all parts in green | S4: Calculated automatically
E5: E-mail contact | F5: ='Whole life model'!F5 -> maria.lefevre@afcp.org.ar | Q5: instruction text in italics, further README information at the right side
E6: Phone contact | F6: ='Whole life model'!F6 -> Phone
B7: ='Whole life model'!B7 -> GCCA Roadmap Template | D7: ='Whole life model'!D7 -> Version 202, 19.07.2022, ECRA | E7: Reference year | F7: ='Whole life model'!F7 -> 2020 | G7: ='Whole life model'!G7 -> 2030 | H7: ='Whole life model'!H7 -> 2050 | J7: total CO2 EF | K7: Biomass share | L7: fossil CO2 EF | M7: remarks and readme information
B8: Index | C8: Section | D8: Description | E8: Unit | G8: Summary | J8: kg CO2/GJ | K8: % carbon from biomass | L8: kg CO2/GJ
B9: 1.2 | C9: Clinker
B10: 1.2.1 | C10: Process emissions
B11: 1.2.1.1 | D11: Calcination process emission factor | E11: kg CO2/kg clinker | F11: 0.525 | G11: 0.525 | H11: 0.525 | N11: The GCCA default value is equal to calcination process emission factor of 0.525 kg CO2/ kg clinker
B12: 1.2.1.2 | D12: Materials use and applied technologies relevant to the indicated reduction of CO2 from raw meal calcination
B13: 1.2.1.3 | E13: Mt of material, or 'x' when applicable | G13: x | H13: x | N13: Enter estimated amount of material in Mt used in a specific reference year or write 'x' to assign general applicability
B14: 1.2.1.4 | E14: Mt of material, or 'x' when applicable | H14: x | N14: Enter estimated amount of material in Mt used in a specific reference year or write 'x' to assign general applicability
B15: 1.2.1.5 | E15: Mt of material, or 'x' when applicable | N15: Enter estimated amount of material in Mt used in a specific reference year or write 'x' to assign general applicability
B16: 1.2.1.6 | D16: CO2 from organic carbon in limestone (TOC) | E16: kg CO2/kg clinker | F16: =0.002*1.55*3.664 -> 0.0113584 | G16: =0.002*1.55*3.664 -> 0.0113584 | H16: =0.002*1.55*3.664 -> 0.0113584 | N16: Estimated from GCCA CO2 protocol V3.1 default values as 0.011 kg CO2/t clinker from 0.2% of organic carbon (TOC) in raw meal
B17: 1.2.2 | C17: Fuel mix
B18: 1.2.2.1 | D18: Coal | E18: % of thermal energy demand | F18: =+'Resumen Ejes de Reduccion'!E105 -> 0 | G18: =+'Resumen Ejes de Reduccion'!F105 -> 0 | H18: =+'Resumen Ejes de Reduccion'!G105 -> 0 | J18: 96 | K18: 0 | L18: =J18*(1-K18) -> 96 | N18: Specify share of coal thermal energy, coal CO2 emission factor, biomass share for fossil fuel = 0%
B19: 1.2.2.2 | D19: Petcoke | E19: % of thermal energy demand | F19: =+'Resumen Ejes de Reduccion'!E107 -> 0.11 | G19: =+'Resumen Ejes de Reduccion'!F107 -> 0.08 | H19: =+'Resumen Ejes de Reduccion'!G107 -> 0.02 | J19: 92.8 | K19: 0 | L19: =J19*(1-K19) -> 92.8 | N19: Specify share of petcoke thermal energy, petcoke CO2 emission factor, biomass share for fossil fuel = 0%
B20: 1.2.2.3 | D20: Natural gas | E20: % of thermal energy demand | F20: =+'Resumen Ejes de Reduccion'!E109 -> 0.82 | G20: =+'Resumen Ejes de Reduccion'!F109 -> 0.82 | H20: =+'Resumen Ejes de Reduccion'!G109 -> 0.75 | J20: 56.1 | K20: 0 | L20: =J20*(1-K20) -> 56.1 | N20: Specify share of natural gas thermal energy, natural gas CO2 emission factor, biomass share for fossil fuel = 0%
B21: 1.2.2.4 | D21: Waste of fossil origin (including fossil fuel from mixed fuels) | E21: % of thermal energy demand | F21: =+'Resumen Ejes de Reduccion'!E112 -> 0.03 | G21: =+'Resumen Ejes de Reduccion'!F112 -> 0.05 | H21: =+'Resumen Ejes de Reduccion'!G112 -> 0.08 | J21: 80 | K21: 0 | L21: =J21*(1-K21) -> 80 | N21: Specify share of fossil waste thermal energy, waste CO2 emission factor. Note: The average biomass share of waste used as fuel should be assessed. The fossil fraction will then become part of line 1.2.2.4, while the biogenic fraction according to the biogenic carbon content shall be added to 1.2.2.5 (according to the biogenic carbon content, which often averages between 0% and 30%).
B22: 1.2.2.5 | D22: Biomass (including biomass from mixed fuels) | E22: % of thermal energy demand | F22: =+'Resumen Ejes de Reduccion'!E114 -> 0.04 | G22: =+'Resumen Ejes de Reduccion'!F114 -> 0.05 | H22: =+'Resumen Ejes de Reduccion'!G114 -> 0.1 | J22: 100 | K22: 1 | L22: =J22*(1-K22) -> 0 | N22: Assuming 100 kg CO2/GJ for biomass fuels [GCCA CSI CO2 Protocol V3.1 average between 110 and 89]
B23: 1.2.2.6 | D23: Optional other fuels use, specify fuel type, contribution to thermal energy demand, EF and biomass in follwoing lines
B24: 1.2.2.7 | D24: Hydrogen | E24: % of thermal energy demand | F24: =+'Resumen Ejes de Reduccion'!E116 -> 0 | G24: =+'Resumen Ejes de Reduccion'!F116 -> 0 | H24: =+'Resumen Ejes de Reduccion'!G116 -> 0.05 | J24: 0 | K24: 0 | L24: =J24*(1-K24) -> 0 | N24: Optional other fuels, please specify fuel type, contribution to thermal energy demand, EF and biomass in follwoing lines
B25: 1.2.2.8 | E25: % of thermal energy demand | F25: 0 | G25: 0 | H25: 0 | J25: 0 | K25: 0 | L25: =J25*(1-K25) -> 0 | N25: see additional default valuesin the GCCA Internet Manual of the CO2 Protocol V3.1:
B26: 1.2.2.9 | E26: % of thermal energy demand | F26: 0 | G26: 0 | H26: 0 | J26: 0 | K26: 0 | L26: =J26*(1-K26) -> 0 | N26: https://www.cement-co2-protocol.org/en/#Internet_Manual/constants.htm
B27: 1.2.2.10 | E27: % of thermal energy demand | F27: 0 | G27: 0 | H27: 0 | J27: 0 | K27: 1 | L27: =J27*(1-K27) -> 0
B28: 1.2.2.11 | E28: % of thermal energy demand | F28: 0 | G28: 0 | H28: 0 | J28: 0 | K28: 0 | L28: =J28*(1-K28) -> 0
B29: 1.2.2.12 | D29: other remaining fuels | E29: % of thermal energy demand | F29: 0 | G29: 0 | H29: 0 | J29: 0 | K29: 0 | L29: =J29*(1-K29) -> 0
B30: 1.2.2.13 | D30: Sum of fuel composition shares | E30: % of thermal energy demand | F30: =SUM(F18:F29) -> 1 | G30: =SUM(G18:G29) -> 1 | H30: =SUM(H18:H29) -> 1
B31: 1.2.3 | C31: Thermal energy demand and fuel emissions
B32: 1.2.3.1 | D32: Thermal energy demand (on annual basis) | E32: MJ/t clinker | F32: 3425 | G32: 3500 | H32: 3300 | N32: Acount for continued imporvement of specific thermal energy demand of clinker production, the value should reflect the anual basis of clinker production including heating up, kiln stoppages and times with less then 100% capacity operation The thermal energy should encompass all kiln fuels including fuels for drying of raw materials and fuels.
B33: 1.2.3.2 | D33: Technologies relevant to the indicated reduction of thermal energy demand
B34: 1.2.3.3 | E34: MJ/t clinker, or 'x' when applicable | G34: x | H34: x | N34: Enter estimated number for the reduction effect in MJ/t clinker in a specific reference year or write 'x' to assign general applicability
B35: 1.2.3.4 | E35: MJ/t clinker, or 'x' when applicable | H35: x | N35: Enter estimated number for the reduction effect in MJ/t clinker in a specific reference year or write 'x' to assign general applicability
B36: 1.2.3.5 | E36: MJ/t clinker, or 'x' when applicable | N36: Enter estimated number for the reduction effect in MJ/t clinker in a specific reference year or write 'x' to assign general applicability
B37: 1.2.3.6 | D37: Fuel CO2 emission factor (fossil CO2 only) | E37: kg CO2/GJ fuel mix | F37: =SUMPRODUCT(F18:F29,$L18:$L29) -> 58.61 | G37: =SUMPRODUCT(G18:G29,$L18:$L29) -> 57.426 | H37: =SUMPRODUCT(H18:H29,$L18:$L29) -> 50.331
B38: 1.2.3.7 | D38: Fossil fuel CO2 emissions factor | E38: kg CO2/kg clinker | F38: =F32/1000*F37/1000 -> 0.20073925 | G38: =G32/1000*G37/1000 -> 0.200991 | H38: =H32/1000*H37/1000 -> 0.1660923
B39: 1.2.3.8 | D39: Biogenic CO2 emissions from biomass combustion | E39: kg CO2/kg clinker | F39: =F32/1000*F22*$J22/1000 -> 0.0137 | G39: =G32/1000*G22*$J22/1000 -> 0.0175 | H39: =H32/1000*H22*$J22/1000 -> 0.033 | J39: =+F39*'Whole life model'!F24 -> 0.11510055 | K39: =+G39*'Whole life model'!G24 -> 0.16156666 | L39: =+H39*'Whole life model'!H24 -> 0.3449978
B40: 1.2.3.9 | D40: Clinker CO2 emission factor (direct CO2 emissions regional clinker production) | E40: kg CO2/kg clinker | F40: =F11+F16+F38 -> 0.73709765 | G40: =G11+G16+G38 -> 0.7373494 | H40: =H11+H16+H38 -> 0.7024507
B41: 1.2.3.10 | C41: Imported clinker
B42: 1.2.3.11 | D42: Share of imported clinker in reference to total clinker usage | E42: % | F42: 0 | G42: 0 | H42: 0
B43: 1.2.3.12 | D43: Imported clinker CO2 emission factor | E43: kg CO2/kg clinker | F43: 0.865 | G43: 0.865 | H43: 0.865 | N43: Default emission factor for clinker import according to GCCA Cement CO2 and Energy Protocol line 49b for 2020. Future values can be adjusted according to assumption or requirement.
B44: 1.2.4 | C44: Emission factor | D44: Clinker CO2 emission factor (direct CO2 emissions) | E44: kg CO2/kg clinker | F44: =(1-F42)*F40+F42*F43 -> 0.73709765 | G44: =(1-G42)*G40+G42*G43 -> 0.7373494 | H44: =(1-H42)*H40+H42*H43 -> 0.7024507
B45: 1.2.5 | C45: Electrical energy demand
B46: 1.2.5.1 | D46: Total electrical energy use for clinker an cement production (for info regarding indirect CO2 emissions) | E46: kWh/t cement | F46: 120 | G46: 115 | H46: 87 | N46: This information is collected for completion of energy demand information. It is not accounted in direct emission CO2 balance. Increasing efficiency affects indirect CO2 emissions.
B47: 1.2.5.2 | D47: Electrical energy production from waste heat recovery | E47: kWh/t cement | F47: 0 | G47: 0 | H47: 0 | N47: This information is collected for completion of energy demand information. It is not accounted in direct emission CO2 balance. Availability of electrical energy from WHR affects indirect CO2 emissions.

Sheet 2.2 & 2.4.2 Cement & Binder
E1: Reference | S1: README information | V1: Colour index: | AF1: high
E2: Region | F2: ='Whole life model'!F2 -> ARGENTINA | V2: text information and descriptions | X2: default starting values, do not change | AF2: medium
E3: Organisation | F3: ='Whole life model'!F3 -> AFCP | V3: start with cement volumes | X3: Value from other worksheet | AF3: low
E4: corresponding author | F4: ='Whole life model'!F4 -> FICEM and AFCP | V4: then fill in all parts in green | X4: Calculated automatically | AF4: no
E5: E-mail contact | F5: ='Whole life model'!F5 -> maria.lefevre@afcp.org.ar | V5: instruction text in italics, further README information at the right side | AF5: <blank>
E6: Phone contact | F6: ='Whole life model'!F6 -> Phone
B7: ='Whole life model'!B7 -> GCCA Roadmap Template | D7: ='Whole life model'!D7 -> Version 202, 19.07.2022, ECRA | E7: Reference year | F7: ='Whole life model'!F7 -> 2020 | G7: ='Whole life model'!G7 -> 2030 | H7: ='Whole life model'!H7 -> 2050 | I7: ='Whole life model'!F7 -> 2020 | J7: ='Whole life model'!G7 -> 2030 | K7: ='Whole life model'!H7 -> 2050 | L7: ='Whole life model'!F7 -> 2020 | M7: ='Whole life model'!G7 -> 2030 | N7: ='Whole life model'!H7 -> 2050 | O7: ='Whole life model'!F7 -> 2020 | P7: ='Whole life model'!G7 -> 2030 | Q7: ='Whole life model'!H7 -> 2050
B8: Index | C8: Section / SCM type | D8: Description of changes in SCM use | G8: Readymix | J8: (Concrete, mortar, screed from ) Bagged Cement | M8: (Mortar, screed, others) Project Site Silos | P8: Precast (all factory produced product)
D9: Name SCMs for use in concrete (2.2) and cement (2.4.2) production; use lines to descibe the expected changes | F9: Give information on relevance of different SCMs by rating with "high, medium, low or no"
B10: 2.2 | C10: SCMs in concrete | D10: Information on use of SCM in concrete production | F10: Relevance for use of SCMs in concrete production
B11: 2.2.1 | C11: Ceniza volante | D11: Continuar con el uso de cenizas volantes en la mezcla preparada, pero las cenizas volantes utilizando la extracción de cenizas volantes | F11: <blank> | G11: <blank> | H11: <blank> | I11: <blank> | J11: <blank> | K11: <blank> | L11: <blank> | M11: <blank> | N11: <blank> | O11: <blank> | P11: <blank> | Q11: <blank> | S11: Rate relevance of fly ash use for concrete production for Precast and Non-Precast today, in 2030 and 2050
B12: 2.2.2 | C12: GBFS | D12: No habrá oferta de este material. | F12: <blank> | G12: <blank> | H12: <blank> | I12: <blank> | J12: <blank> | K12: <blank> | L12: <blank> | M12: <blank> | N12: <blank> | O12: <blank> | P12: <blank> | Q12: <blank> | S12: Rate relevance of GBFS use for concrete production for Precast and Non-Precast today, in 2030 and 2050
B13: 2.2.3 | C13: Arcilla calcinada | D13: Ampliar la producción de arcillas calcinadas para consumo en hormigones | F13: <blank> | G13: <blank> | H13: <blank> | I13: <blank> | J13: <blank> | K13: <blank> | L13: <blank> | M13: <blank> | N13: <blank> | O13: <blank> | P13: <blank> | Q13: <blank> | S13: Rate relevance of calcinded clay use for concrete production for Precast and Non-Precast today, in 2030 and 2050
B14: 2.2.4 | C14: Caliza | D14: Continúe agregando piedra caliza en el concreto | F14: <blank> | G14: <blank> | H14: <blank> | I14: <blank> | J14: <blank> | K14: <blank> | L14: <blank> | M14: <blank> | N14: <blank> | O14: <blank> | P14: <blank> | Q14: <blank> | S14: Define own SCM and rate relevance for concrete production for Precast and Non-Precast today, in 2030 and 2050 or leave blank
B15: 2.2.5 | C15: Microsilicio | F15: <blank> | G15: <blank> | H15: <blank> | I15: <blank> | J15: <blank> | K15: <blank> | L15: <blank> | M15: <blank> | N15: <blank> | O15: <blank> | P15: <blank> | Q15: <blank> | S15: Define own SCM and rate relevance for concrete production for Precast and Non-Precast today, in 2030 and 2050 or leave blank
B16: 2.2.6 | C16: Metacaolín | F16: <blank> | G16: <blank> | H16: <blank> | I16: <blank> | J16: <blank> | K16: <blank> | L16: <blank> | M16: <blank> | N16: <blank> | O16: <blank> | P16: <blank> | Q16: <blank>
B18: 2.4.2 | C18: SCMs in cement | D18: Clinker factor, information on use of SCM in cement production | F18: Relevance for use of SCMs in cement production
B19: 2.4.2.1 | C19: Ceniza volante | D19: Description of changes of SCM use in cement | F19: medium | G19: medium | H19: medium | I19: low | J19: low | K19: low | L19: <blank> | M19: <blank> | N19: <blank> | O19: <blank> | P19: <blank> | Q19: <blank> | S19: Rate relevance of fly ash use for cement production for Precast and Non-Precast today, in 2030 and 2050
B20: 2.4.2.2 | C20: GBFS | D20: Description of changes of SCM use in cement | F20: low | G20: low | H20: low | I20: low | J20: low | K20: low | L20: <blank> | M20: <blank> | N20: <blank> | O20: <blank> | P20: <blank> | Q20: <blank> | S20: Rate relevance of GBFS use for cement production for Precast and Non-Precast today, in 2030 and 2050
B21: 2.4.2.3 | C21: Arcilla calcinada | D21: Description of changes of SCM use in cement | F21: no | G21: low | H21: medium | I21: no | J21: low | K21: low | L21: <blank> | M21: <blank> | N21: <blank> | O21: <blank> | P21: <blank> | Q21: <blank> | S21: Rate relevance of calcinded clay use for cement production for Precast and Non-Precast today, in 2030 and 2050
B22: 2.4.2.4 | C22: Caliza | D22: This is a filler | F22: medium | G22: medium | H22: medium | I22: high | J22: high | K22: high | L22: <blank> | M22: <blank> | N22: <blank> | O22: <blank> | P22: <blank> | Q22: <blank> | S22: Define own SCM and rate relevance for cement production for Precast and Non-Precast today, in 2030 and 2050 or leave blank
B23: 2.4.2.5 | C23: others | F23: <blank> | G23: <blank> | H23: <blank> | I23: <blank> | J23: <blank> | K23: <blank> | L23: <blank> | M23: <blank> | N23: <blank> | O23: <blank> | P23: <blank> | Q23: <blank> | S23: Define own SCM and rate relevance for cement production for Precast and Non-Precast today, in 2030 and 2050 or leave blank
C24: Use sheet 'User_notes' for further description and additional information

Sheet 3.1 Concrete production
E1: Reference | L1: Colour index: | S1: README information | T1: GCCA Example | AD1: high
E2: Region | F2: ='Whole life model'!F2 -> ARGENTINA | L2: text information and descriptions | N2: default starting values, do not change | AD2: medium
E3: Organisation | F3: ='Whole life model'!F3 -> AFCP | L3: start with cement volumes | N3: Value from / to other worksheet | AD3: low
E4: corresponding author | F4: ='Whole life model'!F4 -> FICEM and AFCP | L4: then fill in all parts in green | N4: Calculated automatically | AD4: no
E5: E-mail contact | F5: ='Whole life model'!F5 -> maria.lefevre@afcp.org.ar | L5: instruction text in italics, further README information at the right side | AD5: <blank>
E6: Phone contact | F6: ='Whole life model'!F6 -> Phone
B7: ='Whole life model'!B7 -> GCCA Roadmap Template | D7: ='Whole life model'!D7 -> Version 202, 19.07.2022, ECRA | E7: Reference year | F7: ='Whole life model'!F7 -> 2020 | G7: ='Whole life model'!G7 -> 2030 | H7: ='Whole life model'!H7 -> 2050 | I7: ='Whole life model'!F7 -> 2020 | J7: ='Whole life model'!G7 -> 2030 | K7: ='Whole life model'!H7 -> 2050 | L7: ='Whole life model'!F7 -> 2020 | M7: ='Whole life model'!G7 -> 2030 | N7: ='Whole life model'!H7 -> 2050 | O7: ='Whole life model'!F7 -> 2020 | P7: ='Whole life model'!G7 -> 2030 | Q7: ='Whole life model'!H7 -> 2050
B8: Index | C8: Section / Lever | D8: Description | E8: Relevance rating or unit | G8: Readymix | J8: (Concrete, mortar, screed from ) Bagged Cement | M8: (Mortar, screed, others) Project Site Silos | P8: Precast (all factory produced product)
B9: 3.1 | C9: Concrete efficiency gains
C10: Specify your levers with a name and short description, use given examples or define own | E10: Rate high, medium, low or no
B11: 3.1.1 | C11: Aditivos | D11: Reducción del volumen de la pasta mediante un mayor contenido de aditivo para una trabajabilidad adecuada | E11: low | S11: Rate relevance of "admixtures use" for lowering binder demand of concrete in the 4 different categories in 2030 and 2050 | T11: if fully deployed, estimated saving 2.5% of binder reduction
B12: 3.1.2 | C12: agregados | D12: Curvas granulométricas mejoradas de los áridos, depende mucho de la región y del contenido de arcilla | E12: high | S12: Rate relevance of "aggregates optimisation" for lowering binder demand of concrete in the 4 different categories in 2030 and 2050 | T12: if fully deployed, 9-16% of binder reduction
B13: 3.1.3 | C13: Control de calidad | D13: Control de calidad mejorado en la planta de RMX, solo en nivel de calidad 'regular/bueno' | E13: medium | S13: Rate relevance of "quality control" for lowering binder demand of concrete in the 4 different categories in 2030 and 2050 | T13: if fully deployed, 3-4% of binder reduction
B14: 3.1.4 | C14: Reducción de residuos | D14: Residuos de hormigón y hormigón adherido en tambor y lavado cuando regresa el camión | E14: low | S14: Rate relevance of "waste reduction" for lowering binder demand of concrete in the 4 different categories in 2030 and 2050 | T14: if fully deployed, 5-8%
B15: 3.1.5 | C15: Aprendizaje automático | D15: Mejore el diseño de la mezcla con A.I. | E15: high | K15: Summarize the integrated effect in line 3.1.10 | S15: Define own lever and rate relevance for lowering binder demand of concrete in the 4 different categories in 2030 and 2050 | T15: please give estimation
B16: 3.1.6 | C16: Otros | D16: Por favor especificar | E16: medium | S16: Define own lever and rate relevance for lowering binder demand of concrete in the 4 different categories in 2030 and 2050 | T16: please give estimation
B17: 3.1.7 | C17: others | D17: please specifiy | E17: <blank> | S17: Define own lever and rate relevance for lowering binder demand of concrete in the 4 different categories in 2030 and 2050 | T17: please give estimation
B18: 3.1.8 | C18: others | D18: please specifiy | E18: <blank> | S18: Define own lever and rate relevance for lowering binder demand of concrete in the 4 different categories in 2030 and 2050 | T18: please give estimation
B19: 3.1.9 | C19: Also | D19: please specifiy | E19: <blank> | S19: Define own lever and rate relevance for lowering binder demand of concrete in the 4 different categories in 2030 and 2050 | T19: please give estimation
C20: Use sheet 'User_notes' for further description and additional information | F20: Estimate total reduction of binder content in 2030 and 2050
B21: 3.1.10 | C21: Reduction of binder per m³ by switch from bagged to industrialised process | E21: % | F21: 0 | G21: 0.05 | H21: 0.15 | I21: 0 | J21: 0.05 | K21: 0.1 | L21: 0 | M21: 0 | N21: 0 | O21: 0 | P21: 0 | Q21: 0
B22: 3.1.11 | C22: Reduction of binder content due to shift from bagged ro industrialised process | E22: % | F22: 0 | G22: =+G21*'0.2 Share of concrete'!G18 -> 0.0025 | H22: =+H21*'0.2 Share of concrete'!H18 -> 0.0225 | I22: 0 | J22: 0 | K22: 0.1 | L22: 0 | M22: =+M21*'0.2 Share of concrete'!M18 -> 0 | N22: =+N21*'0.2 Share of concrete'!N18 -> 0 | O22: 0 | P22: =+P21*'0.2 Share of concrete'!P18 -> 0 | Q22: =+Q21*'0.2 Share of concrete'!Q18 -> 0
B23: 3.1.12 | C23: Other reduction of binder content | E23: % | F23: 0 | G23: 0 | H23: 0 | I23: 0 | J23: 0 | K23: 0 | L23: 0 | M23: 0 | N23: 0 | O23: 0 | P23: 0 | Q23: 0 | S23: Give information on binder saving in % of concrete in the 4 categories for 2030 and 2050 compared to 2020 by taking into account the cummualted savings of levers described above, GCCA expert opinion in column T may assist
B24: 3.1.13 | C24: Total demand of binder content | E24: % | F24: 1 | G24: =1-G23-G22 -> 0.9975 | H24: =1-H23-H22 -> 0.9775 | I24: 1 | J24: =1-J23-J22 -> 1 | K24: =1-K23-K22 -> 0.9 | L24: 1 | M24: =1-M23-M22 -> 1 | N24: =1-N23-N22 -> 1 | O24: 1 | P24: =1-P23-P22 -> 1 | Q24: =1-Q23-Q22 -> 1

Sheet User_notes
E1: Reference | J1: README information | L1: Colour index:
E2: Region | F2: ='Whole life model'!F2 -> ARGENTINA | L2: text information and descriptions | N2: default starting values, do not change
E3: Organisation | F3: ='Whole life model'!F3 -> AFCP | L3: start with cement volumes | N3: Value from other worksheet
E4: corresponding author | F4: ='Whole life model'!F4 -> FICEM and AFCP | L4: then fill in all parts in green | N4: Calculated automatically
E5: E-mail contact | F5: ='Whole life model'!F5 -> maria.lefevre@afcp.org.ar | L5: instruction text in italics, further README information at the right side
E6: Phone contact | F6: ='Whole life model'!F6 -> Phone
B7: ='Whole life model'!B7 -> GCCA Roadmap Template | D7: ='Whole life model'!D7 -> Version 202, 19.07.2022, ECRA | E7: Reference year | F7: ='Whole life model'!F7 -> 2020 | G7: ='Whole life model'!G7 -> 2030 | H7: ='Whole life model'!H7 -> 2050
B8: Index | C8: Section | D8: Description | E8: Unit | F8: Notes recorded by the user referring to current 2020 (2018) data | G8: Notes recorded by the user referring to 2030 data | H8: Notes recorded by the user referring to 2050 data
B9: Please identify the reference of any additional note or comment that you like to make | F9: Use cells below to make your user notes and text comments. Increase line hight, when you require more space for your note. Insert new lines at the bottom, if you like to make more notes.
B10: 1.1 | C10: Clinker | D10: Example user note on: Clinker production volume | E10: Mt | F10: Example user note text: The clinker production volume encompasses different kinds of clinker. In this example region the use of belite clinkers makes a small (ca. x Mt,) contribution to the products of the cement industry. | H10: Example user note text: With the introduction of new types of cement, the use of belite cements will change. This means that the volume of belite clinker production will increas/decrease to approximatly x Mt until 2050. | J10: Example for a user note
B11: x.x | C11: Section or lever name | D11: Line description | E11: Unit | F11: Enter your note refering to current, i.e. 2018 or 2020 data here | G11: Enter your note refering to 2030 data here | H11: Enter your note refering to 2050 data here | J11: Overwrite this entry with your own notes and text comments,
J12: Please reference the line index and name of section, lever and description of the specific line.
J13: Use columns F, G, H as apropriate for clear attribution of your note or comment to a specific year, cell or value

Sheet Argentina
B2: DISEÑO Y CONSTRUCCION - 4.1 Design & Construction
D4: Ready Mix
D5: 2020 | G5: 2030 | J5: 2050
D6: Infraestructura | E6: Construccion Estructural | F6: Construccion No Estructural | G6: Infraestructura | H6: Construccion Estructural | I6: Construccion No Estructural | J6: Infraestructura | K6: Construccion Estructural | L6: Construccion No Estructural | N6: Construcción Estructural
C7: Proporción estimada de concreto utilizado en diferentes tipos de edificios en la actualidad | D7: 0 | E7: 0 | F7: =100%-D7-E7 -> 1 | G7: N/A | H7: N/A | I7: N/A | J7: N/A | K7: N/A | L7: N/A | N7: Componentes: Vigas, columnas, fundaciones, losas
C8: Proporción estimada de concreto utilizado en diferentes tipos de edificios 2030 y 2050 | D8: N/A | E8: N/A | F8: N/A | N8: Construcción No Estructural
B9: Ahorros Estimados de Concreto | C9: Especificaciones / Estándares | D9: N/A | E9: N/A | F9: N/A | N9: Componentes: cielos, paredes livianas
C10: Diseño estructural y sistemas. | D10: N/A | E10: N/A | F10: N/A
C11: Procesos Constructivos | D11: N/A | E11: N/A | F11: N/A
C12: Re-utilización elementos de concreto | D12: N/A | E12: N/A | F12: N/A
C13: Ahorro por uso tipos de concreto % | D13: N/A | E13: N/A | F13: N/A | G13: =+(1-(1-G9)*(1-G10)*(1-G11)*(1-G12)) -> 0 | H13: =+(1-(1-H9)*(1-H10)*(1-H11)*(1-H12)) -> 0 | I13: =+(1-(1-I9)*(1-I10)*(1-I11)*(1-I12)) -> 0 | J13: =+(1-(1-J9)*(1-J10)*(1-J11)*(1-J12)) -> 0 | K13: =+(1-(1-K9)*(1-K10)*(1-K11)*(1-K12)) -> 0 | L13: =+(1-(1-L9)*(1-L10)*(1-L11)*(1-L12)) -> 0
C14: Ahorros Acumulados % | D14: N/A | E14: N/A | F14: N/A | G14: =+G8*G13+H8*H13+I8*I13 -> 0 | J14: =+J8*J13+K8*K13+L8*L13 -> 0
C15: Demanda Acumulada % | D15: N/A | E15: N/A | F15: N/A | G15: =1-G14 -> 1 | J15: =1-J14 -> 1
D17: Cemento en Sacos
D18: 2020 | G18: 2030 | J18: 2050
D19: Infraestructura | E19: Construccion Estructural | F19: Construccion No Estructural | G19: Infraestructura | H19: Construccion Estructural | I19: Construccion No Estructural | J19: Infraestructura | K19: Construccion Estructural | L19: Construccion No Estructural
C20: Proporción estimada de concreto utilizado en diferentes tipos de edificios en la actualidad | D20: 0 | E20: 0 | F20: =100%-D20-E20 -> 1 | G20: N/A | H20: N/A | I20: N/A | J20: N/A | K20: N/A | L20: N/A
C21: Proporción estimada de concreto utilizado en diferentes tipos de edificios 2030 y 2050 | D21: N/A | E21: N/A | F21: N/A
B22: Ahorros Estimados de Concreto | C22: Especificaciones / Estándares | D22: N/A | E22: N/A | F22: N/A
C23: Diseño estructural y sistemas. | D23: N/A | E23: N/A | F23: N/A
C24: Procesos Constructivos | D24: N/A | E24: N/A | F24: N/A
C25: Re-utilización elementos de concreto | D25: N/A | E25: N/A | F25: N/A
C26: Ahorro por uso tipos de concreto % | D26: N/A | E26: N/A | F26: N/A | G26: =+(1-(1-G22)*(1-G23)*(1-G24)*(1-G25)) -> 0 | H26: =+(1-(1-H22)*(1-H23)*(1-H24)*(1-H25)) -> 0 | I26: =+(1-(1-I22)*(1-I23)*(1-I24)*(1-I25)) -> 0 | J26: =+(1-(1-J22)*(1-J23)*(1-J24)*(1-J25)) -> 0 | K26: =+(1-(1-K22)*(1-K23)*(1-K24)*(1-K25)) -> 0 | L26: =+(1-(1-L22)*(1-L23)*(1-L24)*(1-L25)) -> 0
C27: Ahorros Acumulados % | D27: N/A | E27: N/A | F27: N/A | G27: =+G21*G26+H21*H26+I21*I26 -> 0 | J27: =+J21*J26+K21*K26+L21*L26 -> 0
C28: Demanda Acumulada % | D28: N/A | E28: N/A | F28: N/A | G28: =1-G27 -> 1 | J28: =1-J27 -> 1
D30: Silos en Obra
D31: 2020 | G31: 2030 | J31: 2050
D32: Infraestructura | E32: Construccion Estructural | F32: Construccion No Estructural | G32: Infraestructura | H32: Construccion Estructural | I32: Construccion No Estructural | J32: Infraestructura | K32: Construccion Estructural | L32: Construccion No Estructural
C33: Proporción estimada de concreto utilizado en diferentes tipos de edificios en la actualidad | D33: 0 | E33: 0 | F33: =100%-D33-E33 -> 1 | G33: N/A | H33: N/A | I33: N/A | J33: N/A | K33: N/A | L33: N/A
C34: Proporción estimada de concreto utilizado en diferentes tipos de edificios 2030 y 2050 | D34: N/A | E34: N/A | F34: N/A
B35: Ahorros Estimados de Concreto | C35: Especificaciones / Estándares | D35: N/A | E35: N/A | F35: N/A
C36: Diseño estructural y sistemas. | D36: N/A | E36: N/A | F36: N/A
C37: Procesos Constructivos | D37: N/A | E37: N/A | F37: N/A
C38: Re-utilización elementos de concreto | D38: N/A | E38: N/A | F38: N/A
C39: Ahorro por uso tipos de concreto % | D39: N/A | E39: N/A | F39: N/A | G39: =+(1-(1-G35)*(1-G36)*(1-G37)*(1-G38)) -> 0 | H39: =+(1-(1-H35)*(1-H36)*(1-H37)*(1-H38)) -> 0 | I39: =+(1-(1-I35)*(1-I36)*(1-I37)*(1-I38)) -> 0 | J39: =+(1-(1-J35)*(1-J36)*(1-J37)*(1-J38)) -> 0 | K39: =+(1-(1-K35)*(1-K36)*(1-K37)*(1-K38)) -> 0 | L39: =+(1-(1-L35)*(1-L36)*(1-L37)*(1-L38)) -> 0
C40: Ahorros Acumulados % | D40: N/A | E40: N/A | F40: N/A | G40: =+G34*G39+H34*H39+I34*I39 -> 0 | J40: =+J34*J39+K34*K39+L34*L39 -> 0
C41: Demanda Acumulada % | D41: N/A | E41: N/A | F41: N/A | G41: =1-G40 -> 1 | J41: =1-J40 -> 1
D43: Prefabricados
D44: 2020 | G44: 2030 | J44: 2050
D45: Infraestructura | E45: Construccion Estructural | F45: Construccion No Estructural | G45: Infraestructura | H45: Construccion Estructural | I45: Construccion No Estructural | J45: Infraestructura | K45: Construccion Estructural | L45: Construccion No Estructural
C46: Proporción estimada de concreto utilizado en diferentes tipos de edificios en la actualidad | D46: 0 | E46: 0 | F46: =100%-D46-E46 -> 1 | G46: N/A | H46: N/A | I46: N/A | J46: N/A | K46: N/A | L46: N/A
C47: Proporción estimada de concreto utilizado en diferentes tipos de edificios 2030 y 2050 | D47: N/A | E47: N/A | F47: N/A
B48: Ahorros Estimados de Concreto | C48: Especificaciones / Estándares | D48: N/A | E48: N/A | F48: N/A
C49: Diseño estructural y sistemas. | D49: N/A | E49: N/A | F49: N/A
C50: Procesos Constructivos | D50: N/A | E50: N/A | F50: N/A
C51: Re-utilización elementos de concreto | D51: N/A | E51: N/A | F51: N/A
C52: Ahorro por uso tipos de concreto % | D52: N/A | E52: N/A | F52: N/A | G52: =+(1-(1-G48)*(1-G49)*(1-G50)*(1-G51)) -> 0 | H52: =+(1-(1-H48)*(1-H49)*(1-H50)*(1-H51)) -> 0 | I52: =+(1-(1-I48)*(1-I49)*(1-I50)*(1-I51)) -> 0 | J52: =+(1-(1-J48)*(1-J49)*(1-J50)*(1-J51)) -> 0 | K52: =+(1-(1-K48)*(1-K49)*(1-K50)*(1-K51)) -> 0 | L52: =+(1-(1-L48)*(1-L49)*(1-L50)*(1-L51)) -> 0
C53: Ahorros Acumulados % | D53: N/A | E53: N/A | F53: N/A | G53: =+G47*G52+H47*H52+I47*I52 -> 0 | J53: =+J47*J52+K47*K52+L47*L52 -> 0
C54: Demanda Acumulada % | D54: N/A | E54: N/A | F54: N/A | G54: =1-G53 -> 1 | J54: =1-J53 -> 1
B57: PROPORCION CONCRETO - 0.2 Share of Concrete
D59: Readymix | G59: Cemento en Sacos | J59: Silos en Obra | M59: Prefabricados
D60: 2020 | E60: 2030 | F60: 2050 | G60: 2020 | H60: 2030 | I60: 2050 | J60: 2020 | K60: 2030 | L60: 2050 | M60: 2020 | N60: 2030 | O60: 2050
C61: Participación en producción total concreto | D61: 0.21 | G61: 0.7 | J61: 0.06 | M61: 0.03
C62: Cambio cuota mercado comparada con BAU | D62: N/A | E62: =+E61-D61 -> -0.21 | F62: =+F61-D61 -> -0.21 | G62: N/A | H62: =+H61-G61 -> -0.7 | I62: =+I61-G61 -> -0.7 | J62: N/A | K62: =+K61-J61 -> -0.06 | L62: =+L61-J61 -> -0.06 | M62: N/A | N62: =+N61-M61 -> -0.03 | O62: =+O61-M61 -> -0.03
C63: Aumento cemento en sacos comparada con BAU | D63: N/A | G63: N/A | H63: =+H61-G61 -> -0.7 | I63: =+I61-G61 -> -0.7 | J63: N/A | M63: N/A
D65: Celda Roja | E65: → | F65: Celda calculada desde otra hoja del libro
D66: Amarilla | E66: → | F66: Celda calculada en esta hoja del libro
B68: PRODUCCION DE CONCRETO - 3.1 Concrete Production
D70: Readymix | G70: Cemento en Sacos | J70: Silos en Obra | M70: Prefabricados
D71: 2020 | E71: 2030 | F71: 2050 | G71: 2020 | H71: 2030 | I71: 2050 | J71: 2020 | K71: 2030 | L71: 2050 | M71: 2020 | N71: 2030 | O71: 2050
C72: Reducción binder/m³ por cambio saco a industrializado | D72: 0 | G72: 0 | J72: 0 | M72: 0
C73: Reducción binder por cambio saco a industrializado | D73: 0 | G73: 0 | J73: 0 | M73: 0
C74: Otra reducción del contenido binder | D74: 0 | G74: 0 | H74: 0.05 | I74: 0.1 | J74: 0 | M74: 0
C75: Demanda total de contenido binder | D75: 1 | E75: =1-E73-E74 -> 1 | F75: =1-F73-F74 -> 1 | G75: 1 | H75: =1-H73-H74 -> 0.95 | I75: =1-I73-I74 -> 0.9 | J75: 1 | K75: =1-K73-K74 -> 1 | L75: =1-L73-L74 -> 1 | M75: 1 | N75: =1-N73-N74 -> 1 | O75: =1-O73-O74 -> 1
D78: Celda Amarilla | E78: → | F78: Celda calculada desde celdas de esta hoja
D79: Celda Azul | E79: → | F79: Celda con valor por defecto

Sheet Ejes HR
B2: ESCENARIO EMISIONES 2050
B4: Las emisiones proyectadas al año 2050 se calculan a partir de la línea base de emisiones al año 2020(*), y el incremento de producción de cemento al 2050 sin eficiencias (58%), según escenario BAU (Business as Usual), que significa producir y utilizar el cemento bajo las mismas condiciones actuales en el 2050.
B6: Las emisiones LB2020 fueron 6,9 MtCO2e, considerando emisiones directas (6,5 MtCO2e) e indirectas del uso de energía eléctrica (0,4 MtCO2e). Al año 2050, se consideró un aumento del 58% del consumo de cemento, que implica llegar a 19,5 Mt, lo que significaría 10,7 MtCO2e de emisiones totales BAU. | V6: Medida D&C | Z6: Potencial Reducción | AA6: Factibilidad Aplicación
V8: Extender la vida útil de las estructuras (reúso, refuncionalización, etc) | Z8: Alto | AA8: Bajo
B10: DISEÑO Y CONSTRUCCION | V10: Optimización estructural (pretensado / postensado, sistemas estructurales mixtos e híbridos, lean design, BIM, AI para diseño estructural, etc) | Z10: Alto | AA10: Medio
B12: Aumentar la eficiencia en el uso de concreto en la construcción, a través de la inclusión de etapas y actividades aguas arriba y aguas abajo de la industria del cemento y concreto – como diseño, planificación, especificación y construcción – significa, entre otros, no sobre utilizar concreto, si no el volumen más bajo posible que cumpla con los requisitos de aplicación sin comprometer durabilidad y seguridad.
V13: Industrialización (incluye prefabricación) | Z13: Medio | AA13: Medio
B14: Algunas aplicaciones son: elementos de fachada tipo sándwich; diseño con AI y optimización elementos estructurales; cálculos de diseño lineal/elásticos hasta cálculos basados en plasticidad, reutilización residuos de concreto, entre otros. Proyectistas, diseñadores, especificadores, inspectores y directores de obra, contratistas y el Poder Público tienen un rol central para su despliegue. | V14: Reducción y reciclaje de RCD | Z14: Medio | AA14: Alto
V15: Especificación de concreto (solicitud sin exceso; desagregar especificación por tipos de elementos; 56 o 90 días como edad de diseño; P2P; uso de concreto de alta resistencia en elementos comprimidos ) | Z15: Medio | AA15: Medio
B17: EFICIENCIA PRODUCCION CONCRETO
B20: La optimización en la producción de concreto, implica hacer más eficiente el uso del cemento en el concreto, para una prestación de referencia, reduciendo, además, la huella de carbono del concreto. Esta mejora se debe lograr sin comprometer la calidad del producto.
B21: actualmente, la composición de la fabricación del concreto en LAC, se distribuye de la siguiente manera: 28% de premezclado, 64% de cemento en sacos; 5% de mezcla en silos de obra; 3% de prefabricados. Se proyecta, que para el año 2050, la distribución sea de la siguiente forma: 45% de premezclado, 40% de cemento en sacos; 5% de mezcla en silos de obra; 10% de prefabricados; aumentando así la industrialización en este proceso.
B26: CEMENTO Y ADICIONES
B28: El parámetro más importante para determinar las emisiones de CO2e del cemento es su contenido o porcentaje de clínker, que se conoce como factor clínker. A nivel global, según datos reportados en GNR al año 2022, el factor clínker fue de 77%, el cual junto al yeso (5%), caliza (9%), puzolana (2%), escoria (3%); cenizas (3%) y otras adiciones (1%), forman el cemento.
B30: En LAC, el porcentaje de clínker es de 67%, 10 puntos porcentuales bajo el valor global, debido a la mayor disponibilidad de adiciones como las puzolanas, escoria y cenizas en nuestra región lo que resulta en un producto con menores emisiones de CO2e. Los porcentajes de composición del cemento en LAC son los siguientes: yeso (6%), caliza (11%), puzolana (11%), escoria (2%); cenizas (2%) y otras adiciones (1%) y clínker (67%).
B35: EFICIENCIA TERMICA
B37: Este eje depende de varios factores, entre los que se destacan la preparación de materias pimas y combustibles, el aumento en la capacidad de los hornos, el cambio de hornos largos a hornos con 6 etapas y precalcinador y uso de enfriadores de clínker con tecnología eficiente. El promedio global reportado en GNR año 2022 es de 3501 MJ/tclínker.
B39: Actualmente, en LAC, según datos de GNR del año 2022, el 55% de los hornos son de tipo proceso seco, con precalentador y precalcinador, mientras que un 24% de hornos operan con proceso seco, con precalentador y sin precalcinador, un 1% de hornos largos sin precalcinador, 18% de hornos mixtos; y el 2% restante corresponde a hornos verticales con proceso húmedo. Los valores de energía específica se encuentran entre los 3465 MJ/tclínker y los 6405 MJ/tclínker. El promedio en LAC es de 3576 MJ/tclínker.
B43: COMBUSTIBLES FOSILES TRADICIONALES

Sheet Graficos
C2: FACTOR CLINKER | M2: COPROCESAMIENTO | V2: % CEMENTO EN SACOS | AE2: EFICIENCIA TERMICA | AN2: AUMENTO DEMANDA
C38: Factor Clinker | D38: 2020 | E38: 2030 | F38: 2040 | G38: 2050 | M38: Coprocesamiento | N38: 2020 | O38: 2030 | P38: 2040 | Q38: 2050 | V38: % Cemento Sacos | W38: 2020 | X38: 2030 | Y38: 2040 | Z38: 2050 | AF38: Eficiencia Térmica | AG38: 2020 | AH38: 2030 | AI38: 2040 | AJ38: 2050 | AN38: Aumento Demanda | AO38: 2030 | AP38: 2040 | AQ38: 2050
C39: FICEM | D39: 67 | E39: 66 | F39: =AVERAGE(E39,G39) -> 63 | G39: 60 | M39: FICEM | N39: 14 | O39: 28 | P39: =AVERAGE(O39,Q39) -> 44 | Q39: 60 | V39: FICEM | W39: 64 | X39: 59 | Y39: =AVERAGE(X39,Z39) -> 49.5 | Z39: 40 | AF39: FICEM | AG39: 3.6 | AH39: 3.5 | AI39: =AVERAGE(AH39,AJ39) -> 3.45 | AJ39: 3.4 | AN39: FICEM | AO39: 20 | AP39: =AVERAGE(AO39,AQ39) -> 45 | AQ39: 70
C40: Perú | D40: 75 | E40: 70 | F40: =AVERAGE(E40,G40) -> 68.5 | G40: 67 | M40: Perú | N40: 0 | O40: 12 | P40: =+AVERAGE(O40,Q40) -> 21 | Q40: 30 | V40: Perú | W40: 78.1 | X40: 75 | Y40: =+AVERAGE(X40,Z40) -> 72.5 | Z40: 70 | AF40: Perú | AG40: 3.4 | AH40: 3.2 | AI40: =AVERAGE(AH40,AJ40) -> 3.15 | AJ40: 3.1 | AN40: Perú | AO40: 20 | AP40: =AVERAGE(AO40,AQ40) -> 50 | AQ40: 80
C41: Colombia | D41: 69 | E41: 64 | F41: =AVERAGE(E41,G41) -> 59.5 | G41: 55 | M41: Colombia | N41: 9 | O41: 18 | P41: =AVERAGE(O41,Q41) -> 29 | Q41: 40 | V41: Colombia | W41: 69 | X41: 64 | Y41: =AVERAGE(X41,Z41) -> 57 | Z41: 50 | AF41: Colombia | AG41: 4.1 | AH41: 3.8 | AI41: =AVERAGE(AH41,AJ41) -> 3.65 | AJ41: 3.5 | AN41: Colombia | AO41: 20 | AP41: =AVERAGE(AO41,AQ41) -> 35 | AQ41: 50
C42: Chile | D42: 71 | E42: 68 | F42: =AVERAGE(E42,G42) -> 65.5 | G42: 63 | M42: Chile | N42: 16 | O42: 37 | P42: =AVERAGE(O42,Q42) -> 62.5 | Q42: 88 | V42: Chile | W42: 30 | X42: 25 | Y42: =AVERAGE(X42,Z42) -> 17.5 | Z42: 10 | AF42: Chile | AG42: 3.9 | AH42: 3.5 | AI42: =AVERAGE(AH42,AJ42) -> 3.4 | AJ42: 3.3 | AN42: Chile | AO42: 10 | AP42: =AVERAGE(AO42,AQ42) -> 25 | AQ42: 40
C43: Argentina | D43: 68 | E43: 65 | F43: =AVERAGE(E43,G43) -> 63 | G43: 61 | M43: Argentina | N43: 7 | O43: 10 | P43: =AVERAGE(O43,Q43) -> 14 | Q43: 18 | V43: Global GNR | AF43: Argentina | AG43: 3.42 | AH43: 3.4 | AI43: =AVERAGE(AH43,AJ43) -> 3.35 | AJ43: 3.3 | AN43: Argentina | AO43: 18 | AP43: =AVERAGE(AO43,AQ43) -> 36.5 | AQ43: 55
C44: Global GNR | M44: Global GNR | AF44: Global GNR | AN44: Global GNR

Sheet User_calculations
G1: Reference
G2: Region | I2: ='Whole life model'!F2 -> ARGENTINA
G3: Organisation | I3: ='Whole life model'!F3 -> AFCP
G4: corresponding author | I4: ='Whole life model'!F4 -> FICEM and AFCP
G5: E-mail contact | I5: ='Whole life model'!F5 -> maria.lefevre@afcp.org.ar
B6: ='Whole life model'!B7 -> GCCA Roadmap Template | D6: ='Whole life model'!D7 -> Version 202, 19.07.2022, ECRA | G6: Phone contact | I6: ='Whole life model'!F6 -> Phone
B7: Space for any additional side calculation by the user
B8: Referring to | C8: Index | D8: Section | E8: Please, add your specific sources of information for the calculation as references, e.g. statistical data, reports and publications as appropriate.
E10: Add your side calculations here

Sheet Stacked areas data
B9: Direct CO2 emissions | C9: Indirect CO2 emissions | D9: CCUS | E9: Fossil waste fuels | F9: Recarbonation | G9: Clinker | H9: Electricity | I9: New binders | J9: Cement & binders | K9: Concrete | L9: Design & Construction | M9: Societal demand
A10: 2020 | B10: ='Waterfall data'!Q10-'Whole life model'!F34 -> 4.9135975 | C10: ='Waterfall data'!R10 -> 0.42043473 | D10: 0 | E10: 0 | F10: ='Whole life model'!F34 -> 1.2791284 | G10: 0 | H10: 0 | I10: 0 | J10: 0 | K10: 0 | L10: 0 | M10: =B10+C10+F10 -> 6.6131606
B11: =B10+((B$20-B$10)/($A$20-$A$10)) -> 4.9483476 | C11: =C10+((C$20-C$10)/($A$20-$A$10)) -> 0.4119384 | D11: =D10+((D$20-D$10)/($A$20-$A$10)) -> 0 | E11: =E10+((E$20-E$10)/($A$20-$A$10)) -> 0.012925333 | F11: =F10+((F$20-F$10)/($A$20-$A$10)) -> 1.2917785 | G11: =G10+((G$20-G$10)/($A$20-$A$10)) -> #VALUE! | H11: =H10+((H$20-H$10)/($A$20-$A$10)) -> 0.013827739 | I11: =I10+((I$20-I$10)/($A$20-$A$10)) -> 0 | ... M11: =M10+((M$20-M$10)/($A$20-$A$10)) -> 6.7321975
B12: =B11+((B$20-B$10)/($A$20-$A$10)) -> 4.9830976 | C12: =C11+((C$20-C$10)/($A$20-$A$10)) -> 0.40344207 | D12: =D11+((D$20-D$10)/($A$20-$A$10)) -> 0 | E12: =E11+((E$20-E$10)/($A$20-$A$10)) -> 0.025850666 | F12: =F11+((F$20-F$10)/($A$20-$A$10)) -> 1.3044287 | G12: =G11+((G$20-G$10)/($A$20-$A$10)) -> #VALUE! | H12: =H11+((H$20-H$10)/($A$20-$A$10)) -> 0.027655477 | I12: =I11+((I$20-I$10)/($A$20-$A$10)) -> 0 | ... M12: =M11+((M$20-M$10)/($A$20-$A$10)) -> 6.8512344
B13: =B12+((B$20-B$10)/($A$20-$A$10)) -> 5.0178476 | C13: =C12+((C$20-C$10)/($A$20-$A$10)) -> 0.39494574 | D13: =D12+((D$20-D$10)/($A$20-$A$10)) -> 0 | E13: =E12+((E$20-E$10)/($A$20-$A$10)) -> 0.038775999 | F13: =F12+((F$20-F$10)/($A$20-$A$10)) -> 1.3170788 | G13: =G12+((G$20-G$10)/($A$20-$A$10)) -> #VALUE! | H13: =H12+((H$20-H$10)/($A$20-$A$10)) -> 0.041483216 | I13: =I12+((I$20-I$10)/($A$20-$A$10)) -> 0 | ... M13: =M12+((M$20-M$10)/($A$20-$A$10)) -> 6.9702713
B14: =B13+((B$20-B$10)/($A$20-$A$10)) -> 5.0525977 | C14: =C13+((C$20-C$10)/($A$20-$A$10)) -> 0.38644941 | D14: =D13+((D$20-D$10)/($A$20-$A$10)) -> 0 | E14: =E13+((E$20-E$10)/($A$20-$A$10)) -> 0.051701332 | F14: =F13+((F$20-F$10)/($A$20-$A$10)) -> 1.329729 | G14: =G13+((G$20-G$10)/($A$20-$A$10)) -> #VALUE! | H14: =H13+((H$20-H$10)/($A$20-$A$10)) -> 0.055310954 | I14: =I13+((I$20-I$10)/($A$20-$A$10)) -> 0 | ... M14: =M13+((M$20-M$10)/($A$20-$A$10)) -> 7.0893082
B15: =B14+((B$20-B$10)/($A$20-$A$10)) -> 5.0873477 | C15: =C14+((C$20-C$10)/($A$20-$A$10)) -> 0.37795308 | D15: =D14+((D$20-D$10)/($A$20-$A$10)) -> 0 | E15: =E14+((E$20-E$10)/($A$20-$A$10)) -> 0.064626665 | F15: =F14+((F$20-F$10)/($A$20-$A$10)) -> 1.3423792 | G15: =G14+((G$20-G$10)/($A$20-$A$10)) -> #VALUE! | H15: =H14+((H$20-H$10)/($A$20-$A$10)) -> 0.069138693 | I15: =I14+((I$20-I$10)/($A$20-$A$10)) -> 0 | ... M15: =M14+((M$20-M$10)/($A$20-$A$10)) -> 7.2083451
B16: =B15+((B$20-B$10)/($A$20-$A$10)) -> 5.1220977 | C16: =C15+((C$20-C$10)/($A$20-$A$10)) -> 0.36945675 | D16: =D15+((D$20-D$10)/($A$20-$A$10)) -> 0 | E16: =E15+((E$20-E$10)/($A$20-$A$10)) -> 0.077551998 | F16: =F15+((F$20-F$10)/($A$20-$A$10)) -> 1.3550293 | G16: =G15+((G$20-G$10)/($A$20-$A$10)) -> #VALUE! | H16: =H15+((H$20-H$10)/($A$20-$A$10)) -> 0.082966432 | I16: =I15+((I$20-I$10)/($A$20-$A$10)) -> 0 | ... M16: =M15+((M$20-M$10)/($A$20-$A$10)) -> 7.327382
B17: =B16+((B$20-B$10)/($A$20-$A$10)) -> 5.1568478 | C17: =C16+((C$20-C$10)/($A$20-$A$10)) -> 0.36096042 | D17: =D16+((D$20-D$10)/($A$20-$A$10)) -> 0 | E17: =E16+((E$20-E$10)/($A$20-$A$10)) -> 0.090477331 | F17: =F16+((F$20-F$10)/($A$20-$A$10)) -> 1.3676795 | G17: =G16+((G$20-G$10)/($A$20-$A$10)) -> #VALUE! | H17: =H16+((H$20-H$10)/($A$20-$A$10)) -> 0.09679417 | I17: =I16+((I$20-I$10)/($A$20-$A$10)) -> 0 | ... M17: =M16+((M$20-M$10)/($A$20-$A$10)) -> 7.4464189
B18: =B17+((B$20-B$10)/($A$20-$A$10)) -> 5.1915978 | C18: =C17+((C$20-C$10)/($A$20-$A$10)) -> 0.35246409 | D18: =D17+((D$20-D$10)/($A$20-$A$10)) -> 0 | E18: =E17+((E$20-E$10)/($A$20-$A$10)) -> 0.10340266 | F18: =F17+((F$20-F$10)/($A$20-$A$10)) -> 1.3803296 | G18: =G17+((G$20-G$10)/($A$20-$A$10)) -> #VALUE! | H18: =H17+((H$20-H$10)/($A$20-$A$10)) -> 0.11062191 | I18: =I17+((I$20-I$10)/($A$20-$A$10)) -> 0 | ... M18: =M17+((M$20-M$10)/($A$20-$A$10)) -> 7.5654558
B19: =B18+((B$20-B$10)/($A$20-$A$10)) -> 5.2263478 | C19: =C18+((C$20-C$10)/($A$20-$A$10)) -> 0.34396776 | D19: =D18+((D$20-D$10)/($A$20-$A$10)) -> 0 | E19: =E18+((E$20-E$10)/($A$20-$A$10)) -> 0.116328 | F19: =F18+((F$20-F$10)/($A$20-$A$10)) -> 1.3929798 | G19: =G18+((G$20-G$10)/($A$20-$A$10)) -> #VALUE! | H19: =H18+((H$20-H$10)/($A$20-$A$10)) -> 0.12444965 | I19: =I18+((I$20-I$10)/($A$20-$A$10)) -> 0 | ... M19: =M18+((M$20-M$10)/($A$20-$A$10)) -> 7.6844927
A20: 2030 | B20: ='Waterfall data'!Q21 -> 5.2610979 | C20: ='Waterfall data'!R21 -> 0.33547143 | D20: 0 | E20: ='Waterfall data'!T19 -> 0.12925333 | F20: ='Waterfall data'!T18 -> 1.40563 | G20: ='Waterfall data'!T17 | H20: ='Waterfall data'!T16 -> 0.13827739 | I20: 0 | J20: ='Waterfall data'!T14 -> 0.17284107 | K20: ='Waterfall data'!T13 -> 0.0072725528 | L20: ='Waterfall data'!T12 -> 0.34450103 | M20: =M10+'Waterfall data'!S11 -> 7.8035296
B21: =B20+((B$40-B$20)/($A$40-$A$20)) -> 4.998043 | C21: =C20+((C$40-C$20)/($A$40-$A$20)) -> 0.32130198 | D21: =D20+((D$40-D$20)/($A$40-$A$20)) -> 0.2753437 | E21: =E20+((E$40-E$20)/($A$40-$A$20)) -> 0.13383059 | F21: =F20+((F$40-F$20)/($A$40-$A$20)) -> 1.4149332 | G21: =G20+((G$40-G$20)/($A$40-$A$20)) -> #VALUE! | H21: =H20+((H$40-H$20)/($A$40-$A$20)) -> 0.15708988 | I21: =I20+((I$40-I$20)/($A$40-$A$20)) -> 0 | ... M21: =M20+((M$40-M$20)/($A$40-$A$20)) -> 7.925873
B22: =B21+((B$40-B$20)/($A$40-$A$20)) -> 4.7349881 | C22: =C21+((C$40-C$20)/($A$40-$A$20)) -> 0.30713253 | D22: =D21+((D$40-D$20)/($A$40-$A$20)) -> 0.5506874 | E22: =E21+((E$40-E$20)/($A$40-$A$20)) -> 0.13840786 | F22: =F21+((F$40-F$20)/($A$40-$A$20)) -> 1.4242364 | G22: =G21+((G$40-G$20)/($A$40-$A$20)) -> #VALUE! | H22: =H21+((H$40-H$20)/($A$40-$A$20)) -> 0.17590237 | I22: =I21+((I$40-I$20)/($A$40-$A$20)) -> 0 | ... M22: =M21+((M$40-M$20)/($A$40-$A$20)) -> 8.0482165
B23: =B22+((B$40-B$20)/($A$40-$A$20)) -> 4.4719332 | C23: =C22+((C$40-C$20)/($A$40-$A$20)) -> 0.29296308 | D23: =D22+((D$40-D$20)/($A$40-$A$20)) -> 0.8260311 | E23: =E22+((E$40-E$20)/($A$40-$A$20)) -> 0.14298512 | F23: =F22+((F$40-F$20)/($A$40-$A$20)) -> 1.4335396 | G23: =G22+((G$40-G$20)/($A$40-$A$20)) -> #VALUE! | H23: =H22+((H$40-H$20)/($A$40-$A$20)) -> 0.19471486 | I23: =I22+((I$40-I$20)/($A$40-$A$20)) -> 0 | ... M23: =M22+((M$40-M$20)/($A$40-$A$20)) -> 8.17056
B24: =B23+((B$40-B$20)/($A$40-$A$20)) -> 4.2088783 | C24: =C23+((C$40-C$20)/($A$40-$A$20)) -> 0.27879363 | D24: =D23+((D$40-D$20)/($A$40-$A$20)) -> 1.1013748 | E24: =E23+((E$40-E$20)/($A$40-$A$20)) -> 0.14756238 | F24: =F23+((F$40-F$20)/($A$40-$A$20)) -> 1.4428428 | G24: =G23+((G$40-G$20)/($A$40-$A$20)) -> #VALUE! | H24: =H23+((H$40-H$20)/($A$40-$A$20)) -> 0.21352735 | I24: =I23+((I$40-I$20)/($A$40-$A$20)) -> 0 | ... M24: =M23+((M$40-M$20)/($A$40-$A$20)) -> 8.2929034
B25: =B24+((B$40-B$20)/($A$40-$A$20)) -> 3.9458234 | C25: =C24+((C$40-C$20)/($A$40-$A$20)) -> 0.26462418 | D25: =D24+((D$40-D$20)/($A$40-$A$20)) -> 1.3767185 | E25: =E24+((E$40-E$20)/($A$40-$A$20)) -> 0.15213964 | F25: =F24+((F$40-F$20)/($A$40-$A$20)) -> 1.4521461 | G25: =G24+((G$40-G$20)/($A$40-$A$20)) -> #VALUE! | H25: =H24+((H$40-H$20)/($A$40-$A$20)) -> 0.23233984 | I25: =I24+((I$40-I$20)/($A$40-$A$20)) -> 0 | ... M25: =M24+((M$40-M$20)/($A$40-$A$20)) -> 8.4152469
B26: =B25+((B$40-B$20)/($A$40-$A$20)) -> 3.6827685 | C26: =C25+((C$40-C$20)/($A$40-$A$20)) -> 0.25045473 | D26: =D25+((D$40-D$20)/($A$40-$A$20)) -> 1.6520622 | E26: =E25+((E$40-E$20)/($A$40-$A$20)) -> 0.15671691 | F26: =F25+((F$40-F$20)/($A$40-$A$20)) -> 1.4614493 | G26: =G25+((G$40-G$20)/($A$40-$A$20)) -> #VALUE! | H26: =H25+((H$40-H$20)/($A$40-$A$20)) -> 0.25115234 | I26: =I25+((I$40-I$20)/($A$40-$A$20)) -> 0 | ... M26: =M25+((M$40-M$20)/($A$40-$A$20)) -> 8.5375904
B27: =B26+((B$40-B$20)/($A$40-$A$20)) -> 3.4197136 | C27: =C26+((C$40-C$20)/($A$40-$A$20)) -> 0.23628527 | D27: =D26+((D$40-D$20)/($A$40-$A$20)) -> 1.9274059 | E27: =E26+((E$40-E$20)/($A$40-$A$20)) -> 0.16129417 | F27: =F26+((F$40-F$20)/($A$40-$A$20)) -> 1.4707525 | G27: =G26+((G$40-G$20)/($A$40-$A$20)) -> #VALUE! | H27: =H26+((H$40-H$20)/($A$40-$A$20)) -> 0.26996483 | I27: =I26+((I$40-I$20)/($A$40-$A$20)) -> 0 | ... M27: =M26+((M$40-M$20)/($A$40-$A$20)) -> 8.6599339
B28: =B27+((B$40-B$20)/($A$40-$A$20)) -> 3.1566587 | C28: =C27+((C$40-C$20)/($A$40-$A$20)) -> 0.22211582 | D28: =D27+((D$40-D$20)/($A$40-$A$20)) -> 2.2027496 | E28: =E27+((E$40-E$20)/($A$40-$A$20)) -> 0.16587143 | F28: =F27+((F$40-F$20)/($A$40-$A$20)) -> 1.4800557 | G28: =G27+((G$40-G$20)/($A$40-$A$20)) -> #VALUE! | H28: =H27+((H$40-H$20)/($A$40-$A$20)) -> 0.28877732 | I28: =I27+((I$40-I$20)/($A$40-$A$20)) -> 0 | ... M28: =M27+((M$40-M$20)/($A$40-$A$20)) -> 8.7822773
B29: =B28+((B$40-B$20)/($A$40-$A$20)) -> 2.8936038 | C29: =C28+((C$40-C$20)/($A$40-$A$20)) -> 0.20794637 | D29: =D28+((D$40-D$20)/($A$40-$A$20)) -> 2.4780933 | E29: =E28+((E$40-E$20)/($A$40-$A$20)) -> 0.1704487 | F29: =F28+((F$40-F$20)/($A$40-$A$20)) -> 1.489359 | G29: =G28+((G$40-G$20)/($A$40-$A$20)) -> #VALUE! | H29: =H28+((H$40-H$20)/($A$40-$A$20)) -> 0.30758981 | I29: =I28+((I$40-I$20)/($A$40-$A$20)) -> 0 | ... M29: =M28+((M$40-M$20)/($A$40-$A$20)) -> 8.9046208
B30: =B29+((B$40-B$20)/($A$40-$A$20)) -> 2.6305489 | C30: =C29+((C$40-C$20)/($A$40-$A$20)) -> 0.19377692 | D30: =D29+((D$40-D$20)/($A$40-$A$20)) -> 2.753437 | E30: =E29+((E$40-E$20)/($A$40-$A$20)) -> 0.17502596 | F30: =F29+((F$40-F$20)/($A$40-$A$20)) -> 1.4986622 | G30: =G29+((G$40-G$20)/($A$40-$A$20)) -> #VALUE! | H30: =H29+((H$40-H$20)/($A$40-$A$20)) -> 0.3264023 | I30: =I29+((I$40-I$20)/($A$40-$A$20)) -> 0 | ... M30: =M29+((M$40-M$20)/($A$40-$A$20)) -> 9.0269643
B31: =B30+((B$40-B$20)/($A$40-$A$20)) -> 2.367494 | C31: =C30+((C$40-C$20)/($A$40-$A$20)) -> 0.17960747 | D31: =D30+((D$40-D$20)/($A$40-$A$20)) -> 3.0287807 | E31: =E30+((E$40-E$20)/($A$40-$A$20)) -> 0.17960322 | F31: =F30+((F$40-F$20)/($A$40-$A$20)) -> 1.5079654 | G31: =G30+((G$40-G$20)/($A$40-$A$20)) -> #VALUE! | H31: =H30+((H$40-H$20)/($A$40-$A$20)) -> 0.34521479 | I31: =I30+((I$40-I$20)/($A$40-$A$20)) -> 0 | ... M31: =M30+((M$40-M$20)/($A$40-$A$20)) -> 9.1493077
B32: =B31+((B$40-B$20)/($A$40-$A$20)) -> 2.1044391 | C32: =C31+((C$40-C$20)/($A$40-$A$20)) -> 0.16543802 | D32: =D31+((D$40-D$20)/($A$40-$A$20)) -> 3.3041244 | E32: =E31+((E$40-E$20)/($A$40-$A$20)) -> 0.18418049 | F32: =F31+((F$40-F$20)/($A$40-$A$20)) -> 1.5172686 | G32: =G31+((G$40-G$20)/($A$40-$A$20)) -> #VALUE! | H32: =H31+((H$40-H$20)/($A$40-$A$20)) -> 0.36402728 | I32: =I31+((I$40-I$20)/($A$40-$A$20)) -> 0 | ... M32: =M31+((M$40-M$20)/($A$40-$A$20)) -> 9.2716512
... B39: =B38+((B$40-B$20)/($A$40-$A$20)) -> 0.26305489 | C39: =C38+((C$40-C$20)/($A$40-$A$20)) -> 0.066251858 | D39: =D38+((D$40-D$20)/($A$40-$A$20)) -> 5.2315303 | E39: =E38+((E$40-E$20)/($A$40-$A$20)) -> 0.21622133 | F39: =F38+((F$40-F$20)/($A$40-$A$20)) -> 1.5823912 | G39: =G38+((G$40-G$20)/($A$40-$A$20)) -> #VALUE! | H39: =H38+((H$40-H$20)/($A$40-$A$20)) -> 0.49571473 | I39: =I38+((I$40-I$20)/($A$40-$A$20)) -> 0 | ... M39: =M38+((M$40-M$20)/($A$40-$A$20)) -> 10.128056
A40: 2050 | B40: ='Waterfall data'!Z21 -> -2.9976022e-15 | C40: ='Waterfall data'!AA21 -> 0.052082407 | D40: ='Waterfall data'!AC20 -> 5.506874 | E40: ='Waterfall data'!AC19 -> 0.22079859 | F40: ='Waterfall data'!AC18 -> 1.5916944 | G40: ='Waterfall data'!AC17 -> 0.36101287 | H40: ='Waterfall data'!AC16 -> 0.51452722 | I40: 0 | J40: ='Waterfall data'!AC14 -> 0.63981376 | K40: ='Waterfall data'!AC13 -> 0.49556426 | L40: ='Waterfall data'!AC12 -> 0.84243964 | M40: =M10+'Waterfall data'!AB11 -> 10.250399

Sheet Stacked bar and box data
A9: Year | B9: Direct CO2 emissions | C9: Indirect CO2 emissions | D9: CCUS | E9: Fossil waste fuels | F9: Recarbonation | G9: Clinker | H9: Electricity | I9: New binders | J9: Cement & binders (incl. new binders) | K9: Concrete | L9: Design & Construction | M9: Societal demand
A10: 2020 | B10: ='Stacked areas data'!B10 -> 4.9135975 | C10: ='Stacked areas data'!C10 -> 0.42043473 | D10: ='Stacked areas data'!D10 -> 0 | E10: ='Stacked areas data'!E10 -> 0 | F10: ='Stacked areas data'!F10 -> 1.2791284 | G10: ='Stacked areas data'!G10 -> 0 | H10: ='Stacked areas data'!H10 -> 0 | I10: ='Stacked areas data'!I10 -> 0 | ... M10: ='Stacked areas data'!M10 -> 6.6131606
A11: 2030 | B11: ='Stacked areas data'!B20 -> 5.2610979 | C11: ='Stacked areas data'!C20 -> 0.33547143 | D11: ='Stacked areas data'!D20 -> 0 | E11: ='Stacked areas data'!E20 -> 0.12925333 | F11: ='Stacked areas data'!F20 -> 1.40563 | G11: ='Stacked areas data'!G20 | H11: ='Stacked areas data'!H20 -> 0.13827739 | I11: ='Stacked areas data'!I20 -> 0 | ... M11: ='Stacked areas data'!M20 -> 7.8035296
A12: 2050 | B12: ='Stacked areas data'!B40 -> -2.9976022e-15 | C12: ='Stacked areas data'!C40 -> 0.052082407 | D12: ='Stacked areas data'!D40 -> 5.506874 | E12: ='Stacked areas data'!E40 -> 0.22079859 | F12: ='Stacked areas data'!F40 -> 1.5916944 | G12: ='Stacked areas data'!G40 -> 0.36101287 | H12: ='Stacked areas data'!H40 -> 0.51452722 | I12: ='Stacked areas data'!I40 -> 0 | ... M12: ='Stacked areas data'!M40 -> 10.250399 | O12: Control value
A13: 2050 savings in % | D13: =D12/$M$12 -> 0.53723509 | E13: =E12/$M$12 -> 0.021540487 | F13: =F12/$M$12 -> 0.15528121 | G13: =G12/$M$12 -> 0.035219397 | H13: =H12/$M$12 -> 0.050195823 | I13: =I12/$M$12 -> 0 | J13: =J12/$M$12 -> 0.062418425 | K13: =K12/$M$12 -> 0.048345851 | L13: =L12/$M$12 -> 0.082186034 | O13: =SUM(D13:L13) -> 0.99242232
A16: Year | B16: Direct CO2 emissions | C16: Indirect CO2 emissions | D16: CCUS | E16: Recarbonation | F16: Clinker (incl. fossil waste fuels) | G16: Electricity | H16: Cement & binders (incl. new binders) | I16: Concrete | J16: Design & Construction | K16: Societal demand
A17: 2020 | B17: =B10 -> 4.9135975 | C17: =C10 -> 0.42043473 | D17: =D10 -> 0 | E17: =F10 -> 1.2791284 | F17: =E10+G10 -> 0 | G17: =H10 -> 0 | H17: =I10+J10 -> 0 | I17: =K10 -> 0 | J17: =L10 -> 0 | K17: =M10 -> 6.6131606
A18: 2030 | B18: =B11 -> 5.2610979 | C18: =C11 -> 0.33547143 | D18: =D11 -> 0 | E18: =F11 -> 1.40563 | F18: =E11+G11 -> #VALUE! | G18: =H11 -> 0.13827739 | H18: =I11+J11 -> 0.17284107 | I18: =K11 -> 0.0072725528 | J18: =L11 -> 0.34450103 | K18: =M11 -> 7.8035296
A19: 2050 | B19: =B12 -> -2.9976022e-15 | C19: =C12 -> 0.052082407 | D19: =D12 -> 5.506874 | E19: =F12 -> 1.5916944 | F19: =E12+G12 -> 0.58181146 | G19: =H12 -> 0.51452722 | H19: =I12+J12 -> 0.63981376 | I19: =K12 -> 0.49556426 | J19: =L12 -> 0.84243964 | K19: =M12 -> 10.250399
A20: 2050 savings in % | D20: =D19/$K$19 -> 0.53723509 | E20: =E19/$K$19 -> 0.15528121 | F20: =F19/$K$19 -> 0.056759884 | G20: =G19/$K$19 -> 0.050195823 | H20: =H19/$K$19 -> 0.062418425 | I20: =I19/$K$19 -> 0.048345851 | J20: =J19/$K$19 -> 0.082186034

Sheet Info Society demand
B1: Information for estimates on future society demand from public sources
B3: It is recommended IEA data is used. IEA regional data groups Asia, Africa & Latin America as rest of World.
B4: Explanation of IEA data, and derivation from Rest of World into regions, is provided below.
B6: Cement tonnage by region. Proxy for societal demand for construction ( assumption of no material subsitution ). (IEA SDS scenario*)
C7: 2020 | D7: 2030 | E7: 2050
C8: IEA* | D8: IEA* | E8: IEA*
B9: China | C9: 2300 | D9: =1970+5.2/100*1970 -> 2072.44 | E9: =1200*15.6/100+1200 -> 1387.2
B10: India | C10: 290 | D10: =560+5.2/100*560 -> 589.12 | E10: =860*15.6/100+860 -> 994.16
B11: North America | C11: 80 | D11: =90+90*5.2/100 -> 94.68 | E11: =100+15.6 -> 115.6
B12: Europe | C12: 170 | D12: =171+171*5.2/100 -> 179.892 | E12: =160*15.6/100+160 -> 184.96
B13: Middle East | C13: 175 | D13: =174+174*5.2/100 -> 183.048 | E13: =170*15.6/100+170 -> 196.52
B14: CIS** | C14: 70 | D14: 87 | E14: 84
B15: Asia** | C15: 466 | D15: 594 | E15: 740
B16: Africa** | C16: 320 | D16: 522 | E16: 923
B17: Latin America** | C17: 175 | D17: 185 | E17: 185
B18: World | C18: 4100 | D18: 5000 | E18: 5000
B19: ** derived from "Rest of World" as explained below
B21: *IEA values provided in personal commuication were for IEA STEPS scenario (i.e. inclusive of 26% reduction due to material efficiency in 2070). To back calculate SDS scenario, this reduction has been removed based on linear reduction over time ( i.e. 5,2% is applied in 2030 and 15,6% in 2050 ).
B25: **For China, India, Middle East, Europe and North America values are estimated by IEA. For the other regions, IEA stated them as 'rest of the world'. To obtain specific values for Asia, Africa, CIS and Latin America, values from Cao et al. for these regions constituting the equivalent of 'rest of the world' in IEA were added together and a ratio of each region can be found. This ratio of Cao et al. is finally used on IEA values and values for each region is obtained. It is be noted that IEA values provided were for IEA STEPS scenario (i.e. inclusive of 26% reduction due to material efficiency in 2070) and to back caclulate SDS scenario regional data, this reduction has been removed using linear potential reduction ( i.e. 5,2% is applied in 2030 and 15,6% in 2050 )."
B32: IEA : IEA regional breakdown data provided in personal communication on November 24th following IEA presentation of ETP 2020 report. Published ETP report does not include regional breakdown
B33: Cao, Z., Myers, R.J., Lupton, R.C. et al. The sponge effect and carbon emission mitigation potentials of the global cement cycle. Nat Commun 11, 3777 (2020).
B34: https://doi.org/10.1038/s41467-020-17583-w | O34: https://interactives.prb.org/2020-wpds/
O35: map of projected population change 2020-2050 for world, regions and coutries (more detailed than table below)
C36: 2020 | E36: 2030 | G36: 2050
C37: IEA | D37: Cao et al. | E37: IEA | F37: Cao et al. | G37: IEA | H37: Cao et al. | J37: IEA | K37: 2020 | L37: 2050 | M37: 2070 | O37: Population | P37: Europe (millions) | Q37: Africa (billions) | R37: Americas (billions) | S37: Asia (billions) | T37: Oceania (millions)
B38: CIS* | C38: =D38/D42*C42 -> 69.830508 | D38: 60 | E38: =F38/F42*E42 -> 87.451349 | F38: 77 | G38: =H38/H42*G42 -> 83.625984 | H38: 77 | J38: Population growth | M38: 0.35 | O38: 2020 | P38: 747 | Q38: 1.3 | R38: 1 | S38: 4.6 | T38: 43
B39: Asia* | C39: =D39/D42*C42 -> 465.53672 | D39: 400 | E39: =F39/F42*E42 -> 593.98774 | F39: 523 | G39: =H39/H42*G42 -> 739.60124 | H39: 681 | J39: Cement demand for building construction | K39: 2 Gt | M39: 2.2 Gt | O39: 2050 | P39: 729 | Q39: 2.6 | R39: 1.2 | S39: 5.3 | T39: 63
B40: Africa* | C40: =D40/D42*C42 -> 320.0565 | D40: 275 | E40: =F40/F42*E42 -> 522.43663 | F40: 460 | G40: =H40/H42*G42 -> 923.14398 | H40: 850 | O40: Difference | P40: -0.02 | Q40: 0.91 | R40: 0.17 | S40: 0.15 | T40: 0.47
B41: Latin America* | C41: =D41/D42*C42 -> 174.57627 | D41: 150 | E41: =F41/F42*E42 -> 185.12428 | F41: 163 | G41: =H41/H42*G42 -> 184.6288 | H41: 170
B42: Reat of World | C42: 1030 | D42: =SUM(D41,D40,D39,D38) -> 885 | E42: 1389 | F42: =SUM(F38,F39,F40,F41) -> 1223 | G42: 1931 | H42: =SUM(H41,H40,H38:H39) -> 1778 | O42: United Nations Population Division (2019), 2019 Revision of World Population Prospects, UN, New York. https://population.un.org/wpp/
O43: graph of population growth until 2100 for all countries and regions/continents
B45: Cao et al. values in the table above: "The scenario (of 9 scenarios ) that is used is "low-moderate scenario" which was selected because it most closely reflected with IEA prediction for worlwide cement production in 2050. (Note that Cao et al chose, following consideration of literature, that a 17% reduction would occur due to material efficiency by 2100 (material efficiency largely reflected efficiency in concrete production and design and construction stages). It is assumed a linear potential reduction from material so a 2% is applied in 2030 and a 6,5% in 2050. Given that the GCCA roadmap model requires societal demand for construction excluding efficiencies measures, the value from Cao et al were multiplied by 100/98 for 2030 and 93,5/100 for 2050 to obtain the table below. " Whilst expressed in tonnes of cement, the percentage change is a proxy for societal demand , given that the efficiency factor has been removed.
B53: The Cao et al graphs for those regions that IEA group as " rest of world" are provided so that GCCA groups have more information to base their own estimates on.
B54: NOTE - Any numerical information from the graphs should be the graphs should be multiplied up to remove the 17% material efficiency embedded within them. ( linear interpolation to be applied 17% by 2100)
B76: NOTE - graph from IEA can be seen below
B77: NOTE - Any numerical information derived from the IEA graphs below should should be multiplied by up to 26% depending on year to obtain SDS scenario - proxy for society construction demand. (linear interpolation to be applied for intervening years).

Sheet Info Regions Countries
E1: Reference | I1: Selection must be made only once on the sheet 'Whole life model'
E2: Region | F2: ='Whole life model'!F2 -> ARGENTINA | I2: North America (Canada/USA) PCA/CAC | L2: Europe (Cembureau, ERMCO, BIBM)
E3: Organisation | F3: ='Whole life model'!F3 -> AFCP | I3: Central + South America (Ficem) | L3: CIS Countries
E4: corresponding author | F4: ='Whole life model'!F4 -> FICEM and AFCP | I4: China (CNBM) | L4: Africa (Dangote)
E5: E-mail contact | F5: ='Whole life model'!F5 -> maria.lefevre@afcp.org.ar | I5: India (GCCA India) | L5: Middle East
E6: Phone contact | F6: ='Whole life model'!F6 -> Phone | I6: Asia (incl. Japan, S.Korea, SE Asia, Oceania, excl. China and India)
B7: ='Whole life model'!B7 -> GCCA Roadmap Template | D7: ='Whole life model'!D7 -> Version 202, 19.07.2022, ECRA | E7: Reference year
B8: North America | C8: Central + South America | D8: China | E8: India | F8: Asia (excl. China and India) | G8: Europe | H8: CIS | I8: Africa | J8: Middle East
B9: USA | C9: FICEM | F9: Afghanistan | G9: Cembureau (EU28) | H9: Armenia | I9: Algeria | J9: Bahrain
B10: Canada | C10: Argentina | F10: Bangladesh | G10: Austria | H10: Azerbaijan | I10: Angola | J10: Irak
C11: Barbados | F11: Bhutan | G11: Belgium | H11: Belarus | I11: Benin | J11: Iran
C12: Brazil | F12: Brunei | G12: Bulgaria | H12: Kazakhstan | I12: Botswana | J12: Israel
C13: Bolivia | F13: Cambodia | G13: Croatia | H13: Kyrgyzstan | I13: Burkina Faso | J13: Jordan
C14: Chile | F14: Indonesia | G14: Czech Republic | H14: Moldova | I14: Burundi | J14: Kuwait
C15: Colombia | F15: Japan | G15: Denmark | H15: Russia | I15: Cabo Verde | J15: Lebanon
C16: Costa Rica | F16: Laos | G16: Estonia | H16: Tajikistan | I16: Cameroon | J16: Oman
C17: Cuba | F17: Malaysia | G17: Finland | H17: Turkmenistan | I17: Central African Republic (CAR) | J17: Palestine
C18: Ecuador | F18: Maldives | G18: France | H18: Uzbekistan | I18: Chad | J18: Qatar
C19: El salvador | F19: Mongolia | G19: Germany | H19: Ukraine | I19: Comoros | J19: Saudi Arabia
C20: Guatemala | F20: Myanmar | G20: Greece | I20: Congo, Democratic Republic of the | J20: Syria
C21: Guateloupe | F21: Nepal | G21: Hungary | I21: Congo, Republic of the | J21: United Arab Emirates
C22: Martinique | F22: North Korea | G22: Ireland | I22: Cote d'Ivoire | J22: Yemen
C23: French Guiana | F23: Pakistan | G23: Italy | I23: Djibouti
C24: Haiti | F24: Philippines | G24: Latvia | I24: Egypt
C25: Honduras | F25: Singapore | G25: Lithuania | I25: Equatorial Guinea
C26: Jamaica | F26: South Korea | G26: Luxembourg | I26: Eritrea
C27: Mexico | F27: Sri Lanka | G27: Netherlands | I27: Eswatini
C28: Nicaragua | F28: Taiwan | G28: Norway | I28: Ethiopia
C29: Panama | F29: Thailand | G29: Poland | I29: Gabon
C30: Paraguay | F30: Timor-Leste | G30: Romania | I30: Gambia
C31: Peru | F31: Vietnam | G31: Serbia | I31: Ghana
C32: Puerto Rico | F32: Oceania | G32: Slovenia | I32: Guinea
C33: Dominican Republic | F33: Australia | G33: Spain | I33: Guinea-Bissau
C34: Suriname | F34: Fiji | G34: Sweden | I34: Kenya
... C42: Saint-Martin | F42: Samoa | G42: Bosnia and Herzegovina | I42: Mauritius
F43: Solomon Islands | G43: Georgia | I43: Morocco
F44: Tonga | G44: Kosovo | I44: Mozambique
F45: Tuvalu | G45: Liechtenstein | I45: Namibia
F46: Vanuatu | G46: Macedonia | I46: Niger
G47: Malta | I47: Nigeria
G48: Monaco | I48: Rwanda
G49: Montenegro | I49: Sao Tome and Principe
G50: San Marino | I50: Senegal
G51: Slovakia | I51: Seychelles
G52: Vatican City | I52: Sierra Leone
G53: Cyprus | I53: Somalia
I54: South Africa
G55: Rest of Europe represents 3,5% of all Europe population | I55: South Sudan
I56: Sudan
I57: Tanzania
I58: Togo
I59: Tunisia
I60: Uganda
I61: Zambia
I62: Zimbabwe

Sheet Info Clinker Fuel EF
A1: Additonal information on default values according to IPCC Guidelines and GCCA CO2 Protocol
A2: GCCA Fuel Category | C2: IPCC default | D2: GCCA CO2 Protocol default | E2: GCCA CO2 Protocol default
C3: kg CO2/GJ | D3: kg CO2/GJ | E3: % biomass
A4: Fossil fuels
B5: coal + anthracite + waste coal | C5: 96
B6: petrol coke | D6: 92.8
B7: (ultra) heavy fuel | C7: 77.4
B8: diesel oil | C8: 74.1
B9: natural gas (dry) | C9: 56.1
B10: oil shale | C10: 107
B11: lignite | C11: 101
B12: gasoline | C12: 69.3
A13: Alternative fossil fuels
B14: waste oil | D14: 74
B15: tyres | D15: 85 | E15: 0.27
B16: plastics | D16: 75
B17: solvents | D17: 74
B18: impregnated saw dust | D18: 75
B19: mixed industrial waste | D19: 83
B20: other fossil based wastes | D20: 80
A21: Biomass fuels
B22: dried sewage sludge | D22: 110
B23: wood, non impregnated saw dust | D23: 110
B24: paper, carton | D24: 110
B25: animal meal | D25: 89
B26: animal bone meal | D26: 89
B27: animal fat | D27: 89
B28: agricultural, organic, diaper waste, charcoal | D28: 110
B29: other biomass | D29: 110
A31: see additional default valuesin the GCCA Internet Manual of the CO2 Protocol V3.1:
A32: https://www.cement-co2-protocol.org/en/#Internet_Manual/constants.htm

Sheet Info Recarbonation
A1: Info for a refined estimate of Recarbonation based on choice of IVL Study Tier 1 | I1: README | J1: Example
A2: Default value for Recarbonation
A3: Product life cycle partial recarbonation according to IVL study (conservative estimate in relation to process emissions) | E3: kg CO2/kg calcination CO2 | F3: 0.2 | I3: Only CO2 from carbonation in the use stage is taken into account here for an conservative estimate (20% acc. to IVL study)
A4: Different value for Recarbonation, chosen for the region
A5: Product life cycle partial recarbonation | E5: kg CO2/kg calcination CO2 | I5: If you do not agree with the default value of 20 % please give own value
A6: Reason for choosing different value
A7: Study used | C7: Short description for chosen value, e.g. calculation
I8: Please give information on the studies used to define own value and short information on e.g. calculation method
I9: Please give information on the studies used to define own value and short information on e.g. calculation method
I10: Please give information on the studies used to define own value and short information on e.g. calculation method
A13: Example for study which can be used to define a value different from 20 %
A14: Reference and link to IVL Study:
A15: R. Andersson, H. Stripple, T. Gustafsson, C. Ljungkrantz, Carbonation as a method to improve climate performance for cement based material, Cement and Concrete Research 124 (2019)
A16: https://doi.org/10.1016/j.cemconres.2019.105819
A18: User can choose option i or ii in column A based on extent of use of mortar
A19: User can choose column E, F, G, H depending on what volumes are known
A21: Tabular summary of IVL Study Tier 1 | D21: Unit | E21: Neither volume at end-of-life or seconday use are known | F21: Volume at end-of-life is known but not for secondary use | G21: Volume for secondary use is known but not at end-of-life | H21: Both volume are known
A22: i | B22: If mortar < 10% of cement consumption | F22: 10 kg CO2/m3 of concrete recycled | G22: 10 kg CO2/m3 of concrete | H22: 10 kg CO2/m3 of concrete recycled + 10 kg CO2/m3 of concrete | I22: The annual CO2 uptake can be estimated as sum of a) 20% of the CO2 from calcination in the use stage, b) 2% of the emissions from calcination in the end-of life stage c) 1% of the emissions from calcination in the secondary use. ALTERNATIVELY, if the amount of concrete processed in a recycling plant at the end-of-life stage is known, the 2% estimation for the uptake in the end-of-life stage can be replaced by 10 kg CO2/m³ concrete. Similarly, if the amount of crushed concrete entering the secondary life as an unbound material is known, the 1% estimation for the uptake in the secondary use can be replaced by 10 kg CO2/m³ concrete. The total of the CO2-uptake is either E23 or the sum of F22 and F23, or the sum of G22 and G23, or the sum of H22 and H23. | J22: Example: in a given country, it is known that the annual amout of concrete processed in recycling plants totals 10 mio m³. The amount of concrete entering the secondary use as unbound material is not known. It is further known that 15% of the cement consumption is used in mortar for rendering applications. Use of the spreadsheet: enter "15%" in cell C25. As the concrete volume processed in recycling plants is known, but not the amount entering the secondary life as unbound aggregates, column F should be considered. The total annual CO2-uptake in the use, end-of-life and secondary use stages can then be calculated as 26,8% (cell F25) of the emissions from calcination plus 10 mio m³ x 10 kg CO2/m³.
D23: Fraction of process CO2 emissions, kg CO2/kg calcination CO2 | E23: =0.2+0.02+0.01 -> 0.23 | F23: =0.2 + 0.01 -> 0.21 | G23: =0.2 +0.02 -> 0.22 | H23: =0.2 -> 0.2
A24: ii | B24: if mortar > 10% and < 30% of cement consumption | C24: cement going to mortar in % | F24: 10 kg CO2/m3 of concrete recycled | G24: 10 kg CO2/m3 of concrete | H24: 10 kg CO2/m3 of concrete recycled + 10 kg CO2/m3 of concrete | I24: If the cement used in mortar for rendering application amounts to >10% but < 30% of the total cement consumption, the percentage (if known) should be entered in cell C9. The uptake in the use stage is then estimated as 20%+1,15%*(C9-10%). For the calculation of the end-of life stage and the secondary use stage the same rules as described above apply. Consequently, according to this consideration, the total of the CO2-uptake is either E25 or the sum of F24 and F25, or the sum of G24 and G25, or the sum of H24 and H25.
C25: 0.15 | D25: Fraction of process CO2 emissions, kg CO2/kg calcination CO2 | E25: =0.2 + 0.0115*($C$25*100 - 10) + 0.01 + 0.02 -> 0.2875 | F25: =0.2 + 0.0115*($C$25*100 - 10) +0.01 -> 0.2675 | G25: =0.2 + 0.0115*($C$25*100 - 10)+0.02 -> 0.2775 | H25: =0.2 + 0.0115*($C$25*100 - 10) -> 0.2575

Sheet Info Template versions
B7: ='Whole life model'!B7 -> GCCA Roadmap Template | D7: ='Whole life model'!D7 -> Version 202, 19.07.2022, ECRA
B8: Version | C8: Date | D8: Description | E8: Author | F8: Amendments, corrections
A9: v | B9: 100 | C9: 44154 | D9: First version used in regional workshops | E9: ECRA | F9: GCCA agreed version for 1st round of workshops
A10: v | B10: 101 & 102 | C10: 03.12.2020, 7.12.2020 | D10: Minor amendments and corrections | E10: ECRA | F10: Minor amendment of info on electricity from waste heat recovery at the bottom of sheet 1.2, minor correction of unit references in sheet 4.1 and 1.2, clarification on heat consumption for 1.2 clinker EF, Info sheets on Regions Countries (Central + South America incl. Brazil) and on Template versions, line reference in lin 1.4.1 corrected, amended column heading "(Concrete or mortar from) Bagged Cement", line 3.1.5 described as "Less cement wastaed through shift from bagged cement to readymix or precast", Amendment of lines 1.2.3.9. to 1.2.3.12 for imported clinker CO2 emission factor calculated with GCCA Cement CO2 and Energy Protocol default emission factor of 0,865 kg CO2/kg clinker
A11: v | B11: 103 | C11: 44182 | D11: Minor amendments and corrections | E11: ECRA | F11: Amendment of Info Society demand
